Workbook
Name BSAcctIDs: Drivers!$L$68:$L$103
Name BSAccts: Drivers!$D$68:$D$97
Name BSAcctType: Drivers!$K$68:$K$97
Name BSDriverAssumptions: Drivers!$F$68:$F$97
Name BSDrivers: Drivers!$E$68:$E$97
Name BSSections: Drivers!$G$68:$G$103
Name BSSectionsCF: Drivers!$J$68:$J$103
Name BSSummarys: Drivers!$H$68:$H$103
Name BSSummarysCF: Drivers!$I$68:$I$103
Name Company_Name: "Model Wiz Demo *"
Name dataGLBS: 'Data Summary'!$N$77:$AW$104
Name dataGLBSAcctIDs: 'Data Summary'!$J$77:$J$104
Name dataGLBSAccts: 'Data Summary'!$D$77:$D$104
Name dataGLBSCF: 'Data Summary'!$M$77:$AW$104
Name dataGLBSSections: 'Data Summary'!$E$77:$E$104
Name dataGLBSSummarys: 'Data Summary'!$F$77:$F$104
Name dataGLBSSummarysCF: 'Data Summary'!$I$77:$I$104
Name dataGLPL: 'Data Summary'!$N$42:$AW$74
Name dataGLPLAcctIDs: 'Data Summary'!$J$42:$J$74
Name dataGLPLAccts: 'Data Summary'!$D$42:$D$74
Name dataGLPLSections: 'Data Summary'!$E$42:$E$74
Name dataGLPLSummarys: 'Data Summary'!$F$42:$F$74
Name dataSummaryBS: 'Data Summary'!$N$28:$AW$38
Name dataSummaryBSAcctIDs: 'Data Summary'!$J$28:$J$38
Name dataSummaryBSAccts: 'Data Summary'!$D$28:$D$38
Name dataSummaryBSCF: 'Data Summary'!$M$28:$AW$38
Name dataSummaryBSSections: 'Data Summary'!$E$28:$E$38
Name dataSummaryBSSummarys: 'Data Summary'!$F$28:$F$38
Name dataSummaryPL: 'Data Summary'!$N$12:$AW$25
Name dataSummaryPLAcctIDs: 'Data Summary'!$J$12:$J$26
Name dataSummaryPLAccts: 'Data Summary'!$D$12:$D$26
Name dataSummaryPLSections: 'Data Summary'!$E$12:$E$25
Name dataSummaryPLSummarys: 'Data Summary'!$F$12:$F$25
Name Drivers_accountId: Drivers!$L:$L
Name Drivers_accountName: Drivers!$D:$D
Name Drivers_cashFlowSection: Drivers!$J:$J
Name Drivers_Driver: Drivers!$E:$E
Name Drivers_driverAccountType: Drivers!$K:$K
Name Drivers_DriverAssumption: Drivers!$F:$F
Name Drivers_driversSection: Drivers!$G:$G
Name Drivers_summaryGrouping: Drivers!$H:$H
Name DriversOwnersEquity: Drivers!$AI$97:$BS$103
Name endDates: 'Data Summary'!$N$5:$AW$5
Name endDatesCF: 'Data Summary'!$M$5:$AW$5
Name Error_Check: 'Error Check'!$D$12
Name Error_Range: 'Data Summary'!$M$107:$AW$124
Name Error_Range: Drivers!$P$106:$BS$116
Name Formats: _xlfn.ANCHORARRAY(Lists!$C$6)
Name LatestMonthOfActuals: 45930
Name Periods: _xlfn.ANCHORARRAY(Lists!$B$6)
Name PLAcctIDs: Drivers!$L$10:$L$66
Name PLAccts: Drivers!$D$10:$D$66
Name PLAcctType: Drivers!$K$10:$K$66
Name PLDriverAssumptions: Drivers!$F$10:$F$66
Name PLDrivers: Drivers!$E$10:$E$66
Name PLSections: Drivers!$G$10:$G$66
Name PLSummarys: Drivers!$H$10:$H$66
Name PLSummarysCF: Drivers!$J$10:$J$66
Name startDates: 'Data Summary'!$N$4:$AW$4
Name startDatesCF: 'Data Summary'!$M$4:$AW$4

Sheet Financial Statements
C2: Nimbus Cloud Solutions
C4: FINANCIAL STATEMENTS | E4: Last Quarter
E5: =B93 -> Q2 2025 | G5: ="vs. "&B97 -> vs. Q1 2025 | K5: ="vs. "&B100 -> vs. Q2 2024
E6: Selected Period | G6: Prior Period | H6: $ Var | I6: % Var | K6: Prior Year | L6: $ Var | M6: % Var
B8: PROFIT & LOSS
C10: Revenue | E10: {=SUMPRODUCT(('Data Summary'!$M$8:$AW$8>=$B$91)*('Data Summary'!$M$8:$AW$8<=$B$92)*'Data Summary'!M13:AW13)} -> 224373.97 | G10: {=SUMPRODUCT(('Data Summary'!$M$8:$AW$8>=$B$95)*('Data Summary'!$M$8:$AW$8<=$B$96)*'Data Summary'!M13:AW13)} -> 186307.22 | H10: =E10-G10 -> 38066.75 | I10: =IFERROR(E10/G10-1,0) -> 0.20432246 | K10: {=SUMPRODUCT(('Data Summary'!$M$8:$AW$8>=$B$98)*('Data Summary'!$M$8:$AW$8<=$B$99)*'Data Summary'!M13:AW13)} -> 143829 | L10: =E10-K10 -> 80544.97 | M10: =IFERROR(E10/K10-1,0) -> 0.56000508
C11: Total Revenue | E11: =E10 -> 224373.97 | G11: =G10 -> 186307.22 | H11: =E11-G11 -> 38066.75 | I11: =IFERROR(E11/G11-1,0) -> 0.20432246 | K11: =K10 -> 143829 | L11: =E11-K11 -> 80544.97 | M11: =IFERROR(E11/K11-1,0) -> 0.56000508
C13: Cost of Goods Sold | E13: {=SUMPRODUCT(('Data Summary'!$M$8:$AW$8>=$B$91)*('Data Summary'!$M$8:$AW$8<=$B$92)*('Data Summary'!M15:AW15+'Data Summary'!M16:AW16))} -> 20775.48 | G13: {=SUMPRODUCT(('Data Summary'!$M$8:$AW$8>=$B$95)*('Data Summary'!$M$8:$AW$8<=$B$96)*('Data Summary'!M15:AW15+'Data Summary'!M16:AW16))} -> 17685.42 | H13: =E13-G13 -> 3090.06 | I13: =IFERROR(E13/G13-1,0) -> 0.17472359 | K13: {=SUMPRODUCT(('Data Summary'!$M$8:$AW$8>=$B$98)*('Data Summary'!$M$8:$AW$8<=$B$99)*('Data Summary'!M15:AW15+'Data Summary'!M16:AW16))} -> 12551.5 | L13: =E13-K13 -> 8223.98 | M13: =IFERROR(E13/K13-1,0) -> 0.6552189
C14: Gross Profit | E14: =E11-E13 -> 203598.49 | G14: =G11-G13 -> 168621.8 | H14: =E14-G14 -> 34976.69 | I14: =IFERROR(E14/G14-1,0) -> 0.20742686 | K14: =K11-K13 -> 131277.5 | L14: =E14-K14 -> 72320.99 | M14: =IFERROR(E14/K14-1,0) -> 0.55090164
C16: Marketing & Advertising | E16: {=SUMPRODUCT(('Data Summary'!$M$8:$AW$8>=$B$91)*('Data Summary'!$M$8:$AW$8<=$B$92)*'Data Summary'!M17:AW17)} -> 226320.72 | G16: {=SUMPRODUCT(('Data Summary'!$M$8:$AW$8>=$B$95)*('Data Summary'!$M$8:$AW$8<=$B$96)*'Data Summary'!M17:AW17)} -> 195505.87 | H16: =E16-G16 -> 30814.85 | I16: =IFERROR(E16/G16-1,0) -> 0.15761598 | K16: {=SUMPRODUCT(('Data Summary'!$M$8:$AW$8>=$B$98)*('Data Summary'!$M$8:$AW$8<=$B$99)*'Data Summary'!M17:AW17)} -> 125723 | L16: =E16-K16 -> 100597.72 | M16: =IFERROR(E16/K16-1,0) -> 0.80015367
C17: Office & Other G&A | E17: {=SUMPRODUCT(('Data Summary'!$M$8:$AW$8>=$B$91)*('Data Summary'!$M$8:$AW$8<=$B$92)*'Data Summary'!M18:AW18)} -> 224926.82 | G17: {=SUMPRODUCT(('Data Summary'!$M$8:$AW$8>=$B$95)*('Data Summary'!$M$8:$AW$8<=$B$96)*'Data Summary'!M18:AW18)} -> 193436.37 | H17: =E17-G17 -> 31490.45 | I17: =IFERROR(E17/G17-1,0) -> 0.16279488 | K17: {=SUMPRODUCT(('Data Summary'!$M$8:$AW$8>=$B$98)*('Data Summary'!$M$8:$AW$8<=$B$99)*'Data Summary'!M18:AW18)} -> 132220.5 | L17: =E17-K17 -> 92706.32 | M17: =IFERROR(E17/K17-1,0) -> 0.70114937
C18: Payroll | E18: {=SUMPRODUCT(('Data Summary'!$M$8:$AW$8>=$B$91)*('Data Summary'!$M$8:$AW$8<=$B$92)*'Data Summary'!M19:AW19)} -> 201582.84 | G18: {=SUMPRODUCT(('Data Summary'!$M$8:$AW$8>=$B$95)*('Data Summary'!$M$8:$AW$8<=$B$96)*'Data Summary'!M19:AW19)} -> 174134.87 | H18: =E18-G18 -> 27447.97 | I18: =IFERROR(E18/G18-1,0) -> 0.15762478 | K18: {=SUMPRODUCT(('Data Summary'!$M$8:$AW$8>=$B$98)*('Data Summary'!$M$8:$AW$8<=$B$99)*'Data Summary'!M19:AW19)} -> 108961 | L18: =E18-K18 -> 92621.84 | M18: =IFERROR(E18/K18-1,0) -> 0.8500458
C19: Professional Services | E19: {=SUMPRODUCT(('Data Summary'!$M$8:$AW$8>=$B$91)*('Data Summary'!$M$8:$AW$8<=$B$92)*'Data Summary'!M20:AW20)} -> 72600 | G19: {=SUMPRODUCT(('Data Summary'!$M$8:$AW$8>=$B$95)*('Data Summary'!$M$8:$AW$8<=$B$96)*'Data Summary'!M20:AW20)} -> 62714.72 | H19: =E19-G19 -> 9885.28 | I19: =IFERROR(E19/G19-1,0) -> 0.15762296 | K19: {=SUMPRODUCT(('Data Summary'!$M$8:$AW$8>=$B$98)*('Data Summary'!$M$8:$AW$8<=$B$99)*'Data Summary'!M20:AW20)} -> 39437 | L19: =E19-K19 -> 33163 | M19: =IFERROR(E19/K19-1,0) -> 0.84091082
C20: Travel & Entertainment | E20: {=SUMPRODUCT(('Data Summary'!$M$8:$AW$8>=$B$91)*('Data Summary'!$M$8:$AW$8<=$B$92)*'Data Summary'!M21:AW21)} -> 24456.9 | G20: {=SUMPRODUCT(('Data Summary'!$M$8:$AW$8>=$B$95)*('Data Summary'!$M$8:$AW$8<=$B$96)*'Data Summary'!M21:AW21)} -> 21125.46 | H20: =E20-G20 -> 3331.44 | I20: =IFERROR(E20/G20-1,0) -> 0.15769787 | K20: {=SUMPRODUCT(('Data Summary'!$M$8:$AW$8>=$B$98)*('Data Summary'!$M$8:$AW$8<=$B$99)*'Data Summary'!M21:AW21)} -> 13593 | L20: =E20-K20 -> 10863.9 | M20: =IFERROR(E20/K20-1,0) -> 0.79922754
C21: Total Operating Expenses | E21: =SUM(E16:E20) -> 749887.28 | G21: =SUM(G16:G20) -> 646917.29 | H21: =E21-G21 -> 102969.99 | I21: =IFERROR(E21/G21-1,0) -> 0.15917025 | K21: =SUM(K16:K20) -> 419934.5 | L21: =E21-K21 -> 329952.78 | M21: =IFERROR(E21/K21-1,0) -> 0.78572439
C23: Operating Income (Loss) | E23: =E14-E21 -> -546288.79 | G23: =G14-G21 -> -478295.49 | H23: =E23-G23 -> -67993.3 | I23: =IFERROR(E23/G23-1,0) -> 0.14215752 | K23: =K14-K21 -> -288657 | L23: =E23-K23 -> -257631.79 | M23: =IFERROR(E23/K23-1,0) -> 0.89251877
C25: Other Income | E25: {=SUMPRODUCT(('Data Summary'!$M$8:$AW$8>=$B$91)*('Data Summary'!$M$8:$AW$8<=$B$92)*'Data Summary'!M22:AW22)} -> 0 | G25: {=SUMPRODUCT(('Data Summary'!$M$8:$AW$8>=$B$95)*('Data Summary'!$M$8:$AW$8<=$B$96)*'Data Summary'!M22:AW22)} -> 0 | H25: =E25-G25 -> 0 | I25: =IFERROR(E25/G25-1,0) -> 0 | K25: {=SUMPRODUCT(('Data Summary'!$M$8:$AW$8>=$B$98)*('Data Summary'!$M$8:$AW$8<=$B$99)*'Data Summary'!M22:AW22)} -> 0 | L25: =E25-K25 -> 0 | M25: =IFERROR(E25/K25-1,0) -> 0
C26: Depreciation & Amortization | E26: {=SUMPRODUCT(('Data Summary'!$M$8:$AW$8>=$B$91)*('Data Summary'!$M$8:$AW$8<=$B$92)*'Data Summary'!M23:AW23)} -> 0 | G26: {=SUMPRODUCT(('Data Summary'!$M$8:$AW$8>=$B$95)*('Data Summary'!$M$8:$AW$8<=$B$96)*'Data Summary'!M23:AW23)} -> 0 | H26: =E26-G26 -> 0 | I26: =IFERROR(E26/G26-1,0) -> 0 | K26: {=SUMPRODUCT(('Data Summary'!$M$8:$AW$8>=$B$98)*('Data Summary'!$M$8:$AW$8<=$B$99)*'Data Summary'!M23:AW23)} -> 0 | L26: =E26-K26 -> 0 | M26: =IFERROR(E26/K26-1,0) -> 0
C27: Other Expenses | E27: {=SUMPRODUCT(('Data Summary'!$M$8:$AW$8>=$B$91)*('Data Summary'!$M$8:$AW$8<=$B$92)*('Data Summary'!M24:AW24+'Data Summary'!M25:AW25))} -> 64486.74 | G27: {=SUMPRODUCT(('Data Summary'!$M$8:$AW$8>=$B$95)*('Data Summary'!$M$8:$AW$8<=$B$96)*('Data Summary'!M24:AW24+'Data Summary'!M25:AW25))} -> 64486.74 | H27: =E27-G27 -> 0 | I27: =IFERROR(E27/G27-1,0) -> -1.110223e-16 | K27: {=SUMPRODUCT(('Data Summary'!$M$8:$AW$8>=$B$98)*('Data Summary'!$M$8:$AW$8<=$B$99)*('Data Summary'!M24:AW24+'Data Summary'!M25:AW25))} -> 64488 | L27: =E27-K27 -> -1.26 | M27: =IFERROR(E27/K27-1,0) -> -1.9538519e-05
C29: Net Income (Loss) | E29: =E23+E25-E26-E27 -> -610775.53 | G29: =G23+G25-G26-G27 -> -542782.23 | H29: =E29-G29 -> -67993.3 | I29: =IFERROR(E29/G29-1,0) -> 0.1252681 | K29: =K23+K25-K26-K27 -> -353145 | L29: =E29-K29 -> -257630.53 | M29: =IFERROR(E29/K29-1,0) -> 0.72953186
B32: BALANCE SHEET
C34: Assets
C35: Cash | E35: =INDEX('Data Summary'!M29:AW29,MATCH($B$92,'Data Summary'!$M$8:$AW$8,0)) -> 1594040.1 | G35: =INDEX('Data Summary'!M29:AW29,MATCH($B$96,'Data Summary'!$M$8:$AW$8,0)) -> 2207358.5 | H35: =E35-G35 -> -613318.33 | I35: =IFERROR(E35/G35-1,0) -> -0.27785171 | K35: =INDEX('Data Summary'!M29:AW29,MATCH($B$99,'Data Summary'!$M$8:$AW$8,0)) -> 3656851.5 | L35: =E35-K35 -> -2062811.4 | M35: =IFERROR(E35/K35-1,0) -> -0.56409492
C36: Accounts Receivable | E36: =INDEX('Data Summary'!M28:AW28,MATCH($B$92,'Data Summary'!$M$8:$AW$8,0)) -> 69302.55 | G36: =INDEX('Data Summary'!M28:AW28,MATCH($B$96,'Data Summary'!$M$8:$AW$8,0)) -> 56307.77 | H36: =E36-G36 -> 12994.78 | I36: =IFERROR(E36/G36-1,0) -> 0.23078129 | K36: =INDEX('Data Summary'!M28:AW28,MATCH($B$99,'Data Summary'!$M$8:$AW$8,0)) -> 44983 | L36: =E36-K36 -> 24319.55 | M36: =IFERROR(E36/K36-1,0) -> 0.54063869
C37: Current Assets | E37: =INDEX('Data Summary'!M30:AW30,MATCH($B$92,'Data Summary'!$M$8:$AW$8,0)) -> 25819.5 | G37: =INDEX('Data Summary'!M30:AW30,MATCH($B$96,'Data Summary'!$M$8:$AW$8,0)) -> 26119.5 | H37: =E37-G37 -> -300 | I37: =IFERROR(E37/G37-1,0) -> -0.011485672 | K37: =INDEX('Data Summary'!M30:AW30,MATCH($B$99,'Data Summary'!$M$8:$AW$8,0)) -> 26119.5 | L37: =E37-K37 -> -300 | M37: =IFERROR(E37/K37-1,0) -> -0.011485672
C38: Fixed Assets | E38: =INDEX('Data Summary'!M31:AW31,MATCH($B$92,'Data Summary'!$M$8:$AW$8,0)) -> 48553.54 | G38: =INDEX('Data Summary'!M31:AW31,MATCH($B$96,'Data Summary'!$M$8:$AW$8,0)) -> 57705.52 | H38: =E38-G38 -> -9151.98 | I38: =IFERROR(E38/G38-1,0) -> -0.158598 | K38: =INDEX('Data Summary'!M31:AW31,MATCH($B$99,'Data Summary'!$M$8:$AW$8,0)) -> 85163 | L38: =E38-K38 -> -36609.46 | M38: =IFERROR(E38/K38-1,0) -> -0.42987518
C39: Other Current Assets | E39: =INDEX('Data Summary'!M32:AW32,MATCH($B$92,'Data Summary'!$M$8:$AW$8,0)) -> 0 | G39: =INDEX('Data Summary'!M32:AW32,MATCH($B$96,'Data Summary'!$M$8:$AW$8,0)) -> 0 | H39: =E39-G39 -> 0 | I39: =IFERROR(E39/G39-1,0) -> 0 | K39: =INDEX('Data Summary'!M32:AW32,MATCH($B$99,'Data Summary'!$M$8:$AW$8,0)) -> 0 | L39: =E39-K39 -> 0 | M39: =IFERROR(E39/K39-1,0) -> 0
C40: Total Assets | E40: =SUM(E35:E39) -> 1737715.7 | G40: =SUM(G35:G39) -> 2347491.3 | H40: =E40-G40 -> -609775.53 | I40: =IFERROR(E40/G40-1,0) -> -0.25975625 | K40: =SUM(K35:K39) -> 3813117 | L40: =E40-K40 -> -2075401.3 | M40: =IFERROR(E40/K40-1,0) -> -0.54427946
H41: =E41-G41 -> 0 | I41: =IFERROR(E41/G41-1,0) -> 0 | L41: =E41-K41 -> 0 | M41: =IFERROR(E41/K41-1,0) -> 0
C42: Liabilities | H42: =E42-G42 -> 0 | I42: =IFERROR(E42/G42-1,0) -> 0 | L42: =E42-K42 -> 0 | M42: =IFERROR(E42/K42-1,0) -> 0
C43: Accounts Payable | E43: =INDEX('Data Summary'!M33:AW33,MATCH($B$92,'Data Summary'!$M$8:$AW$8,0)) -> 56349.5 | G43: =INDEX('Data Summary'!M33:AW33,MATCH($B$96,'Data Summary'!$M$8:$AW$8,0)) -> 55349.5 | H43: =E43-G43 -> 1000 | I43: =IFERROR(E43/G43-1,0) -> 0.018067011 | K43: =INDEX('Data Summary'!M33:AW33,MATCH($B$99,'Data Summary'!$M$8:$AW$8,0)) -> 55349.5 | L43: =E43-K43 -> 1000 | M43: =IFERROR(E43/K43-1,0) -> 0.018067011
C44: Current Liabilities | E44: =INDEX('Data Summary'!M34:AW34,MATCH($B$92,'Data Summary'!$M$8:$AW$8,0)) -> -4942 | G44: =INDEX('Data Summary'!M34:AW34,MATCH($B$96,'Data Summary'!$M$8:$AW$8,0)) -> -4942 | H44: =E44-G44 -> 0 | I44: =IFERROR(E44/G44-1,0) -> 0 | K44: =INDEX('Data Summary'!M34:AW34,MATCH($B$99,'Data Summary'!$M$8:$AW$8,0)) -> -4942 | L44: =E44-K44 -> 0 | M44: =IFERROR(E44/K44-1,0) -> 0
C45: Debt | E45: =INDEX('Data Summary'!M35:AW35,MATCH($B$92,'Data Summary'!$M$8:$AW$8,0)) -> 1530000 | G45: =INDEX('Data Summary'!M35:AW35,MATCH($B$96,'Data Summary'!$M$8:$AW$8,0)) -> 1530000 | H45: =E45-G45 -> 0 | I45: =IFERROR(E45/G45-1,0) -> 0 | K45: =INDEX('Data Summary'!M35:AW35,MATCH($B$99,'Data Summary'!$M$8:$AW$8,0)) -> 1530000 | L45: =E45-K45 -> 0 | M45: =IFERROR(E45/K45-1,0) -> 0
C46: Deferred Revenue | E46: =INDEX('Data Summary'!M36:AW36,MATCH($B$92,'Data Summary'!$M$8:$AW$8,0)) -> 23270 | G46: =INDEX('Data Summary'!M36:AW36,MATCH($B$96,'Data Summary'!$M$8:$AW$8,0)) -> 23270 | H46: =E46-G46 -> 0 | I46: =IFERROR(E46/G46-1,0) -> 0 | K46: =INDEX('Data Summary'!M36:AW36,MATCH($B$99,'Data Summary'!$M$8:$AW$8,0)) -> 23270 | L46: =E46-K46 -> 0 | M46: =IFERROR(E46/K46-1,0) -> 0
C47: Total Liabilities | E47: =SUM(E43:E46) -> 1604677.5 | G47: =SUM(G43:G46) -> 1603677.5 | H47: =E47-G47 -> 1000 | I47: =IFERROR(E47/G47-1,0) -> 0.00062356677 | K47: =SUM(K43:K46) -> 1603677.5 | L47: =E47-K47 -> 1000 | M47: =IFERROR(E47/K47-1,0) -> 0.00062356677
H48: =E48-G48 -> 0 | I48: =IFERROR(E48/G48-1,0) -> 0 | L48: =E48-K48 -> 0 | M48: =IFERROR(E48/K48-1,0) -> 0
C49: Equity | H49: =E49-G49 -> 0 | I49: =IFERROR(E49/G49-1,0) -> 0 | L49: =E49-K49 -> 0 | M49: =IFERROR(E49/K49-1,0) -> 0
C50: Contributed Capital | E50: =INDEX('Data Summary'!M37:AW37,MATCH($B$92,'Data Summary'!$M$8:$AW$8,0)) -> 3500000 | G50: =INDEX('Data Summary'!M37:AW37,MATCH($B$96,'Data Summary'!$M$8:$AW$8,0)) -> 3500000 | H50: =E50-G50 -> 0 | I50: =IFERROR(E50/G50-1,0) -> 0 | K50: =INDEX('Data Summary'!M37:AW37,MATCH($B$99,'Data Summary'!$M$8:$AW$8,0)) -> 3500000 | L50: =E50-K50 -> 0 | M50: =IFERROR(E50/K50-1,0) -> 0
C51: Retained Earnings | E51: =INDEX('Data Summary'!M38:AW38,MATCH($B$92,'Data Summary'!$M$8:$AW$8,0)) -> -3366961.8 | G51: =INDEX('Data Summary'!M38:AW38,MATCH($B$96,'Data Summary'!$M$8:$AW$8,0)) -> -2756186.2 | H51: =E51-G51 -> -610775.53 | I51: =IFERROR(E51/G51-1,0) -> 0.22160169 | K51: =INDEX('Data Summary'!M38:AW38,MATCH($B$99,'Data Summary'!$M$8:$AW$8,0)) -> -1290560.5 | L51: =E51-K51 -> -2076401.3 | M51: =IFERROR(E51/K51-1,0) -> 1.6089143
C52: Total Equity | E52: =E50+E51 -> 133038.24 | G52: =G50+G51 -> 743813.77 | H52: =E52-G52 -> -610775.53 | I52: =IFERROR(E52/G52-1,0) -> -0.82114039 | K52: =K50+K51 -> 2209439.5 | L52: =E52-K52 -> -2076401.3 | M52: =IFERROR(E52/K52-1,0) -> -0.93978643
H53: =E53-G53 -> 0 | I53: =IFERROR(E53/G53-1,0) -> 0 | L53: =E53-K53 -> 0 | M53: =IFERROR(E53/K53-1,0) -> 0
C54: Total Liabilities & Equity | E54: =E47+E52 -> 1737715.7 | G54: =G47+G52 -> 2347491.3 | H54: =E54-G54 -> -609775.53 | I54: =IFERROR(E54/G54-1,0) -> -0.25975625 | K54: =K47+K52 -> 3813117 | L54: =E54-K54 -> -2075401.3 | M54: =IFERROR(E54/K54-1,0) -> -0.54427946
B57: CASH FLOW STATEMENT
C59: Cash from Operations
C60: Net Income (Loss) | E60: =E29 -> -610775.53 | G60: =G29 -> -542782.23 | H60: =E60-G60 -> -67993.3 | I60: =IFERROR(E60/G60-1,0) -> 0.1252681 | K60: =K29 -> -353145 | L60: =E60-K60 -> -257630.53 | M60: =IFERROR(E60/K60-1,0) -> 0.72953186
C61: Depreciation & Amortization | E61: =E26 -> 0 | G61: =G26 -> 0 | H61: =E61-G61 -> 0 | I61: =IFERROR(E61/G61-1,0) -> 0 | K61: =K26 -> 0 | L61: =E61-K61 -> 0 | M61: =IFERROR(E61/K61-1,0) -> 0
C63: Changes in Working Capital
C64: (Inc)/Dec in Accounts Receivable | E64: =-(E36-INDEX('Data Summary'!M28:AW28,MATCH($B$91-1,'Data Summary'!$M$8:$AW$8,0))) -> -12994.78 | G64: =-(G36-INDEX('Data Summary'!M28:AW28,MATCH($B$95-1,'Data Summary'!$M$8:$AW$8,0))) -> -3993.77 | H64: =E64-G64 -> -9001.01 | I64: =IFERROR(E64/G64-1,0) -> 2.2537627 | K64: =-(K36-INDEX('Data Summary'!M28:AW28,MATCH($B$98-1,'Data Summary'!$M$8:$AW$8,0))) -> -3996 | L64: =E64-K64 -> -8998.78 | M64: =IFERROR(E64/K64-1,0) -> 2.2519469
C65: (Inc)/Dec in Current Assets | E65: =-(E37-INDEX('Data Summary'!M30:AW30,MATCH($B$91-1,'Data Summary'!$M$8:$AW$8,0))) -> 300 | G65: =-(G37-INDEX('Data Summary'!M30:AW30,MATCH($B$95-1,'Data Summary'!$M$8:$AW$8,0))) -> 0 | H65: =E65-G65 -> 300 | I65: =IFERROR(E65/G65-1,0) -> 0 | K65: =-(K37-INDEX('Data Summary'!M30:AW30,MATCH($B$98-1,'Data Summary'!$M$8:$AW$8,0))) -> 0 | L65: =E65-K65 -> 300 | M65: =IFERROR(E65/K65-1,0) -> 0
C66: (Inc)/Dec in Other Current Assets | E66: =-(E39-INDEX('Data Summary'!M32:AW32,MATCH($B$91-1,'Data Summary'!$M$8:$AW$8,0))) -> 0 | G66: =-(G39-INDEX('Data Summary'!M32:AW32,MATCH($B$95-1,'Data Summary'!$M$8:$AW$8,0))) -> 0 | H66: =E66-G66 -> 0 | I66: =IFERROR(E66/G66-1,0) -> 0 | K66: =-(K39-INDEX('Data Summary'!M32:AW32,MATCH($B$98-1,'Data Summary'!$M$8:$AW$8,0))) -> 0 | L66: =E66-K66 -> 0 | M66: =IFERROR(E66/K66-1,0) -> 0
C67: Inc/(Dec) in Accounts Payable | E67: =E43-INDEX('Data Summary'!M33:AW33,MATCH($B$91-1,'Data Summary'!$M$8:$AW$8,0)) -> 1000 | G67: =G43-INDEX('Data Summary'!M33:AW33,MATCH($B$95-1,'Data Summary'!$M$8:$AW$8,0)) -> 0 | H67: =E67-G67 -> 1000 | I67: =IFERROR(E67/G67-1,0) -> 0 | K67: =K43-INDEX('Data Summary'!M33:AW33,MATCH($B$98-1,'Data Summary'!$M$8:$AW$8,0)) -> 0 | L67: =E67-K67 -> 1000 | M67: =IFERROR(E67/K67-1,0) -> 0
C68: Inc/(Dec) in Current Liabilities | E68: =E44-INDEX('Data Summary'!M34:AW34,MATCH($B$91-1,'Data Summary'!$M$8:$AW$8,0)) -> 0 | G68: =G44-INDEX('Data Summary'!M34:AW34,MATCH($B$95-1,'Data Summary'!$M$8:$AW$8,0)) -> 0 | H68: =E68-G68 -> 0 | I68: =IFERROR(E68/G68-1,0) -> 0 | K68: =K44-INDEX('Data Summary'!M34:AW34,MATCH($B$98-1,'Data Summary'!$M$8:$AW$8,0)) -> 0 | L68: =E68-K68 -> 0 | M68: =IFERROR(E68/K68-1,0) -> 0
C69: Inc/(Dec) in Deferred Revenue | E69: =E46-INDEX('Data Summary'!M36:AW36,MATCH($B$91-1,'Data Summary'!$M$8:$AW$8,0)) -> 0 | G69: =G46-INDEX('Data Summary'!M36:AW36,MATCH($B$95-1,'Data Summary'!$M$8:$AW$8,0)) -> 0 | H69: =E69-G69 -> 0 | I69: =IFERROR(E69/G69-1,0) -> 0 | K69: =K46-INDEX('Data Summary'!M36:AW36,MATCH($B$98-1,'Data Summary'!$M$8:$AW$8,0)) -> 0 | L69: =E69-K69 -> 0 | M69: =IFERROR(E69/K69-1,0) -> 0
C70: Net Cash from Operations | E70: =E60+E61+SUM(E64:E69) -> -622470.31 | G70: =G60+G61+SUM(G64:G69) -> -546776 | H70: =E70-G70 -> -75694.31 | I70: =IFERROR(E70/G70-1,0) -> 0.13843751 | K70: =K60+K61+SUM(K64:K69) -> -357141 | L70: =E70-K70 -> -265329.31 | M70: =IFERROR(E70/K70-1,0) -> 0.74292593
C72: Cash from Investing
C73: Capital Expenditures (Net) | E73: =-(E38-INDEX('Data Summary'!M31:AW31,MATCH($B$91-1,'Data Summary'!$M$8:$AW$8,0)))-E61 -> 9151.98 | G73: =-(G38-INDEX('Data Summary'!M31:AW31,MATCH($B$95-1,'Data Summary'!$M$8:$AW$8,0)))-G61 -> 9151.98 | H73: =E73-G73 -> 0 | I73: =IFERROR(E73/G73-1,0) -> 0 | K73: =-(K38-INDEX('Data Summary'!M31:AW31,MATCH($B$98-1,'Data Summary'!$M$8:$AW$8,0)))-K61 -> 9152 | L73: =E73-K73 -> -0.02 | M73: =IFERROR(E73/K73-1,0) -> -2.1853147e-06
C74: Net Cash from Investing | E74: =E73 -> 9151.98 | G74: =G73 -> 9151.98 | H74: =E74-G74 -> 0 | I74: =IFERROR(E74/G74-1,0) -> 0 | K74: =K73 -> 9152 | L74: =E74-K74 -> -0.02 | M74: =IFERROR(E74/K74-1,0) -> -2.1853147e-06
C76: Cash from Financing
C77: Inc/(Dec) in Debt | E77: =E45-INDEX('Data Summary'!M35:AW35,MATCH($B$91-1,'Data Summary'!$M$8:$AW$8,0)) -> 0 | G77: =G45-INDEX('Data Summary'!M35:AW35,MATCH($B$95-1,'Data Summary'!$M$8:$AW$8,0)) -> 0 | H77: =E77-G77 -> 0 | I77: =IFERROR(E77/G77-1,0) -> 0 | K77: =K45-INDEX('Data Summary'!M35:AW35,MATCH($B$98-1,'Data Summary'!$M$8:$AW$8,0)) -> 0 | L77: =E77-K77 -> 0 | M77: =IFERROR(E77/K77-1,0) -> 0
C78: Inc/(Dec) in Contributed Capital | E78: =E50-INDEX('Data Summary'!M37:AW37,MATCH($B$91-1,'Data Summary'!$M$8:$AW$8,0)) -> 0 | G78: =G50-INDEX('Data Summary'!M37:AW37,MATCH($B$95-1,'Data Summary'!$M$8:$AW$8,0)) -> 0 | H78: =E78-G78 -> 0 | I78: =IFERROR(E78/G78-1,0) -> 0 | K78: =K50-INDEX('Data Summary'!M37:AW37,MATCH($B$98-1,'Data Summary'!$M$8:$AW$8,0)) -> 0 | L78: =E78-K78 -> 0 | M78: =IFERROR(E78/K78-1,0) -> 0
C79: Net Cash from Financing | E79: =SUM(E77:E78) -> 0 | G79: =SUM(G77:G78) -> 0 | H79: =E79-G79 -> 0 | I79: =IFERROR(E79/G79-1,0) -> 0 | K79: =SUM(K77:K78) -> 0 | L79: =E79-K79 -> 0 | M79: =IFERROR(E79/K79-1,0) -> 0
C81: Net Change in Cash | E81: =E70+E74+E79 -> -613318.33 | G81: =G70+G74+G79 -> -537624.02 | H81: =E81-G81 -> -75694.31 | I81: =IFERROR(E81/G81-1,0) -> 0.14079414 | K81: =K70+K74+K79 -> -347989 | L81: =E81-K81 -> -265329.33 | M81: =IFERROR(E81/K81-1,0) -> 0.7624647
C82: Beginning Cash Balance | E82: =INDEX('Data Summary'!M29:AW29,MATCH($B$91-1,'Data Summary'!$M$8:$AW$8,0)) -> 2207358.5 | G82: =INDEX('Data Summary'!M29:AW29,MATCH($B$95-1,'Data Summary'!$M$8:$AW$8,0)) -> 2744982.5 | H82: =E82-G82 -> -537624.02 | I82: =IFERROR(E82/G82-1,0) -> -0.19585699 | K82: =INDEX('Data Summary'!M29:AW29,MATCH($B$98-1,'Data Summary'!$M$8:$AW$8,0)) -> 4004840.5 | L82: =E82-K82 -> -1797482 | M82: =IFERROR(E82/K82-1,0) -> -0.44882737
C83: Ending Cash Balance | E83: =E81+E82 -> 1594040.1 | G83: =G81+G82 -> 2207358.5 | H83: =E83-G83 -> -613318.33 | I83: =IFERROR(E83/G83-1,0) -> -0.27785171 | K83: =K81+K82 -> 3656851.5 | L83: =E83-K83 -> -2062811.4 | M83: =IFERROR(E83/K83-1,0) -> -0.56409492
C84: Balance Sheet Check | E84: =E83-E35 -> 0 | G84: =G83-G35 -> 0 | H84: =E84-G84 -> 0 | I84: =IFERROR(E84/G84-1,0) -> 0 | K84: =K83-K35 -> 0 | L84: =E84-K84 -> 0 | M84: =IFERROR(E84/K84-1,0) -> 0
A90: Selected Period | B90: =E4 -> Last Quarter
A91: Start Date | B91: =VLOOKUP(B90,Lists!E6:O20,2,FALSE) -> 45748
A92: End Date | B92: =VLOOKUP(B90,Lists!E6:O20,3,FALSE) -> 45838
A93: Display Text | B93: =VLOOKUP(B90,Lists!E6:O20,4,FALSE) -> Q2 2025
A94: Periods | B94: =VLOOKUP(B90,Lists!E6:O20,5,FALSE) -> 3
A95: PP Start | B95: =VLOOKUP(B90,Lists!E6:O20,6,FALSE) -> 45658
A96: PP End | B96: =VLOOKUP(B90,Lists!E6:O20,7,FALSE) -> 45747
A97: PP Display | B97: =VLOOKUP(B90,Lists!E6:O20,8,FALSE) -> Q1 2025
A98: PY Start | B98: =VLOOKUP(B90,Lists!E6:O20,9,FALSE) -> 45383
A99: PY End | B99: =VLOOKUP(B90,Lists!E6:O20,10,FALSE) -> 45473
A100: PY Display | B100: =VLOOKUP(B90,Lists!E6:O20,11,FALSE) -> Q2 2024

Sheet AR Command Center
B2: ◼ ◼ | D2: AR AGING COMMAND CENTER | K2: As of: May 11, 2026
B5: TOTAL AR OUTSTANDING | D5: CURRENT DSO | F5: % PAST DUE | H5: # OPEN INVOICES
B6: =SUMIF('AR Data'!J2:J35,"<>Paid",'AR Data'!G2:G35) -> 5495500 | D6: ='AR Data'!P14 -> 227.4 | F6: =SUMIF('AR Data'!J2:J35,"Past Due",'AR Data'!G2:G35)/SUMIF('AR Data'!J2:J35,"<>Paid",'AR Data'!G2:G35) -> 1 | H6: =COUNTIF('AR Data'!J2:J35,"<>Paid") -> 30
B7: All unpaid invoices | D7: Days Sales Outstanding | F7: AR beyond 30 days | H7: Outstanding invoices
B36: AGING BUCKETS | I36: DSO TREND (12-MONTH)
C37: Bucket | D37: Amount | E37: # Invoices | F37: % of Total | G37: Avg Days Out | I37: Month | J37: DSO | K37: Target
C38: Current (0-30) | D38: =SUMIFS('AR Data'!G2:G35,'AR Data'!I2:I35,"Current") -> 0 | E38: =COUNTIFS('AR Data'!I2:I35,"Current") -> 0 | F38: =IF(D42=0,0,D38/D42) -> 0 | G38: =IFERROR(AVERAGEIFS('AR Data'!H2:H35,'AR Data'!I2:I35,"Current"),0) -> 0 | I38: ='AR Data'!M3 -> Jun-25 | J38: ='AR Data'!P3 -> 124.81752 | K38: 45
C39: 31-60 Days | D39: =SUMIFS('AR Data'!G2:G35,'AR Data'!I2:I35,"31-60") -> 2689000 | E39: =COUNTIFS('AR Data'!I2:I35,"31-60") -> 12 | F39: =IF(D42=0,0,D39/D42) -> 0.48930943 | G39: =IFERROR(AVERAGEIFS('AR Data'!H2:H35,'AR Data'!I2:I35,"31-60"),0) -> 43.166667 | I39: ='AR Data'!M4 -> Jul-25 | J39: ='AR Data'!P4 -> 123.38028 | K39: 45
C40: 61-90 Days | D40: =SUMIFS('AR Data'!G2:G35,'AR Data'!I2:I35,"61-90") -> 1351500 | E40: =COUNTIFS('AR Data'!I2:I35,"61-90") -> 7 | F40: =IF(D42=0,0,D40/D42) -> 0.24592849 | G40: =IFERROR(AVERAGEIFS('AR Data'!H2:H35,'AR Data'!I2:I35,"61-90"),0) -> 71.571429 | I40: ='AR Data'!M5 -> Aug-25 | J40: ='AR Data'!P5 -> 131.25 | K40: 45
C41: 90+ Days | D41: =SUMIFS('AR Data'!G2:G35,'AR Data'!I2:I35,"90+") -> 1455000 | E41: =COUNTIFS('AR Data'!I2:I35,"90+") -> 11 | F41: =IF(D42=0,0,D41/D42) -> 0.26476208 | G41: =IFERROR(AVERAGEIFS('AR Data'!H2:H35,'AR Data'!I2:I35,"90+"),0) -> 229.36364 | I41: ='AR Data'!M6 -> Sep-25 | J41: ='AR Data'!P6 -> 145.89928 | K41: 45
C42: TOTAL | D42: =SUM(D38:D41) -> 5495500 | E42: =SUM(E38:E41) -> 30 | F42: =SUM(F38:F41) -> 1 | G42: =IFERROR(AVERAGEIFS('AR Data'!H2:H35,'AR Data'!J2:J35,"<>Paid"),0) -> 118.06667 | I42: ='AR Data'!M7 -> Oct-25 | J42: ='AR Data'!P7 -> 125.34247 | K42: 45
I43: ='AR Data'!M8 -> Nov-25 | J43: ='AR Data'!P8 -> 129.26174 | K43: 45
B44: CUSTOMER CONCENTRATION | I44: ='AR Data'!M9 -> Dec-25 | J44: ='AR Data'!P9 -> 139.73684 | K44: 45
B45: Customer | C45: AR Balance | D45: % of Total | E45: Risk | I45: ='AR Data'!M10 -> Jan-26 | J45: ='AR Data'!P10 -> 157.71429 | K45: 45
B46: GlobalTech Solutions | C46: =SUMIFS('AR Data'!G2:G35,'AR Data'!B2:B35,B46,'AR Data'!J2:J35,"<>Paid") -> 665000 | D46: =IF($C$59=0,0,C46/$C$59) -> 0.1210081 | E46: =IF(D46>=0.15,"⚠ High",IF(D46>=0.1,"Medium","Low")) -> Medium | I46: ='AR Data'!M11 -> Feb-26 | J46: ='AR Data'!P11 -> 148.69565 | K46: 45
B47: Ironclad Manufacturing | C47: =SUMIFS('AR Data'!G2:G35,'AR Data'!B2:B35,B47,'AR Data'!J2:J35,"<>Paid") -> 912000 | D47: =IF($C$59=0,0,C47/$C$59) -> 0.16595396 | E47: =IF(D47>=0.15,"⚠ High",IF(D47>=0.1,"Medium","Low")) -> ⚠ High | I47: ='AR Data'!M12 -> Mar-26 | J47: ='AR Data'!P12 -> 157.34266 | K47: 45
B48: Cascade Industries | C48: =SUMIFS('AR Data'!G2:G35,'AR Data'!B2:B35,B48,'AR Data'!J2:J35,"<>Paid") -> 698000 | D48: =IF($C$59=0,0,C48/$C$59) -> 0.12701301 | E48: =IF(D48>=0.15,"⚠ High",IF(D48>=0.1,"Medium","Low")) -> Medium | I48: ='AR Data'!M13 -> Apr-26 | J48: ='AR Data'!P13 -> 157.7027 | K48: 45
B49: Apex Technologies | C49: =SUMIFS('AR Data'!G2:G35,'AR Data'!B2:B35,B49,'AR Data'!J2:J35,"<>Paid") -> 594500 | D49: =IF($C$59=0,0,C49/$C$59) -> 0.10817942 | E49: =IF(D49>=0.15,"⚠ High",IF(D49>=0.1,"Medium","Low")) -> Medium | I49: ='AR Data'!M14 -> May-26 | J49: ='AR Data'!P14 -> 227.4 | K49: 45
B50: Evergreen Health | C50: =SUMIFS('AR Data'!G2:G35,'AR Data'!B2:B35,B50,'AR Data'!J2:J35,"<>Paid") -> 575000 | D50: =IF($C$59=0,0,C50/$C$59) -> 0.10463106 | E50: =IF(D50>=0.15,"⚠ High",IF(D50>=0.1,"Medium","Low")) -> Medium
B51: Luminary Brands | C51: =SUMIFS('AR Data'!G2:G35,'AR Data'!B2:B35,B51,'AR Data'!J2:J35,"<>Paid") -> 495000 | D51: =IF($C$59=0,0,C51/$C$59) -> 0.090073697 | E51: =IF(D51>=0.15,"⚠ High",IF(D51>=0.1,"Medium","Low")) -> Low | I51: ⚠ TOP PAST DUE INVOICES
B52: Nexus Consulting | C52: =SUMIFS('AR Data'!G2:G35,'AR Data'!B2:B35,B52,'AR Data'!J2:J35,"<>Paid") -> 360000 | D52: =IF($C$59=0,0,C52/$C$59) -> 0.065508143 | E52: =IF(D52>=0.15,"⚠ High",IF(D52>=0.1,"Medium","Low")) -> Low | I52: Invoice | J52: Customer | K52: Balance
B53: BlueStar Logistics | C53: =SUMIFS('AR Data'!G2:G35,'AR Data'!B2:B35,B53,'AR Data'!J2:J35,"<>Paid") -> 266000 | D53: =IF($C$59=0,0,C53/$C$59) -> 0.048403239 | E53: =IF(D53>=0.15,"⚠ High",IF(D53>=0.1,"Medium","Low")) -> Low | I53: {=IFERROR(INDEX('AR Data'!A2:A35,MATCH(LARGE(IF('AR Data'!J2:J35="Past Due",'AR Data'!G2:G35),1),'AR Data'!G2:G35,0)),"")} -> INV-1017 | J53: {=IFERROR(INDEX('AR Data'!B2:B35,MATCH(LARGE(IF('AR Data'!J2:J35="Past Due",'AR Data'!G2:G35),1),'AR Data'!G2:G35,0)),"")} -> GlobalTech Solutions | K53: {=IFERROR(LARGE(IF('AR Data'!J2:J35="Past Due",'AR Data'!G2:G35),1),"")} -> 520000
B54: Jetstream Aviation | C54: =SUMIFS('AR Data'!G2:G35,'AR Data'!B2:B35,B54,'AR Data'!J2:J35,"<>Paid") -> 279000 | D54: =IF($C$59=0,0,C54/$C$59) -> 0.050768811 | E54: =IF(D54>=0.15,"⚠ High",IF(D54>=0.1,"Medium","Low")) -> Low | I54: {=IFERROR(INDEX('AR Data'!A2:A35,MATCH(LARGE(IF('AR Data'!J2:J35="Past Due",'AR Data'!G2:G35),2),'AR Data'!G2:G35,0)),"")} -> INV-1022 | J54: {=IFERROR(INDEX('AR Data'!B2:B35,MATCH(LARGE(IF('AR Data'!J2:J35="Past Due",'AR Data'!G2:G35),2),'AR Data'!G2:G35,0)),"")} -> Ironclad Manufacturing | K54: {=IFERROR(LARGE(IF('AR Data'!J2:J35="Past Due",'AR Data'!G2:G35),2),"")} -> 445000
B55: Delta Partners | C55: =SUMIFS('AR Data'!G2:G35,'AR Data'!B2:B35,B55,'AR Data'!J2:J35,"<>Paid") -> 201500 | D55: =IF($C$59=0,0,C55/$C$59) -> 0.036666363 | E55: =IF(D55>=0.15,"⚠ High",IF(D55>=0.1,"Medium","Low")) -> Low | I55: {=IFERROR(INDEX('AR Data'!A2:A35,MATCH(LARGE(IF('AR Data'!J2:J35="Past Due",'AR Data'!G2:G35),3),'AR Data'!G2:G35,0)),"")} -> INV-1007 | J55: {=IFERROR(INDEX('AR Data'!B2:B35,MATCH(LARGE(IF('AR Data'!J2:J35="Past Due",'AR Data'!G2:G35),3),'AR Data'!G2:G35,0)),"")} -> Cascade Industries | K55: {=IFERROR(LARGE(IF('AR Data'!J2:J35="Past Due",'AR Data'!G2:G35),3),"")} -> 425000
B56: Harbor Financial | C56: =SUMIFS('AR Data'!G2:G35,'AR Data'!B2:B35,B56,'AR Data'!J2:J35,"<>Paid") -> 198000 | D56: =IF($C$59=0,0,C56/$C$59) -> 0.036029479 | E56: =IF(D56>=0.15,"⚠ High",IF(D56>=0.1,"Medium","Low")) -> Low | I56: {=IFERROR(INDEX('AR Data'!A2:A35,MATCH(LARGE(IF('AR Data'!J2:J35="Past Due",'AR Data'!G2:G35),4),'AR Data'!G2:G35,0)),"")} -> INV-1023 | J56: {=IFERROR(INDEX('AR Data'!B2:B35,MATCH(LARGE(IF('AR Data'!J2:J35="Past Due",'AR Data'!G2:G35),4),'AR Data'!G2:G35,0)),"")} -> Ironclad Manufacturing | K56: {=IFERROR(LARGE(IF('AR Data'!J2:J35="Past Due",'AR Data'!G2:G35),4),"")} -> 367000
B57: KeyPoint Analytics | C57: =SUMIFS('AR Data'!G2:G35,'AR Data'!B2:B35,B57,'AR Data'!J2:J35,"<>Paid") -> 173500 | D57: =IF($C$59=0,0,C57/$C$59) -> 0.031571286 | E57: =IF(D57>=0.15,"⚠ High",IF(D57>=0.1,"Medium","Low")) -> Low | I57: {=IFERROR(INDEX('AR Data'!A2:A35,MATCH(LARGE(IF('AR Data'!J2:J35="Past Due",'AR Data'!G2:G35),5),'AR Data'!G2:G35,0)),"")} -> INV-1012 | J57: {=IFERROR(INDEX('AR Data'!B2:B35,MATCH(LARGE(IF('AR Data'!J2:J35="Past Due",'AR Data'!G2:G35),5),'AR Data'!G2:G35,0)),"")} -> Evergreen Health | K57: {=IFERROR(LARGE(IF('AR Data'!J2:J35="Past Due",'AR Data'!G2:G35),5),"")} -> 298000
B58: Frontier Software | C58: =SUMIFS('AR Data'!G2:G35,'AR Data'!B2:B35,B58,'AR Data'!J2:J35,"<>Paid") -> 78000 | D58: =IF($C$59=0,0,C58/$C$59) -> 0.014193431 | E58: =IF(D58>=0.15,"⚠ High",IF(D58>=0.1,"Medium","Low")) -> Low
B59: TOTAL | C59: =SUM(C46:C58) -> 5495500 | D59: =SUM(D46:D58) -> 1 | E59: =IF(D59>=0.15,"⚠ High",IF(D59>=0.1,"Medium","Low")) -> ⚠ High | I59: Top 3 Concentration: | J59: {=SUMPRODUCT(LARGE(C46:C58,{1,2,3}))/C59} -> 0.41397507
I60: Top 5 Concentration: | J60: {=SUMPRODUCT(LARGE(C46:C58,{1,2,3,4,5}))/C59} -> 0.62678555
I61: HHI Index: | J61: {=SUMPRODUCT((C46:C58/C59)^2)*10000} -> 1021.3211

Sheet KPI Dashboard
B2: ◼ ◼ | C2: Nimbus Cloud Solutions | O2: ="As of: "&TEXT(TODAY(),"MMM DD, YYYY") -> As of: Jun 05, 2026
B4: KPI DASHBOARD | O4: ="Latest Actuals: "&TEXT('Data Summary'!AH8,"MMM YYYY") -> Latest Actuals: Sep 2025
C6: REVENUE (LTM) | D6: COGS (LTM) | E6: GROSS MARGIN (LTM) | F6: NET INCOME (LTM) | H6: CASH BALANCE | I6: ACCOUNTS RECEIVABLE | J6: TOTAL OPEX (LTM) | K6: DEBT BALANCE | M6: MONTHLY BURN RATE | N6: CASH RUNWAY (MONTHS)
C7: {=SUMPRODUCT(('Data Summary'!M3:AW3="Actual")*'Data Summary'!M13:AW13)} -> 1294745.6 | D7: {=SUMPRODUCT(('Data Summary'!M3:AW3="Actual")*'Data Summary'!M15:AW15)} -> 118232.14 | E7: =IFERROR(1-D7/C7, 0) -> 0.90868311 | F7: {=C7-D7-SUMPRODUCT(('Data Summary'!M3:AW3="Actual")*(('Data Summary'!M17:AW17+'Data Summary'!M18:AW18+'Data Summary'!M19:AW19+'Data Summary'!M20:AW20+'Data Summary'!M21:AW21)))} -> -3062766.8 | H7: ='Data Summary'!AH29 -> 893122.77 | I7: ='Data Summary'!AH28 -> 73923.66 | J7: {=SUMPRODUCT(('Data Summary'!M3:AW3="Actual")*(('Data Summary'!M17:AW17+'Data Summary'!M18:AW18+'Data Summary'!M19:AW19+'Data Summary'!M20:AW20+'Data Summary'!M21:AW21)))} -> 4239280.2 | K7: ='Data Summary'!AH35 -> 1530000 | M7: =D11-C11 -> 215869.64 | N7: =IFERROR(ROUND(H7/M7,1),"N/A") -> 4.1
C8: Cumulative Actual Period | D8: Cumulative Actual Period | E8: Revenue less COGS | F8: Revenue less all expenses | H8: Latest actual month | I8: Latest actual month | J8: Cumulative Actual Period | K8: Latest actual month | M8: Opex minus Revenue | N8: Cash ÷ Monthly Burn
C10: MONTHLY REVENUE | D10: MONTHLY OPEX | E10: PAYROLL | F10: MARKETING & ADVERTISING | H10: PROF. SERVICES | I10: OFFICE & G&A | J10: TRAVEL & ENTERTAINMENT | K10: OTHER EXPENSES | M10: COGS % OF REVENUE | N10: OPEX % OF REVENUE
C11: ='Data Summary'!AH13 -> 87314.98 | D11: ='Data Summary'!AH17+'Data Summary'!AH18+'Data Summary'!AH19+'Data Summary'!AH20+'Data Summary'!AH21 -> 303184.62 | E11: ='Data Summary'!AH19 -> 81610 | F11: ='Data Summary'!AH17 -> 91625.69 | H11: ='Data Summary'!AH20 -> 29392.09 | I11: ='Data Summary'!AH18 -> 90655.73 | J11: ='Data Summary'!AH21 -> 9901.11 | K11: ='Data Summary'!AH25 -> 21495.42 | M11: =IFERROR('Data Summary'!AH15/'Data Summary'!AH13,0) -> 0.094933882 | N11: =IFERROR(D11/C11,0) -> 3.4723093
C12: =TEXT('Data Summary'!AH8,"MMM YYYY") -> Sep 2025 | D12: =TEXT('Data Summary'!AH8,"MMM YYYY") -> Sep 2025 | E12: =TEXT('Data Summary'!AH8,"MMM YYYY") -> Sep 2025 | F12: =TEXT('Data Summary'!AH8,"MMM YYYY") -> Sep 2025 | H12: =TEXT('Data Summary'!AH8,"MMM YYYY") -> Sep 2025 | I12: =TEXT('Data Summary'!AH8,"MMM YYYY") -> Sep 2025 | J12: =TEXT('Data Summary'!AH8,"MMM YYYY") -> Sep 2025 | K12: =TEXT('Data Summary'!AH8,"MMM YYYY") -> Sep 2025 | M12: =TEXT('Data Summary'!AH8,"MMM YYYY") -> Sep 2025 | N12: =TEXT('Data Summary'!AH8,"MMM YYYY") -> Sep 2025
B50: Month | C50: =TEXT('Data Summary'!W8,"MMM YY") -> Oct 24 | D50: =TEXT('Data Summary'!X8,"MMM YY") -> Nov 24 | E50: =TEXT('Data Summary'!Y8,"MMM YY") -> Dec 24 | F50: =TEXT('Data Summary'!Z8,"MMM YY") -> Jan 25 | G50: =TEXT('Data Summary'!AA8,"MMM YY") -> Feb 25 | H50: =TEXT('Data Summary'!AB8,"MMM YY") -> Mar 25 | I50: =TEXT('Data Summary'!AC8,"MMM YY") -> Apr 25 | J50: =TEXT('Data Summary'!AD8,"MMM YY") -> May 25 | ... N50: =TEXT('Data Summary'!AH8,"MMM YY") -> Sep 25
B51: Revenue | C51: ='Data Summary'!W13 -> 51051 | D51: ='Data Summary'!X13 -> 53604 | E51: ='Data Summary'!Y13 -> 56284 | F51: ='Data Summary'!Z13 -> 59098.22 | G51: ='Data Summary'!AA13 -> 62053 | H51: ='Data Summary'!AB13 -> 65156 | I51: ='Data Summary'!AC13 -> 68414 | J51: ='Data Summary'!AD13 -> 71834 | ... N51: ='Data Summary'!AH13 -> 87314.98
B52: COGS | C52: ='Data Summary'!W15 -> 4846.33 | D52: ='Data Summary'!X15 -> 5089.33 | E52: ='Data Summary'!Y15 -> 5343 | F52: ='Data Summary'!Z15 -> 5610.42 | G52: ='Data Summary'!AA15 -> 5890 | H52: ='Data Summary'!AB15 -> 6185 | I52: ='Data Summary'!AC15 -> 6495 | J52: ='Data Summary'!AD15 -> 6820 | ... N52: ='Data Summary'!AH15 -> 8289.15
B54: Category | C54: Amount
B55: Marketing & Advertising | C55: ='Data Summary'!AH17 -> 91625.69
B56: Office & G&A | C56: ='Data Summary'!AH18 -> 90655.73
B57: Payroll | C57: ='Data Summary'!AH19 -> 81610
B58: Professional Services | C58: ='Data Summary'!AH20 -> 29392.09
B59: Travel & Entertainment | C59: ='Data Summary'!AH21 -> 9901.11
B61: Month | C61: =C50 -> Oct 24 | D61: =D50 -> Nov 24 | E61: =E50 -> Dec 24 | F61: =F50 -> Jan 25 | G61: =G50 -> Feb 25 | H61: =H50 -> Mar 25 | I61: =I50 -> Apr 25 | J61: =J50 -> May 25 | ... N61: =N50 -> Sep 25
B62: Cash | C62: ='Data Summary'!W29 -> 3066455.5 | D62: ='Data Summary'!X29 -> 2909186.5 | E62: ='Data Summary'!Y29 -> 2744982.5 | F62: ='Data Summary'!Z29 -> 2573511.5 | G62: ='Data Summary'!AA29 -> 2394437.5 | H62: ='Data Summary'!AB29 -> 2207358.5 | I62: ='Data Summary'!AC29 -> 2011881.5 | J62: ='Data Summary'!AD29 -> 1807588.5 | ... N62: ='Data Summary'!AH29 -> 893122.77
B64: Month | C64: =C50 -> Oct 24 | D64: =D50 -> Nov 24 | E64: =E50 -> Dec 24 | F64: =F50 -> Jan 25 | G64: =G50 -> Feb 25 | H64: =H50 -> Mar 25 | I64: =I50 -> Apr 25 | J64: =J50 -> May 25 | ... N64: =N50 -> Sep 25
B65: Revenue | C65: =C51 -> 51051 | D65: =D51 -> 53604 | E65: =E51 -> 56284 | F65: =F51 -> 59098.22 | G65: =G51 -> 62053 | H65: =H51 -> 65156 | I65: =I51 -> 68414 | J65: =J51 -> 71834 | ... N65: =N51 -> 87314.98
B66: Total Opex | C66: ='Data Summary'!W17+'Data Summary'!W18+'Data Summary'!W19+'Data Summary'!W20+'Data Summary'!W21 -> 177265.67 | D66: ='Data Summary'!X17+'Data Summary'!X18+'Data Summary'!X19+'Data Summary'!X20+'Data Summary'!X21 -> 186128.67 | E66: ='Data Summary'!Y17+'Data Summary'!Y18+'Data Summary'!Y19+'Data Summary'!Y20+'Data Summary'!Y21 -> 195434.5 | F66: ='Data Summary'!Z17+'Data Summary'!Z18+'Data Summary'!Z19+'Data Summary'!Z20+'Data Summary'!Z21 -> 205207.29 | G66: ='Data Summary'!AA17+'Data Summary'!AA18+'Data Summary'!AA19+'Data Summary'!AA20+'Data Summary'!AA21 -> 215468 | H66: ='Data Summary'!AB17+'Data Summary'!AB18+'Data Summary'!AB19+'Data Summary'!AB20+'Data Summary'!AB21 -> 226242 | I66: ='Data Summary'!AC17+'Data Summary'!AC18+'Data Summary'!AC19+'Data Summary'!AC20+'Data Summary'!AC21 -> 237553 | J66: ='Data Summary'!AD17+'Data Summary'!AD18+'Data Summary'!AD19+'Data Summary'!AD20+'Data Summary'!AD21 -> 249432 | ... N66: ='Data Summary'!AH17+'Data Summary'!AH18+'Data Summary'!AH19+'Data Summary'!AH20+'Data Summary'!AH21 -> 303184.62

Sheet AR Data
A1: Invoice # | B1: Customer | C1: Invoice Date | D1: Due Date | E1: Invoice Amount | F1: Amount Paid | G1: Balance | H1: Days Outstanding | I1: Aging Bucket | J1: Status | K1: Revenue (TTM) | M1: DSO TREND DATA
A2: INV-1001 | B2: Apex Technologies | C2: 46140 | D2: 46170 | E2: 187500 | F2: 0 | G2: =E2-F2 -> 187500 | H2: =IF(G2>0,TODAY()-C2,0) -> 38 | I2: =IF(G2=0,"Paid",IF(H2<=30,"Current",IF(H2<=60,"31-60",IF(H2<=90,"61-90","90+")))) -> 31-60 | J2: =IF(G2=0,"Paid",IF(H2<=30,"Current","Past Due")) -> Past Due | K2: 8450000 | M2: Month | N2: AR Balance | O2: Monthly Revenue | P2: DSO
A3: INV-1002 | B3: Apex Technologies | C3: 46110 | D3: 46140 | E3: 245000 | F3: 0 | G3: =E3-F3 -> 245000 | H3: =IF(G3>0,TODAY()-C3,0) -> 68 | I3: =IF(G3=0,"Paid",IF(H3<=30,"Current",IF(H3<=60,"31-60",IF(H3<=90,"61-90","90+")))) -> 61-90 | J3: =IF(G3=0,"Paid",IF(H3<=30,"Current","Past Due")) -> Past Due | M3: Jun-25 | N3: 2850000 | O3: 685000 | P3: =N3/O3*30 -> 124.81752
A4: INV-1003 | B4: Apex Technologies | C4: 45990 | D4: 46020 | E4: 312000 | F4: 150000 | G4: =E4-F4 -> 162000 | H4: =IF(G4>0,TODAY()-C4,0) -> 188 | I4: =IF(G4=0,"Paid",IF(H4<=30,"Current",IF(H4<=60,"31-60",IF(H4<=90,"61-90","90+")))) -> 90+ | J4: =IF(G4=0,"Paid",IF(H4<=30,"Current","Past Due")) -> Past Due | M4: Jul-25 | N4: 2920000 | O4: 710000 | P4: =N4/O4*30 -> 123.38028 | Q4: 685000 | R4: =P4/Q4*30 -> 0.005403516
A5: INV-1004 | B5: BlueStar Logistics | C5: 46135 | D5: 46165 | E5: 156000 | F5: 0 | G5: =E5-F5 -> 156000 | H5: =IF(G5>0,TODAY()-C5,0) -> 43 | I5: =IF(G5=0,"Paid",IF(H5<=30,"Current",IF(H5<=60,"31-60",IF(H5<=90,"61-90","90+")))) -> 31-60 | J5: =IF(G5=0,"Paid",IF(H5<=30,"Current","Past Due")) -> Past Due | M5: Aug-25 | N5: 3150000 | O5: 720000 | P5: =N5/O5*30 -> 131.25 | Q5: 710000
A6: INV-1005 | B6: BlueStar Logistics | C6: 46020 | D6: 46050 | E6: 89500 | F6: 89500 | G6: =E6-F6 -> 0 | H6: =IF(G6>0,TODAY()-C6,0) -> 0 | I6: =IF(G6=0,"Paid",IF(H6<=30,"Current",IF(H6<=60,"31-60",IF(H6<=90,"61-90","90+")))) -> Paid | J6: =IF(G6=0,"Paid",IF(H6<=30,"Current","Past Due")) -> Paid | M6: Sep-25 | N6: 3380000 | O6: 695000 | P6: =N6/O6*30 -> 145.89928 | Q6: 720000
A7: INV-1006 | B7: BlueStar Logistics | C7: 45960 | D7: 45990 | E7: 210000 | F7: 100000 | G7: =E7-F7 -> 110000 | H7: =IF(G7>0,TODAY()-C7,0) -> 218 | I7: =IF(G7=0,"Paid",IF(H7<=30,"Current",IF(H7<=60,"31-60",IF(H7<=90,"61-90","90+")))) -> 90+ | J7: =IF(G7=0,"Paid",IF(H7<=30,"Current","Past Due")) -> Past Due | M7: Oct-25 | N7: 3050000 | O7: 730000 | P7: =N7/O7*30 -> 125.34247 | Q7: 695000
A8: INV-1007 | B8: Cascade Industries | C8: 46143 | D8: 46173 | E8: 425000 | F8: 0 | G8: =E8-F8 -> 425000 | H8: =IF(G8>0,TODAY()-C8,0) -> 35 | I8: =IF(G8=0,"Paid",IF(H8<=30,"Current",IF(H8<=60,"31-60",IF(H8<=90,"61-90","90+")))) -> 31-60 | J8: =IF(G8=0,"Paid",IF(H8<=30,"Current","Past Due")) -> Past Due | M8: Nov-25 | N8: 3210000 | O8: 745000 | P8: =N8/O8*30 -> 129.26174 | Q8: 730000
A9: INV-1008 | B9: Cascade Industries | C9: 46105 | D9: 46135 | E9: 178000 | F9: 0 | G9: =E9-F9 -> 178000 | H9: =IF(G9>0,TODAY()-C9,0) -> 73 | I9: =IF(G9=0,"Paid",IF(H9<=30,"Current",IF(H9<=60,"31-60",IF(H9<=90,"61-90","90+")))) -> 61-90 | J9: =IF(G9=0,"Paid",IF(H9<=30,"Current","Past Due")) -> Past Due | M9: Dec-25 | N9: 3540000 | O9: 760000 | P9: =N9/O9*30 -> 139.73684 | Q9: 745000
A10: INV-1009 | B10: Cascade Industries | C10: 45930 | D10: 45960 | E10: 95000 | F10: 0 | G10: =E10-F10 -> 95000 | H10: =IF(G10>0,TODAY()-C10,0) -> 248 | I10: =IF(G10=0,"Paid",IF(H10<=30,"Current",IF(H10<=60,"31-60",IF(H10<=90,"61-90","90+")))) -> 90+ | J10: =IF(G10=0,"Paid",IF(H10<=30,"Current","Past Due")) -> Past Due | M10: Jan-26 | N10: 3680000 | O10: 700000 | P10: =N10/O10*30 -> 157.71429 | Q10: 760000
A11: INV-1010 | B11: Delta Partners | C11: 46138 | D11: 46168 | E11: 67500 | F11: 0 | G11: =E11-F11 -> 67500 | H11: =IF(G11>0,TODAY()-C11,0) -> 40 | I11: =IF(G11=0,"Paid",IF(H11<=30,"Current",IF(H11<=60,"31-60",IF(H11<=90,"61-90","90+")))) -> 31-60 | J11: =IF(G11=0,"Paid",IF(H11<=30,"Current","Past Due")) -> Past Due | M11: Feb-26 | N11: 3420000 | O11: 690000 | P11: =N11/O11*30 -> 148.69565 | Q11: 700000
A12: INV-1011 | B12: Delta Partners | C12: 46115 | D12: 46145 | E12: 134000 | F12: 0 | G12: =E12-F12 -> 134000 | H12: =IF(G12>0,TODAY()-C12,0) -> 63 | I12: =IF(G12=0,"Paid",IF(H12<=30,"Current",IF(H12<=60,"31-60",IF(H12<=90,"61-90","90+")))) -> 61-90 | J12: =IF(G12=0,"Paid",IF(H12<=30,"Current","Past Due")) -> Past Due | M12: Mar-26 | N12: 3750000 | O12: 715000 | P12: =N12/O12*30 -> 157.34266 | Q12: 690000
A13: INV-1012 | B13: Evergreen Health | C13: 46130 | D13: 46160 | E13: 298000 | F13: 0 | G13: =E13-F13 -> 298000 | H13: =IF(G13>0,TODAY()-C13,0) -> 48 | I13: =IF(G13=0,"Paid",IF(H13<=30,"Current",IF(H13<=60,"31-60",IF(H13<=90,"61-90","90+")))) -> 31-60 | J13: =IF(G13=0,"Paid",IF(H13<=30,"Current","Past Due")) -> Past Due | M13: Apr-26 | N13: 3890000 | O13: 740000 | P13: =N13/O13*30 -> 157.7027 | Q13: 715000
A14: INV-1013 | B14: Evergreen Health | C14: 46010 | D14: 46040 | E14: 185000 | F14: 0 | G14: =E14-F14 -> 185000 | H14: =IF(G14>0,TODAY()-C14,0) -> 168 | I14: =IF(G14=0,"Paid",IF(H14<=30,"Current",IF(H14<=60,"31-60",IF(H14<=90,"61-90","90+")))) -> 90+ | J14: =IF(G14=0,"Paid",IF(H14<=30,"Current","Past Due")) -> Past Due | M14: May-26 | N14: =SUMIF(J2:J35,"<>Paid",G2:G35) -> 5495500 | O14: 725000 | P14: =N14/O14*30 -> 227.4 | Q14: 740000
A15: INV-1014 | B15: Evergreen Health | C15: 45920 | D15: 45950 | E15: 142000 | F15: 50000 | G15: =E15-F15 -> 92000 | H15: =IF(G15>0,TODAY()-C15,0) -> 258 | I15: =IF(G15=0,"Paid",IF(H15<=30,"Current",IF(H15<=60,"31-60",IF(H15<=90,"61-90","90+")))) -> 90+ | J15: =IF(G15=0,"Paid",IF(H15<=30,"Current","Past Due")) -> Past Due | P15: =SUMIF(L3:L36,"<>Paid",I3:I36) -> 0 | Q15: 725000
A16: INV-1015 | B16: Frontier Software | C16: 46118 | D16: 46148 | E16: 78000 | F16: 0 | G16: =E16-F16 -> 78000 | H16: =IF(G16>0,TODAY()-C16,0) -> 60 | I16: =IF(G16=0,"Paid",IF(H16<=30,"Current",IF(H16<=60,"31-60",IF(H16<=90,"61-90","90+")))) -> 31-60 | J16: =IF(G16=0,"Paid",IF(H16<=30,"Current","Past Due")) -> Past Due
A17: INV-1016 | B17: Frontier Software | C17: 46000 | D17: 46030 | E17: 112000 | F17: 112000 | G17: =E17-F17 -> 0 | H17: =IF(G17>0,TODAY()-C17,0) -> 0 | I17: =IF(G17=0,"Paid",IF(H17<=30,"Current",IF(H17<=60,"31-60",IF(H17<=90,"61-90","90+")))) -> Paid | J17: =IF(G17=0,"Paid",IF(H17<=30,"Current","Past Due")) -> Paid
A18: INV-1017 | B18: GlobalTech Solutions | C18: 46142 | D18: 46172 | E18: 520000 | F18: 0 | G18: =E18-F18 -> 520000 | H18: =IF(G18>0,TODAY()-C18,0) -> 36 | I18: =IF(G18=0,"Paid",IF(H18<=30,"Current",IF(H18<=60,"31-60",IF(H18<=90,"61-90","90+")))) -> 31-60 | J18: =IF(G18=0,"Paid",IF(H18<=30,"Current","Past Due")) -> Past Due
A19: INV-1018 | B19: GlobalTech Solutions | C19: 46108 | D19: 46138 | E19: 345000 | F19: 200000 | G19: =E19-F19 -> 145000 | H19: =IF(G19>0,TODAY()-C19,0) -> 70 | I19: =IF(G19=0,"Paid",IF(H19<=30,"Current",IF(H19<=60,"31-60",IF(H19<=90,"61-90","90+")))) -> 61-90 | J19: =IF(G19=0,"Paid",IF(H19<=30,"Current","Past Due")) -> Past Due
A20: INV-1019 | B20: GlobalTech Solutions | C20: 45940 | D20: 45970 | E20: 275000 | F20: 275000 | G20: =E20-F20 -> 0 | H20: =IF(G20>0,TODAY()-C20,0) -> 0 | I20: =IF(G20=0,"Paid",IF(H20<=30,"Current",IF(H20<=60,"31-60",IF(H20<=90,"61-90","90+")))) -> Paid | J20: =IF(G20=0,"Paid",IF(H20<=30,"Current","Past Due")) -> Paid
A21: INV-1020 | B21: Harbor Financial | C21: 46112 | D21: 46142 | E21: 198000 | F21: 0 | G21: =E21-F21 -> 198000 | H21: =IF(G21>0,TODAY()-C21,0) -> 66 | I21: =IF(G21=0,"Paid",IF(H21<=30,"Current",IF(H21<=60,"31-60",IF(H21<=90,"61-90","90+")))) -> 61-90 | J21: =IF(G21=0,"Paid",IF(H21<=30,"Current","Past Due")) -> Past Due
A22: INV-1021 | B22: Harbor Financial | C22: 45985 | D22: 46015 | E22: 87000 | F22: 87000 | G22: =E22-F22 -> 0 | H22: =IF(G22>0,TODAY()-C22,0) -> 0 | I22: =IF(G22=0,"Paid",IF(H22<=30,"Current",IF(H22<=60,"31-60",IF(H22<=90,"61-90","90+")))) -> Paid | J22: =IF(G22=0,"Paid",IF(H22<=30,"Current","Past Due")) -> Paid
A23: INV-1022 | B23: Ironclad Manufacturing | C23: 46137 | D23: 46167 | E23: 445000 | F23: 0 | G23: =E23-F23 -> 445000 | H23: =IF(G23>0,TODAY()-C23,0) -> 41 | I23: =IF(G23=0,"Paid",IF(H23<=30,"Current",IF(H23<=60,"31-60",IF(H23<=90,"61-90","90+")))) -> 31-60 | J23: =IF(G23=0,"Paid",IF(H23<=30,"Current","Past Due")) -> Past Due
A24: INV-1023 | B24: Ironclad Manufacturing | C24: 46095 | D24: 46125 | E24: 367000 | F24: 0 | G24: =E24-F24 -> 367000 | H24: =IF(G24>0,TODAY()-C24,0) -> 83 | I24: =IF(G24=0,"Paid",IF(H24<=30,"Current",IF(H24<=60,"31-60",IF(H24<=90,"61-90","90+")))) -> 61-90 | J24: =IF(G24=0,"Paid",IF(H24<=30,"Current","Past Due")) -> Past Due
A25: INV-1024 | B25: Ironclad Manufacturing | C25: 45910 | D25: 45940 | E25: 290000 | F25: 190000 | G25: =E25-F25 -> 100000 | H25: =IF(G25>0,TODAY()-C25,0) -> 268 | I25: =IF(G25=0,"Paid",IF(H25<=30,"Current",IF(H25<=60,"31-60",IF(H25<=90,"61-90","90+")))) -> 90+ | J25: =IF(G25=0,"Paid",IF(H25<=30,"Current","Past Due")) -> Past Due
A26: INV-1025 | B26: Jetstream Aviation | C26: 46133 | D26: 46163 | E26: 156000 | F26: 0 | G26: =E26-F26 -> 156000 | H26: =IF(G26>0,TODAY()-C26,0) -> 45 | I26: =IF(G26=0,"Paid",IF(H26<=30,"Current",IF(H26<=60,"31-60",IF(H26<=90,"61-90","90+")))) -> 31-60 | J26: =IF(G26=0,"Paid",IF(H26<=30,"Current","Past Due")) -> Past Due
A27: INV-1027 | B27: Jetstream Aviation | C27: 45950 | D27: 45980 | E27: 223000 | F27: 100000 | G27: =E27-F27 -> 123000 | H27: =IF(G27>0,TODAY()-C27,0) -> 228 | I27: =IF(G27=0,"Paid",IF(H27<=30,"Current",IF(H27<=60,"31-60",IF(H27<=90,"61-90","90+")))) -> 90+ | J27: =IF(G27=0,"Paid",IF(H27<=30,"Current","Past Due")) -> Past Due
... A35: INV-1035 | B35: Nexus Consulting | C35: 45880 | D35: 45910 | E35: 195000 | F35: 0 | G35: =E35-F35 -> 195000 | H35: =IF(G35>0,TODAY()-C35,0) -> 298 | I35: =IF(G35=0,"Paid",IF(H35<=30,"Current",IF(H35<=60,"31-60",IF(H35<=90,"61-90","90+")))) -> 90+ | J35: =IF(G35=0,"Paid",IF(H35<=30,"Current","Past Due")) -> Past Due

Sheet Financial Summary
A1: __FIND_ME__
C2: Nimbus Cloud Solutions
C4: FINANCIAL SUMMARY
E5: 45292 | F5: 45323 | G5: 45352 | H5: 45383 | I5: 45413 | J5: 45444 | K5: 45474 | L5: 45505 | M5: 45536 | N5: 45566 | O5: 45597 | P5: 45627 | Q5: 45658 | R5: 45689 | S5: 45717 | T5: 45748 | U5: 45778 | V5: 45809 | W5: 45839 | X5: 45870 | Y5: 45901 | AA5: Q1 2024 | AB5: Q2 2024 | AC5: Q3 2024 | AD5: Q4 2024 | AE5: Q1 2025 | AF5: Q2 2025 | AG5: Q3 2025 | AI5: FY 2024 | AK5: YTD 2025 | AL5: TTM
E6: Monthly | F6: Monthly | G6: Monthly | H6: Monthly | I6: Monthly | J6: Monthly | K6: Monthly | L6: Monthly | M6: Monthly | N6: Monthly | O6: Monthly | P6: Monthly | Q6: Monthly | R6: Monthly | S6: Monthly | T6: Monthly | U6: Monthly | V6: Monthly | W6: Monthly | X6: Monthly | Y6: Monthly | AA6: Quarterly | AB6: Quarterly | AC6: Quarterly | AD6: Quarterly | AE6: Quarterly | AF6: Quarterly | AG6: Quarterly | AI6: Annual | AK6: Year-to-Date | AL6: Trailing 12 Mo.
B8: PROFIT & LOSS
C10: Revenue | E10: ='Data Summary'!N13 -> 48456.5 | F10: ='Data Summary'!O13 -> 42000 | G10: ='Data Summary'!P13 -> 50879.5 | H10: ='Data Summary'!Q13 -> 44100 | I10: ='Data Summary'!R13 -> 53424 | J10: ='Data Summary'!S13 -> 46305 | K10: ='Data Summary'!T13 -> 48620 | L10: ='Data Summary'!U13 -> 48620 | ... Y10: ='Data Summary'!AH13 -> 87314.98 | AA10: =SUM(E10:G10) -> 141336 | AB10: =SUM(H10:J10) -> 143829 | AC10: =SUM(K10:M10) -> 148291 | AD10: =SUM(N10:P10) -> 160939 | AE10: =SUM(Q10:S10) -> 186307.22 | AF10: =SUM(T10:V10) -> 224373.97 | AG10: =SUM(W10:Y10) -> 249669.37 | AI10: =SUM(E10:P10) -> 594395 | AK10: =SUM(Q10:Y10) -> 660350.56 | AL10: =SUM(N10:Y10) -> 821289.56
C11: Total Revenue | E11: =E10 -> 48456.5 | F11: =F10 -> 42000 | G11: =G10 -> 50879.5 | H11: =H10 -> 44100 | I11: =I10 -> 53424 | J11: =J10 -> 46305 | K11: =K10 -> 48620 | L11: =L10 -> 48620 | ... Y11: =Y10 -> 87314.98 | AA11: =AA10 -> 141336 | AB11: =AB10 -> 143829 | AC11: =AC10 -> 148291 | AD11: =AD10 -> 160939 | AE11: =AE10 -> 186307.22 | AF11: =AF10 -> 224373.97 | AG11: =AG10 -> 249669.37 | AI11: =AI10 -> 594395 | AK11: =AK10 -> 660350.56 | AL11: =AL10 -> 821289.56
C13: Cost of Goods Sold | E13: ='Data Summary'!N15+'Data Summary'!N16 -> 3599 | F13: ='Data Summary'!O15+'Data Summary'!O16 -> 3988 | G13: ='Data Summary'!P15+'Data Summary'!P16 -> 3779 | H13: ='Data Summary'!Q15+'Data Summary'!Q16 -> 4186.5 | I13: ='Data Summary'!R15+'Data Summary'!R16 -> 3968.5 | J13: ='Data Summary'!S15+'Data Summary'!S16 -> 4396.5 | K13: ='Data Summary'!T15+'Data Summary'!T16 -> 4615 | L13: ='Data Summary'!U15+'Data Summary'!U16 -> 4614.5 | ... Y13: ='Data Summary'!AH15+'Data Summary'!AH16 -> 8289.15 | AA13: =SUM(E13:G13) -> 11366 | AB13: =SUM(H13:J13) -> 12551.5 | AC13: =SUM(K13:M13) -> 14075.5 | AD13: =SUM(N13:P13) -> 15278.66 | AE13: =SUM(Q13:S13) -> 17685.42 | AF13: =SUM(T13:V13) -> 20775.48 | AG13: =SUM(W13:Y13) -> 22702.08 | AI13: =SUM(E13:P13) -> 53271.66 | AK13: =SUM(Q13:Y13) -> 61162.98 | AL13: =SUM(N13:Y13) -> 76441.64
C14: Gross Profit | E14: =E11-E13 -> 44857.5 | F14: =F11-F13 -> 38012 | G14: =G11-G13 -> 47100.5 | H14: =H11-H13 -> 39913.5 | I14: =I11-I13 -> 49455.5 | J14: =J11-J13 -> 41908.5 | K14: =K11-K13 -> 44005 | L14: =L11-L13 -> 44005.5 | ... Y14: =Y11-Y13 -> 79025.83 | AA14: =AA11-AA13 -> 129970 | AB14: =AB11-AB13 -> 131277.5 | AC14: =AC11-AC13 -> 134215.5 | AD14: =AD11-AD13 -> 145660.34 | AE14: =AE11-AE13 -> 168621.8 | AF14: =AF11-AF13 -> 203598.49 | AG14: =AG11-AG13 -> 226967.29 | AI14: =AI11-AI13 -> 541123.34 | AK14: =AK11-AK13 -> 599187.58 | AL14: =AL11-AL13 -> 744847.92
C16: Marketing & Advertising | E16: ='Data Summary'!N17 -> 27987 | F16: ='Data Summary'!O17 -> 44074 | G16: ='Data Summary'!P17 -> 29386 | H16: ='Data Summary'!Q17 -> 46277 | I16: ='Data Summary'!R17 -> 30855 | J16: ='Data Summary'!S17 -> 48591 | K16: ='Data Summary'!T17 -> 51020 | L16: ='Data Summary'!U17 -> 51020 | ... Y16: ='Data Summary'!AH17 -> 91625.69 | AA16: =SUM(E16:G16) -> 101447 | AB16: =SUM(H16:J16) -> 125723 | AC16: =SUM(K16:M16) -> 155612 | AD16: =SUM(N16:P16) -> 168885 | AE16: =SUM(Q16:S16) -> 195505.87 | AF16: =SUM(T16:V16) -> 226320.72 | AG16: =SUM(W16:Y16) -> 261995.46 | AI16: =SUM(E16:P16) -> 551667 | AK16: =SUM(Q16:Y16) -> 683822.05 | AL16: =SUM(N16:Y16) -> 852707.05
C17: Office & Other G&A | E17: ='Data Summary'!N18 -> 34792.5 | F17: ='Data Summary'!O18 -> 43606 | G17: ='Data Summary'!P18 -> 36531 | H17: ='Data Summary'!Q18 -> 45786 | I17: ='Data Summary'!R18 -> 38358 | J17: ='Data Summary'!S18 -> 48076.5 | K17: ='Data Summary'!T18 -> 50480 | L17: ='Data Summary'!U18 -> 50479.5 | ... Y17: ='Data Summary'!AH18 -> 90655.73 | AA17: =SUM(E17:G17) -> 114929.5 | AB17: =SUM(H17:J17) -> 132220.5 | AC17: =SUM(K17:M17) -> 153963.5 | AD17: =SUM(N17:P17) -> 167093.16 | AE17: =SUM(Q17:S17) -> 193436.37 | AF17: =SUM(T17:V17) -> 224926.82 | AG17: =SUM(W17:Y17) -> 259221.93 | AI17: =SUM(E17:P17) -> 568206.66 | AK17: =SUM(Q17:Y17) -> 677585.12 | AL17: =SUM(N17:Y17) -> 844678.28
C18: Payroll | E18: ='Data Summary'!N19 -> 22188 | F18: ='Data Summary'!O19 -> 39256 | G18: ='Data Summary'!P19 -> 23297 | H18: ='Data Summary'!Q19 -> 41219 | I18: ='Data Summary'!R19 -> 24463 | J18: ='Data Summary'!S19 -> 43279 | K18: ='Data Summary'!T19 -> 45443 | L18: ='Data Summary'!U19 -> 45443 | ... Y18: ='Data Summary'!AH19 -> 81610 | AA18: =SUM(E18:G18) -> 84741 | AB18: =SUM(H18:J18) -> 108961 | AC18: =SUM(K18:M18) -> 138602 | AD18: =SUM(N18:P18) -> 150425.68 | AE18: =SUM(Q18:S18) -> 174134.87 | AF18: =SUM(T18:V18) -> 201582.84 | AG18: =SUM(W18:Y18) -> 233356.49 | AI18: =SUM(E18:P18) -> 482729.68 | AK18: =SUM(Q18:Y18) -> 609074.2 | AL18: =SUM(N18:Y18) -> 759499.88
C19: Professional Services | E19: ='Data Summary'!N20 -> 8168 | F19: ='Data Summary'!O20 -> 14138 | G19: ='Data Summary'!P20 -> 8577 | H19: ='Data Summary'!Q20 -> 14845 | I19: ='Data Summary'!R20 -> 9005 | J19: ='Data Summary'!S20 -> 15587 | K19: ='Data Summary'!T20 -> 16368 | L19: ='Data Summary'!U20 -> 16368 | ... Y19: ='Data Summary'!AH20 -> 29392.09 | AA19: =SUM(E19:G19) -> 30883 | AB19: =SUM(H19:J19) -> 39437 | AC19: =SUM(K19:M19) -> 49920 | AD19: =SUM(N19:P19) -> 54175 | AE19: =SUM(Q19:S19) -> 62714.72 | AF19: =SUM(T19:V19) -> 72600 | AG19: =SUM(W19:Y19) -> 84044.04 | AI19: =SUM(E19:P19) -> 174415 | AK19: =SUM(Q19:Y19) -> 219358.76 | AL19: =SUM(N19:Y19) -> 273533.76
C20: Travel & Entertainment | E20: ='Data Summary'!N21 -> 3031 | F20: ='Data Summary'!O21 -> 4762 | G20: ='Data Summary'!P21 -> 3183 | H20: ='Data Summary'!Q21 -> 5001 | I20: ='Data Summary'!R21 -> 3341 | J20: ='Data Summary'!S21 -> 5251 | K20: ='Data Summary'!T21 -> 5514 | L20: ='Data Summary'!U21 -> 5514 | ... Y20: ='Data Summary'!AH21 -> 9901.11 | AA20: =SUM(E20:G20) -> 10976 | AB20: =SUM(H20:J20) -> 13593 | AC20: =SUM(K20:M20) -> 16817 | AD20: =SUM(N20:P20) -> 18250 | AE20: =SUM(Q20:S20) -> 21125.46 | AF20: =SUM(T20:V20) -> 24456.9 | AG20: =SUM(W20:Y20) -> 28311.36 | AI20: =SUM(E20:P20) -> 59636 | AK20: =SUM(Q20:Y20) -> 73893.72 | AL20: =SUM(N20:Y20) -> 92143.72
C21: Total Operating Expenses | E21: =SUM(E16:E20) -> 96166.5 | F21: =SUM(F16:F20) -> 145836 | G21: =SUM(G16:G20) -> 100974 | H21: =SUM(H16:H20) -> 153128 | I21: =SUM(I16:I20) -> 106022 | J21: =SUM(J16:J20) -> 160784.5 | K21: =SUM(K16:K20) -> 168825 | L21: =SUM(L16:L20) -> 168824.5 | ... Y21: =SUM(Y16:Y20) -> 303184.62 | AA21: =SUM(AA16:AA20) -> 342976.5 | AB21: =SUM(AB16:AB20) -> 419934.5 | AC21: =SUM(AC16:AC20) -> 514914.5 | AD21: =SUM(AD16:AD20) -> 558828.84 | AE21: =SUM(AE16:AE20) -> 646917.29 | AF21: =SUM(AF16:AF20) -> 749887.28 | AG21: =SUM(AG16:AG20) -> 866929.28 | AI21: =SUM(AI16:AI20) -> 1836654.3 | AK21: =SUM(AK16:AK20) -> 2263733.9 | AL21: =SUM(AL16:AL20) -> 2822562.7
C23: Operating Income (Loss) | E23: =E14-E21 -> -51309 | F23: =F14-F21 -> -107824 | G23: =G14-G21 -> -53873.5 | H23: =H14-H21 -> -113214.5 | I23: =I14-I21 -> -56566.5 | J23: =J14-J21 -> -118876 | K23: =K14-K21 -> -124820 | L23: =L14-L21 -> -124819 | ... Y23: =Y14-Y21 -> -224158.79 | AA23: =AA14-AA21 -> -213006.5 | AB23: =AB14-AB21 -> -288657 | AC23: =AC14-AC21 -> -380699 | AD23: =AD14-AD21 -> -413168.5 | AE23: =AE14-AE21 -> -478295.49 | AF23: =AF14-AF21 -> -546288.79 | AG23: =AG14-AG21 -> -639961.99 | AI23: =AI14-AI21 -> -1295531 | AK23: =AK14-AK21 -> -1664546.3 | AL23: =AL14-AL21 -> -2077714.8
C25: Other Income | E25: ='Data Summary'!N22 -> 0 | F25: ='Data Summary'!O22 -> 0 | G25: ='Data Summary'!P22 -> 0 | H25: ='Data Summary'!Q22 -> 0 | I25: ='Data Summary'!R22 -> 0 | J25: ='Data Summary'!S22 -> 0 | K25: ='Data Summary'!T22 -> 0 | L25: ='Data Summary'!U22 -> 0 | ... Y25: ='Data Summary'!AH22 -> 0 | AA25: =SUM(E25:G25) -> 0 | AB25: =SUM(H25:J25) -> 0 | AC25: =SUM(K25:M25) -> 0 | AD25: =SUM(N25:P25) -> 0 | AE25: =SUM(Q25:S25) -> 0 | AF25: =SUM(T25:V25) -> 0 | AG25: =SUM(W25:Y25) -> 0 | AI25: =SUM(E25:P25) -> 0 | AK25: =SUM(Q25:Y25) -> 0 | AL25: =SUM(N25:Y25) -> 0
C26: Depreciation & Amortization | E26: ='Data Summary'!N23 -> 0 | F26: ='Data Summary'!O23 -> 0 | G26: ='Data Summary'!P23 -> 0 | H26: ='Data Summary'!Q23 -> 0 | I26: ='Data Summary'!R23 -> 0 | J26: ='Data Summary'!S23 -> 0 | K26: ='Data Summary'!T23 -> 0 | L26: ='Data Summary'!U23 -> 0 | ... Y26: ='Data Summary'!AH23 -> 0 | AA26: =SUM(E26:G26) -> 0 | AB26: =SUM(H26:J26) -> 0 | AC26: =SUM(K26:M26) -> 0 | AD26: =SUM(N26:P26) -> 0 | AE26: =SUM(Q26:S26) -> 0 | AF26: =SUM(T26:V26) -> 0 | AG26: =SUM(W26:Y26) -> 0 | AI26: =SUM(E26:P26) -> 0 | AK26: =SUM(Q26:Y26) -> 0 | AL26: =SUM(N26:Y26) -> 0
C27: Other Expenses | E27: ='Data Summary'!N24+'Data Summary'!N25 -> 21495.5 | F27: ='Data Summary'!O24+'Data Summary'!O25 -> 21496 | G27: ='Data Summary'!P24+'Data Summary'!P25 -> 21496 | H27: ='Data Summary'!Q24+'Data Summary'!Q25 -> 21496 | I27: ='Data Summary'!R24+'Data Summary'!R25 -> 21496 | J27: ='Data Summary'!S24+'Data Summary'!S25 -> 21496 | K27: ='Data Summary'!T24+'Data Summary'!T25 -> 21496 | L27: ='Data Summary'!U24+'Data Summary'!U25 -> 21496 | ... Y27: ='Data Summary'!AH24+'Data Summary'!AH25 -> 21495.42 | AA27: =SUM(E27:G27) -> 64487.5 | AB27: =SUM(H27:J27) -> 64488 | AC27: =SUM(K27:M27) -> 64488 | AD27: =SUM(N27:P27) -> 64488 | AE27: =SUM(Q27:S27) -> 64486.74 | AF27: =SUM(T27:V27) -> 64486.74 | AG27: =SUM(W27:Y27) -> 64486.26 | AI27: =SUM(E27:P27) -> 257951.5 | AK27: =SUM(Q27:Y27) -> 193459.74 | AL27: =SUM(N27:Y27) -> 257947.74
C29: Net Income (Loss) | E29: =E23+E25-E26-E27 -> -72804.5 | F29: =F23+F25-F26-F27 -> -129320 | G29: =G23+G25-G26-G27 -> -75369.5 | H29: =H23+H25-H26-H27 -> -134710.5 | I29: =I23+I25-I26-I27 -> -78062.5 | J29: =J23+J25-J26-J27 -> -140372 | K29: =K23+K25-K26-K27 -> -146316 | L29: =L23+L25-L26-L27 -> -146315 | ... Y29: =Y23+Y25-Y26-Y27 -> -245654.21 | AA29: =AA23+AA25-AA26-AA27 -> -277494 | AB29: =AB23+AB25-AB26-AB27 -> -353145 | AC29: =AC23+AC25-AC26-AC27 -> -445187 | AD29: =AD23+AD25-AD26-AD27 -> -477656.5 | AE29: =AE23+AE25-AE26-AE27 -> -542782.23 | AF29: =AF23+AF25-AF26-AF27 -> -610775.53 | AG29: =AG23+AG25-AG26-AG27 -> -704448.25 | AI29: =AI23+AI25-AI26-AI27 -> -1553482.5 | AK29: =AK23+AK25-AK26-AK27 -> -1858006 | AL29: =AL23+AL25-AL26-AL27 -> -2335662.5
B32: BALANCE SHEET
C34: Assets
C35: Cash | E35: {=INDEX('Data Summary'!N$8:N$38,29-7)} -> 4191288.5 | F35: {=INDEX('Data Summary'!O$8:O$38,29-7)} -> 4076334.5 | G35: {=INDEX('Data Summary'!P$8:P$38,29-7)} -> 4004840.5 | H35: {=INDEX('Data Summary'!Q$8:Q$38,29-7)} -> 3870793.5 | I35: {=INDEX('Data Summary'!R$8:R$38,29-7)} -> 3794994.5 | J35: {=INDEX('Data Summary'!S$8:S$38,29-7)} -> 3656851.5 | K35: {=INDEX('Data Summary'!T$8:T$38,29-7)} -> 3512188.5 | L35: {=INDEX('Data Summary'!U$8:U$38,29-7)} -> 3367871.5 | ... Y35: {=INDEX('Data Summary'!AH$8:AH$38,29-7)} -> 893122.77 | AA35: =G35 -> 4004840.5 | AB35: =J35 -> 3656851.5 | AC35: =M35 -> 3217220.5 | AD35: =P35 -> 2744982.5 | AE35: =S35 -> 2207358.5 | AF35: =V35 -> 1594040.1 | AG35: =Y35 -> 893122.77 | AI35: =P35 -> 2744982.5 | AK35: =Y35 -> 893122.77 | AL35: =Y35 -> 893122.77
C36: Accounts Receivable | E36: {=INDEX('Data Summary'!N$8:N$38,28-7)} -> 41127 | F36: {=INDEX('Data Summary'!O$8:O$38,28-7)} -> 41812 | G36: {=INDEX('Data Summary'!P$8:P$38,28-7)} -> 40987 | H36: {=INDEX('Data Summary'!Q$8:Q$38,28-7)} -> 43374 | I36: {=INDEX('Data Summary'!R$8:R$38,28-7)} -> 44161 | J36: {=INDEX('Data Summary'!S$8:S$38,28-7)} -> 44983 | K36: {=INDEX('Data Summary'!T$8:T$38,28-7)} -> 46381 | L36: {=INDEX('Data Summary'!U$8:U$38,28-7)} -> 47434 | ... Y36: {=INDEX('Data Summary'!AH$8:AH$38,28-7)} -> 73923.66 | AA36: =G36 -> 40987 | AB36: =J36 -> 44983 | AC36: =M36 -> 48580 | AD36: =P36 -> 52314 | AE36: =S36 -> 56307.77 | AF36: =V36 -> 69302.55 | AG36: =Y36 -> 73923.66 | AI36: =P36 -> 52314 | AK36: =Y36 -> 73923.66 | AL36: =Y36 -> 73923.66
C37: Current Assets | E37: {=INDEX('Data Summary'!N$8:N$38,30-7)} -> 26119.5 | F37: {=INDEX('Data Summary'!O$8:O$38,30-7)} -> 26119.5 | G37: {=INDEX('Data Summary'!P$8:P$38,30-7)} -> 26119.5 | H37: {=INDEX('Data Summary'!Q$8:Q$38,30-7)} -> 26119.5 | I37: {=INDEX('Data Summary'!R$8:R$38,30-7)} -> 26119.5 | J37: {=INDEX('Data Summary'!S$8:S$38,30-7)} -> 26119.5 | K37: {=INDEX('Data Summary'!T$8:T$38,30-7)} -> 26119.5 | L37: {=INDEX('Data Summary'!U$8:U$38,30-7)} -> 26119.5 | ... Y37: {=INDEX('Data Summary'!AH$8:AH$38,30-7)} -> 26819.5 | AA37: =G37 -> 26119.5 | AB37: =J37 -> 26119.5 | AC37: =M37 -> 26119.5 | AD37: =P37 -> 26119.5 | AE37: =S37 -> 26119.5 | AF37: =V37 -> 25819.5 | AG37: =Y37 -> 26819.5 | AI37: =P37 -> 26119.5 | AK37: =Y37 -> 26819.5 | AL37: =Y37 -> 26819.5
C38: Fixed Assets | E38: {=INDEX('Data Summary'!N$8:N$38,31-7)} -> 112416.5 | F38: {=INDEX('Data Summary'!O$8:O$38,31-7)} -> 97365.5 | G38: {=INDEX('Data Summary'!P$8:P$38,31-7)} -> 94315 | H38: {=INDEX('Data Summary'!Q$8:Q$38,31-7)} -> 91264.5 | I38: {=INDEX('Data Summary'!R$8:R$38,31-7)} -> 88214 | J38: {=INDEX('Data Summary'!S$8:S$38,31-7)} -> 85163 | K38: {=INDEX('Data Summary'!T$8:T$38,31-7)} -> 82112 | L38: {=INDEX('Data Summary'!U$8:U$38,31-7)} -> 79061 | ... Y38: {=INDEX('Data Summary'!AH$8:AH$38,31-7)} -> 39401.56 | AA38: =G38 -> 94315 | AB38: =J38 -> 85163 | AC38: =M38 -> 76010 | AD38: =P38 -> 66857.5 | AE38: =S38 -> 57705.52 | AF38: =V38 -> 48553.54 | AG38: =Y38 -> 39401.56 | AI38: =P38 -> 66857.5 | AK38: =Y38 -> 39401.56 | AL38: =Y38 -> 39401.56
C39: Other Current Assets | E39: {=INDEX('Data Summary'!N$8:N$38,32-7)} -> 0 | F39: {=INDEX('Data Summary'!O$8:O$38,32-7)} -> 0 | G39: {=INDEX('Data Summary'!P$8:P$38,32-7)} -> 0 | H39: {=INDEX('Data Summary'!Q$8:Q$38,32-7)} -> 0 | I39: {=INDEX('Data Summary'!R$8:R$38,32-7)} -> 0 | J39: {=INDEX('Data Summary'!S$8:S$38,32-7)} -> 0 | K39: {=INDEX('Data Summary'!T$8:T$38,32-7)} -> 0 | L39: {=INDEX('Data Summary'!U$8:U$38,32-7)} -> 0 | ... Y39: {=INDEX('Data Summary'!AH$8:AH$38,32-7)} -> 0 | AA39: =G39 -> 0 | AB39: =J39 -> 0 | AC39: =M39 -> 0 | AD39: =P39 -> 0 | AE39: =S39 -> 0 | AF39: =V39 -> 0 | AG39: =Y39 -> 0 | AI39: =P39 -> 0 | AK39: =Y39 -> 0 | AL39: =Y39 -> 0
C40: Total Assets | E40: =SUM(E35:E39) -> 4370951.5 | F40: =SUM(F35:F39) -> 4241631.5 | G40: =SUM(G35:G39) -> 4166262 | H40: =SUM(H35:H39) -> 4031551.5 | I40: =SUM(I35:I39) -> 3953489 | J40: =SUM(J35:J39) -> 3813117 | K40: =SUM(K35:K39) -> 3666801 | L40: =SUM(L35:L39) -> 3520486 | ... Y40: =SUM(Y35:Y39) -> 1033267.5 | AA40: =SUM(AA35:AA39) -> 4166262 | AB40: =SUM(AB35:AB39) -> 3813117 | AC40: =SUM(AC35:AC39) -> 3367930 | AD40: =SUM(AD35:AD39) -> 2890273.5 | AE40: =SUM(AE35:AE39) -> 2347491.3 | AF40: =SUM(AF35:AF39) -> 1737715.7 | AG40: =SUM(AG35:AG39) -> 1033267.5 | AI40: =SUM(AI35:AI39) -> 2890273.5 | AK40: =SUM(AK35:AK39) -> 1033267.5 | AL40: =SUM(AL35:AL39) -> 1033267.5
C42: Liabilities
C43: Accounts Payable | E43: {=INDEX('Data Summary'!N$8:N$38,33-7)} -> 55349.5 | F43: {=INDEX('Data Summary'!O$8:O$38,33-7)} -> 55349.5 | G43: {=INDEX('Data Summary'!P$8:P$38,33-7)} -> 55349.5 | H43: {=INDEX('Data Summary'!Q$8:Q$38,33-7)} -> 55349.5 | I43: {=INDEX('Data Summary'!R$8:R$38,33-7)} -> 55349.5 | J43: {=INDEX('Data Summary'!S$8:S$38,33-7)} -> 55349.5 | K43: {=INDEX('Data Summary'!T$8:T$38,33-7)} -> 55349.5 | L43: {=INDEX('Data Summary'!U$8:U$38,33-7)} -> 55349.5 | ... Y43: {=INDEX('Data Summary'!AH$8:AH$38,33-7)} -> 56349.5 | AA43: =G43 -> 55349.5 | AB43: =J43 -> 55349.5 | AC43: =M43 -> 55349.5 | AD43: =P43 -> 55349.5 | AE43: =S43 -> 55349.5 | AF43: =V43 -> 56349.5 | AG43: =Y43 -> 56349.5 | AI43: =P43 -> 55349.5 | AK43: =Y43 -> 56349.5 | AL43: =Y43 -> 56349.5
C44: Current Liabilities | E44: {=INDEX('Data Summary'!N$8:N$38,34-7)} -> -4942 | F44: {=INDEX('Data Summary'!O$8:O$38,34-7)} -> -4942 | G44: {=INDEX('Data Summary'!P$8:P$38,34-7)} -> -4942 | H44: {=INDEX('Data Summary'!Q$8:Q$38,34-7)} -> -4942 | I44: {=INDEX('Data Summary'!R$8:R$38,34-7)} -> -4942 | J44: {=INDEX('Data Summary'!S$8:S$38,34-7)} -> -4942 | K44: {=INDEX('Data Summary'!T$8:T$38,34-7)} -> -4942 | L44: {=INDEX('Data Summary'!U$8:U$38,34-7)} -> -4942 | ... Y44: {=INDEX('Data Summary'!AH$8:AH$38,34-7)} -> -4942 | AA44: =G44 -> -4942 | AB44: =J44 -> -4942 | AC44: =M44 -> -4942 | AD44: =P44 -> -4942 | AE44: =S44 -> -4942 | AF44: =V44 -> -4942 | AG44: =Y44 -> -4942 | AI44: =P44 -> -4942 | AK44: =Y44 -> -4942 | AL44: =Y44 -> -4942
C45: Debt | E45: {=INDEX('Data Summary'!N$8:N$38,35-7)} -> 1530000 | F45: {=INDEX('Data Summary'!O$8:O$38,35-7)} -> 1530000 | G45: {=INDEX('Data Summary'!P$8:P$38,35-7)} -> 1530000 | H45: {=INDEX('Data Summary'!Q$8:Q$38,35-7)} -> 1530000 | I45: {=INDEX('Data Summary'!R$8:R$38,35-7)} -> 1530000 | J45: {=INDEX('Data Summary'!S$8:S$38,35-7)} -> 1530000 | K45: {=INDEX('Data Summary'!T$8:T$38,35-7)} -> 1530000 | L45: {=INDEX('Data Summary'!U$8:U$38,35-7)} -> 1530000 | ... Y45: {=INDEX('Data Summary'!AH$8:AH$38,35-7)} -> 1530000 | AA45: =G45 -> 1530000 | AB45: =J45 -> 1530000 | AC45: =M45 -> 1530000 | AD45: =P45 -> 1530000 | AE45: =S45 -> 1530000 | AF45: =V45 -> 1530000 | AG45: =Y45 -> 1530000 | AI45: =P45 -> 1530000 | AK45: =Y45 -> 1530000 | AL45: =Y45 -> 1530000
C46: Deferred Revenue | E46: {=INDEX('Data Summary'!N$8:N$38,36-7)} -> 23270 | F46: {=INDEX('Data Summary'!O$8:O$38,36-7)} -> 23270 | G46: {=INDEX('Data Summary'!P$8:P$38,36-7)} -> 23270 | H46: {=INDEX('Data Summary'!Q$8:Q$38,36-7)} -> 23270 | I46: {=INDEX('Data Summary'!R$8:R$38,36-7)} -> 23270 | J46: {=INDEX('Data Summary'!S$8:S$38,36-7)} -> 23270 | K46: {=INDEX('Data Summary'!T$8:T$38,36-7)} -> 23270 | L46: {=INDEX('Data Summary'!U$8:U$38,36-7)} -> 23270 | ... Y46: {=INDEX('Data Summary'!AH$8:AH$38,36-7)} -> 23270 | AA46: =G46 -> 23270 | AB46: =J46 -> 23270 | AC46: =M46 -> 23270 | AD46: =P46 -> 23270 | AE46: =S46 -> 23270 | AF46: =V46 -> 23270 | AG46: =Y46 -> 23270 | AI46: =P46 -> 23270 | AK46: =Y46 -> 23270 | AL46: =Y46 -> 23270
C47: Total Liabilities | E47: =SUM(E43:E46) -> 1603677.5 | F47: =SUM(F43:F46) -> 1603677.5 | G47: =SUM(G43:G46) -> 1603677.5 | H47: =SUM(H43:H46) -> 1603677.5 | I47: =SUM(I43:I46) -> 1603677.5 | J47: =SUM(J43:J46) -> 1603677.5 | K47: =SUM(K43:K46) -> 1603677.5 | L47: =SUM(L43:L46) -> 1603677.5 | ... Y47: =SUM(Y43:Y46) -> 1604677.5 | AA47: =SUM(AA43:AA46) -> 1603677.5 | AB47: =SUM(AB43:AB46) -> 1603677.5 | AC47: =SUM(AC43:AC46) -> 1603677.5 | AD47: =SUM(AD43:AD46) -> 1603677.5 | AE47: =SUM(AE43:AE46) -> 1603677.5 | AF47: =SUM(AF43:AF46) -> 1604677.5 | AG47: =SUM(AG43:AG46) -> 1604677.5 | AI47: =SUM(AI43:AI46) -> 1603677.5 | AK47: =SUM(AK43:AK46) -> 1604677.5 | AL47: =SUM(AL43:AL46) -> 1604677.5
C49: Equity
C50: Contributed Capital | E50: {=INDEX('Data Summary'!N$8:N$38,37-7)} -> 3500000 | F50: {=INDEX('Data Summary'!O$8:O$38,37-7)} -> 3500000 | G50: {=INDEX('Data Summary'!P$8:P$38,37-7)} -> 3500000 | H50: {=INDEX('Data Summary'!Q$8:Q$38,37-7)} -> 3500000 | I50: {=INDEX('Data Summary'!R$8:R$38,37-7)} -> 3500000 | J50: {=INDEX('Data Summary'!S$8:S$38,37-7)} -> 3500000 | K50: {=INDEX('Data Summary'!T$8:T$38,37-7)} -> 3500000 | L50: {=INDEX('Data Summary'!U$8:U$38,37-7)} -> 3500000 | ... Y50: {=INDEX('Data Summary'!AH$8:AH$38,37-7)} -> 3500000 | AA50: =G50 -> 3500000 | AB50: =J50 -> 3500000 | AC50: =M50 -> 3500000 | AD50: =P50 -> 3500000 | AE50: =S50 -> 3500000 | AF50: =V50 -> 3500000 | AG50: =Y50 -> 3500000 | AI50: =P50 -> 3500000 | AK50: =Y50 -> 3500000 | AL50: =Y50 -> 3500000
C51: Retained Earnings | E51: {=INDEX('Data Summary'!N$8:N$38,38-7)} -> -732726 | F51: {=INDEX('Data Summary'!O$8:O$38,38-7)} -> -862046 | G51: {=INDEX('Data Summary'!P$8:P$38,38-7)} -> -937415.5 | H51: {=INDEX('Data Summary'!Q$8:Q$38,38-7)} -> -1072126 | I51: {=INDEX('Data Summary'!R$8:R$38,38-7)} -> -1150188.5 | J51: {=INDEX('Data Summary'!S$8:S$38,38-7)} -> -1290560.5 | K51: {=INDEX('Data Summary'!T$8:T$38,38-7)} -> -1436876.5 | L51: {=INDEX('Data Summary'!U$8:U$38,38-7)} -> -1583191.5 | ... Y51: {=INDEX('Data Summary'!AH$8:AH$38,38-7)} -> -4071410 | AA51: =G51 -> -937415.5 | AB51: =J51 -> -1290560.5 | AC51: =M51 -> -1735747.5 | AD51: =P51 -> -2213404 | AE51: =S51 -> -2756186.2 | AF51: =V51 -> -3366961.8 | AG51: =Y51 -> -4071410 | AI51: =P51 -> -2213404 | AK51: =Y51 -> -4071410 | AL51: =Y51 -> -4071410
C52: Total Equity | E52: =E50+E51 -> 2767274 | F52: =F50+F51 -> 2637954 | G52: =G50+G51 -> 2562584.5 | H52: =H50+H51 -> 2427874 | I52: =I50+I51 -> 2349811.5 | J52: =J50+J51 -> 2209439.5 | K52: =K50+K51 -> 2063123.5 | L52: =L50+L51 -> 1916808.5 | ... Y52: =Y50+Y51 -> -571410.01 | AA52: =AA50+AA51 -> 2562584.5 | AB52: =AB50+AB51 -> 2209439.5 | AC52: =AC50+AC51 -> 1764252.5 | AD52: =AD50+AD51 -> 1286596 | AE52: =AE50+AE51 -> 743813.77 | AF52: =AF50+AF51 -> 133038.24 | AG52: =AG50+AG51 -> -571410.01 | AI52: =AI50+AI51 -> 1286596 | AK52: =AK50+AK51 -> -571410.01 | AL52: =AL50+AL51 -> -571410.01
C54: Total Liabilities & Equity | E54: =E47+E52 -> 4370951.5 | F54: =F47+F52 -> 4241631.5 | G54: =G47+G52 -> 4166262 | H54: =H47+H52 -> 4031551.5 | I54: =I47+I52 -> 3953489 | J54: =J47+J52 -> 3813117 | K54: =K47+K52 -> 3666801 | L54: =L47+L52 -> 3520486 | ... Y54: =Y47+Y52 -> 1033267.5 | AA54: =AA47+AA52 -> 4166262 | AB54: =AB47+AB52 -> 3813117 | AC54: =AC47+AC52 -> 3367930 | AD54: =AD47+AD52 -> 2890273.5 | AE54: =AE47+AE52 -> 2347491.3 | AF54: =AF47+AF52 -> 1737715.7 | AG54: =AG47+AG52 -> 1033267.5 | AI54: =AI47+AI52 -> 2890273.5 | AK54: =AK47+AK52 -> 1033267.5 | AL54: =AL47+AL52 -> 1033267.5
B57: CASH FLOW STATEMENT
C59: Cash from Operations
C60: Net Income (Loss) | E60: =E29 -> -72804.5 | F60: =F29 -> -129320 | G60: =G29 -> -75369.5 | H60: =H29 -> -134710.5 | I60: =I29 -> -78062.5 | J60: =J29 -> -140372 | K60: =K29 -> -146316 | L60: =L29 -> -146315 | ... Y60: =Y29 -> -245654.21 | AA60: =SUM(E60:G60) -> -277494 | AB60: =SUM(H60:J60) -> -353145 | AC60: =SUM(K60:M60) -> -445187 | AD60: =SUM(N60:P60) -> -477656.5 | AE60: =SUM(Q60:S60) -> -542782.23 | AF60: =SUM(T60:V60) -> -610775.53 | AG60: =SUM(W60:Y60) -> -704448.25 | AI60: =SUM(E60:P60) -> -1553482.5 | AK60: =SUM(Q60:Y60) -> -1858006 | AL60: =SUM(N60:Y60) -> -2335662.5
C61: Depreciation & Amortization | E61: =E26 -> 0 | F61: =F26 -> 0 | G61: =G26 -> 0 | H61: =H26 -> 0 | I61: =I26 -> 0 | J61: =J26 -> 0 | K61: =K26 -> 0 | L61: =L26 -> 0 | ... Y61: =Y26 -> 0 | AA61: =SUM(E61:G61) -> 0 | AB61: =SUM(H61:J61) -> 0 | AC61: =SUM(K61:M61) -> 0 | AD61: =SUM(N61:P61) -> 0 | AE61: =SUM(Q61:S61) -> 0 | AF61: =SUM(T61:V61) -> 0 | AG61: =SUM(W61:Y61) -> 0 | AI61: =SUM(E61:P61) -> 0 | AK61: =SUM(Q61:Y61) -> 0 | AL61: =SUM(N61:Y61) -> 0
C63: Changes in Working Capital
C64: (Inc)/Dec in Accounts Receivable | E64: {=-(E36-INDEX('Data Summary'!M$8:M$38,28-7))} -> -6958 | F64: =-(F36-E36) -> -685 | G64: =-(G36-F36) -> 825 | H64: =-(H36-G36) -> -2387 | I64: =-(I36-H36) -> -787 | J64: =-(J36-I36) -> -822 | K64: =-(K36-J36) -> -1398 | L64: =-(L36-K36) -> -1053 | M64: =-(M36-L36) -> -1146 | ... Y64: =-(Y36-X36) -> -1578.34 | AA64: =SUM(E64:G64) -> -6818 | AB64: =SUM(H64:J64) -> -3996 | AC64: =SUM(K64:M64) -> -3597 | AD64: =SUM(N64:P64) -> -3734 | AE64: =SUM(Q64:S64) -> -3993.77 | AF64: =SUM(T64:V64) -> -12994.78 | AG64: =SUM(W64:Y64) -> -4621.11 | AI64: =SUM(E64:P64) -> -18145 | AK64: =SUM(Q64:Y64) -> -21609.66 | AL64: =SUM(N64:Y64) -> -25343.66
C65: (Inc)/Dec in Current Assets | E65: {=-(E37-INDEX('Data Summary'!M$8:M$38,30-7))} -> 0 | F65: =-(F37-E37) -> 0 | G65: =-(G37-F37) -> 0 | H65: =-(H37-G37) -> 0 | I65: =-(I37-H37) -> 0 | J65: =-(J37-I37) -> 0 | K65: =-(K37-J37) -> 0 | L65: =-(L37-K37) -> 0 | M65: =-(M37-L37) -> 0 | ... Y65: =-(Y37-X37) -> 0 | AA65: =SUM(E65:G65) -> 0 | AB65: =SUM(H65:J65) -> 0 | AC65: =SUM(K65:M65) -> 0 | AD65: =SUM(N65:P65) -> 0 | AE65: =SUM(Q65:S65) -> 0 | AF65: =SUM(T65:V65) -> 300 | AG65: =SUM(W65:Y65) -> -1000 | AI65: =SUM(E65:P65) -> 0 | AK65: =SUM(Q65:Y65) -> -700 | AL65: =SUM(N65:Y65) -> -700
C66: (Inc)/Dec in Other Current Assets | E66: {=-(E39-INDEX('Data Summary'!M$8:M$38,32-7))} -> 0 | F66: =-(F39-E39) -> 0 | G66: =-(G39-F39) -> 0 | H66: =-(H39-G39) -> 0 | I66: =-(I39-H39) -> 0 | J66: =-(J39-I39) -> 0 | K66: =-(K39-J39) -> 0 | L66: =-(L39-K39) -> 0 | M66: =-(M39-L39) -> 0 | ... Y66: =-(Y39-X39) -> 0 | AA66: =SUM(E66:G66) -> 0 | AB66: =SUM(H66:J66) -> 0 | AC66: =SUM(K66:M66) -> 0 | AD66: =SUM(N66:P66) -> 0 | AE66: =SUM(Q66:S66) -> 0 | AF66: =SUM(T66:V66) -> 0 | AG66: =SUM(W66:Y66) -> 0 | AI66: =SUM(E66:P66) -> 0 | AK66: =SUM(Q66:Y66) -> 0 | AL66: =SUM(N66:Y66) -> 0
C67: Inc/(Dec) in Accounts Payable | E67: {=E43-INDEX('Data Summary'!M$8:M$38,33-7)} -> 0 | F67: =F43-E43 -> 0 | G67: =G43-F43 -> 0 | H67: =H43-G43 -> 0 | I67: =I43-H43 -> 0 | J67: =J43-I43 -> 0 | K67: =K43-J43 -> 0 | L67: =L43-K43 -> 0 | M67: =M43-L43 -> 0 | ... Y67: =Y43-X43 -> 0 | AA67: =SUM(E67:G67) -> 0 | AB67: =SUM(H67:J67) -> 0 | AC67: =SUM(K67:M67) -> 0 | AD67: =SUM(N67:P67) -> 0 | AE67: =SUM(Q67:S67) -> 0 | AF67: =SUM(T67:V67) -> 1000 | AG67: =SUM(W67:Y67) -> 0 | AI67: =SUM(E67:P67) -> 0 | AK67: =SUM(Q67:Y67) -> 1000 | AL67: =SUM(N67:Y67) -> 1000
C68: Inc/(Dec) in Current Liabilities | E68: {=E44-INDEX('Data Summary'!M$8:M$38,34-7)} -> 0 | F68: =F44-E44 -> 0 | G68: =G44-F44 -> 0 | H68: =H44-G44 -> 0 | I68: =I44-H44 -> 0 | J68: =J44-I44 -> 0 | K68: =K44-J44 -> 0 | L68: =L44-K44 -> 0 | M68: =M44-L44 -> 0 | ... Y68: =Y44-X44 -> 0 | AA68: =SUM(E68:G68) -> 0 | AB68: =SUM(H68:J68) -> 0 | AC68: =SUM(K68:M68) -> 0 | AD68: =SUM(N68:P68) -> 0 | AE68: =SUM(Q68:S68) -> 0 | AF68: =SUM(T68:V68) -> 0 | AG68: =SUM(W68:Y68) -> 0 | AI68: =SUM(E68:P68) -> 0 | AK68: =SUM(Q68:Y68) -> 0 | AL68: =SUM(N68:Y68) -> 0
C69: Inc/(Dec) in Deferred Revenue | E69: {=E46-INDEX('Data Summary'!M$8:M$38,36-7)} -> 0 | F69: =F46-E46 -> 0 | G69: =G46-F46 -> 0 | H69: =H46-G46 -> 0 | I69: =I46-H46 -> 0 | J69: =J46-I46 -> 0 | K69: =K46-J46 -> 0 | L69: =L46-K46 -> 0 | M69: =M46-L46 -> 0 | ... Y69: =Y46-X46 -> 0 | AA69: =SUM(E69:G69) -> 0 | AB69: =SUM(H69:J69) -> 0 | AC69: =SUM(K69:M69) -> 0 | AD69: =SUM(N69:P69) -> 0 | AE69: =SUM(Q69:S69) -> 0 | AF69: =SUM(T69:V69) -> 0 | AG69: =SUM(W69:Y69) -> 0 | AI69: =SUM(E69:P69) -> 0 | AK69: =SUM(Q69:Y69) -> 0 | AL69: =SUM(N69:Y69) -> 0
C70: Net Cash from Operations | E70: =E60+E61+SUM(E64:E69) -> -79762.5 | F70: =F60+F61+SUM(F64:F69) -> -130005 | G70: =G60+G61+SUM(G64:G69) -> -74544.5 | H70: =H60+H61+SUM(H64:H69) -> -137097.5 | I70: =I60+I61+SUM(I64:I69) -> -78849.5 | J70: =J60+J61+SUM(J64:J69) -> -141194 | K70: =K60+K61+SUM(K64:K69) -> -147714 | L70: =L60+L61+SUM(L64:L69) -> -147368 | ... Y70: =Y60+Y61+SUM(Y64:Y69) -> -247232.55 | AA70: =AA60+AA61+SUM(AA64:AA69) -> -284312 | AB70: =AB60+AB61+SUM(AB64:AB69) -> -357141 | AC70: =AC60+AC61+SUM(AC64:AC69) -> -448784 | AD70: =AD60+AD61+SUM(AD64:AD69) -> -481390.5 | AE70: =AE60+AE61+SUM(AE64:AE69) -> -546776 | AF70: =AF60+AF61+SUM(AF64:AF69) -> -622470.31 | AG70: =AG60+AG61+SUM(AG64:AG69) -> -710069.36 | AI70: =AI60+AI61+SUM(AI64:AI69) -> -1571627.5 | AK70: =AK60+AK61+SUM(AK64:AK69) -> -1879315.7 | AL70: =AL60+AL61+SUM(AL64:AL69) -> -2360706.2
C72: Cash from Investing
C73: Capital Expenditures (Net) | E73: {=-(E38-INDEX('Data Summary'!M$8:M$38,31-7))-E61} -> -13949.5 | F73: =-(F38-E38)-F61 -> 15051 | G73: =-(G38-F38)-G61 -> 3050.5 | H73: =-(H38-G38)-H61 -> 3050.5 | I73: =-(I38-H38)-I61 -> 3050.5 | J73: =-(J38-I38)-J61 -> 3051 | K73: =-(K38-J38)-K61 -> 3051 | L73: =-(L38-K38)-L61 -> 3051 | M73: =-(M38-L38)-M61 -> 3051 | ... Y73: =-(Y38-X38)-Y61 -> 3050.66 | AA73: =SUM(E73:G73) -> 4152 | AB73: =SUM(H73:J73) -> 9152 | AC73: =SUM(K73:M73) -> 9153 | AD73: =SUM(N73:P73) -> 9152.5 | AE73: =SUM(Q73:S73) -> 9151.98 | AF73: =SUM(T73:V73) -> 9151.98 | AG73: =SUM(W73:Y73) -> 9151.98 | AI73: =SUM(E73:P73) -> 31609.5 | AK73: =SUM(Q73:Y73) -> 27455.94 | AL73: =SUM(N73:Y73) -> 36608.44
C74: Net Cash from Investing | E74: =E73 -> -13949.5 | F74: =F73 -> 15051 | G74: =G73 -> 3050.5 | H74: =H73 -> 3050.5 | I74: =I73 -> 3050.5 | J74: =J73 -> 3051 | K74: =K73 -> 3051 | L74: =L73 -> 3051 | ... Y74: =Y73 -> 3050.66 | AA74: =AA73 -> 4152 | AB74: =AB73 -> 9152 | AC74: =AC73 -> 9153 | AD74: =AD73 -> 9152.5 | AE74: =AE73 -> 9151.98 | AF74: =AF73 -> 9151.98 | AG74: =AG73 -> 9151.98 | AI74: =AI73 -> 31609.5 | AK74: =AK73 -> 27455.94 | AL74: =AL73 -> 36608.44
C76: Cash from Financing
C77: Inc/(Dec) in Debt | E77: {=E45-INDEX('Data Summary'!M$8:M$38,35-7)} -> 0 | F77: =F45-E45 -> 0 | G77: =G45-F45 -> 0 | H77: =H45-G45 -> 0 | I77: =I45-H45 -> 0 | J77: =J45-I45 -> 0 | K77: =K45-J45 -> 0 | L77: =L45-K45 -> 0 | M77: =M45-L45 -> 0 | ... Y77: =Y45-X45 -> 0 | AA77: =SUM(E77:G77) -> 0 | AB77: =SUM(H77:J77) -> 0 | AC77: =SUM(K77:M77) -> 0 | AD77: =SUM(N77:P77) -> 0 | AE77: =SUM(Q77:S77) -> 0 | AF77: =SUM(T77:V77) -> 0 | AG77: =SUM(W77:Y77) -> 0 | AI77: =SUM(E77:P77) -> 0 | AK77: =SUM(Q77:Y77) -> 0 | AL77: =SUM(N77:Y77) -> 0
C78: Inc/(Dec) in Contributed Capital | E78: {=E50-INDEX('Data Summary'!M$8:M$38,37-7)} -> 0 | F78: =F50-E50 -> 0 | G78: =G50-F50 -> 0 | H78: =H50-G50 -> 0 | I78: =I50-H50 -> 0 | J78: =J50-I50 -> 0 | K78: =K50-J50 -> 0 | L78: =L50-K50 -> 0 | M78: =M50-L50 -> 0 | ... Y78: =Y50-X50 -> 0 | AA78: =SUM(E78:G78) -> 0 | AB78: =SUM(H78:J78) -> 0 | AC78: =SUM(K78:M78) -> 0 | AD78: =SUM(N78:P78) -> 0 | AE78: =SUM(Q78:S78) -> 0 | AF78: =SUM(T78:V78) -> 0 | AG78: =SUM(W78:Y78) -> 0 | AI78: =SUM(E78:P78) -> 0 | AK78: =SUM(Q78:Y78) -> 0 | AL78: =SUM(N78:Y78) -> 0
C79: Net Cash from Financing | E79: =SUM(E77:E78) -> 0 | F79: =SUM(F77:F78) -> 0 | G79: =SUM(G77:G78) -> 0 | H79: =SUM(H77:H78) -> 0 | I79: =SUM(I77:I78) -> 0 | J79: =SUM(J77:J78) -> 0 | K79: =SUM(K77:K78) -> 0 | L79: =SUM(L77:L78) -> 0 | ... Y79: =SUM(Y77:Y78) -> 0 | AA79: =SUM(AA77:AA78) -> 0 | AB79: =SUM(AB77:AB78) -> 0 | AC79: =SUM(AC77:AC78) -> 0 | AD79: =SUM(AD77:AD78) -> 0 | AE79: =SUM(AE77:AE78) -> 0 | AF79: =SUM(AF77:AF78) -> 0 | AG79: =SUM(AG77:AG78) -> 0 | AI79: =SUM(AI77:AI78) -> 0 | AK79: =SUM(AK77:AK78) -> 0 | AL79: =SUM(AL77:AL78) -> 0
C81: Net Change in Cash | E81: =E70+E74+E79 -> -93712 | F81: =F70+F74+F79 -> -114954 | G81: =G70+G74+G79 -> -71494 | H81: =H70+H74+H79 -> -134047 | I81: =I70+I74+I79 -> -75799 | J81: =J70+J74+J79 -> -138143 | K81: =K70+K74+K79 -> -144663 | L81: =L70+L74+L79 -> -144317 | ... Y81: =Y70+Y74+Y79 -> -244181.89 | AA81: =AA70+AA74+AA79 -> -280160 | AB81: =AB70+AB74+AB79 -> -347989 | AC81: =AC70+AC74+AC79 -> -439631 | AD81: =AD70+AD74+AD79 -> -472238 | AE81: =AE70+AE74+AE79 -> -537624.02 | AF81: =AF70+AF74+AF79 -> -613318.33 | AG81: =AG70+AG74+AG79 -> -700917.38 | AI81: =AI70+AI74+AI79 -> -1540018 | AK81: =AK70+AK74+AK79 -> -1851859.7 | AL81: =AL70+AL74+AL79 -> -2324097.7
C82: Beginning Cash Balance | E82: {=INDEX('Data Summary'!M$8:M$38,29-7)} -> 4285000.5 | F82: =E35 -> 4191288.5 | G82: =F35 -> 4076334.5 | H82: =G35 -> 4004840.5 | I82: =H35 -> 3870793.5 | J82: =I35 -> 3794994.5 | K82: =J35 -> 3656851.5 | L82: =K35 -> 3512188.5 | M82: =L35 -> 3367871.5 | ... Y82: =X35 -> 1137304.7 | AA82: {=INDEX('Data Summary'!M$8:M$38,29-7)} -> 4285000.5 | AB82: {=INDEX('Data Summary'!P$8:P$38,29-7)} -> 4004840.5 | AC82: {=INDEX('Data Summary'!S$8:S$38,29-7)} -> 3656851.5 | AD82: {=INDEX('Data Summary'!V$8:V$38,29-7)} -> 3217220.5 | AE82: {=INDEX('Data Summary'!Y$8:Y$38,29-7)} -> 2744982.5 | AF82: {=INDEX('Data Summary'!AB$8:AB$38,29-7)} -> 2207358.5 | AG82: {=INDEX('Data Summary'!AE$8:AE$38,29-7)} -> 1594040.1 | AI82: {=INDEX('Data Summary'!M$8:M$38,29-7)} -> 4285000.5 | AK82: {=INDEX('Data Summary'!Y$8:Y$38,29-7)} -> 2744982.5 | AL82: {=INDEX('Data Summary'!V$8:V$38,29-7)} -> 3217220.5
C83: Ending Cash Balance | E83: =E81+E82 -> 4191288.5 | F83: =F81+F82 -> 4076334.5 | G83: =G81+G82 -> 4004840.5 | H83: =H81+H82 -> 3870793.5 | I83: =I81+I82 -> 3794994.5 | J83: =J81+J82 -> 3656851.5 | K83: =K81+K82 -> 3512188.5 | L83: =L81+L82 -> 3367871.5 | ... Y83: =Y81+Y82 -> 893122.77 | AA83: =AA81+AA82 -> 4004840.5 | AB83: =AB81+AB82 -> 3656851.5 | AC83: =AC81+AC82 -> 3217220.5 | AD83: =AD81+AD82 -> 2744982.5 | AE83: =AE81+AE82 -> 2207358.5 | AF83: =AF81+AF82 -> 1594040.1 | AG83: =AG81+AG82 -> 893122.77 | AI83: =AI81+AI82 -> 2744982.5 | AK83: =AK81+AK82 -> 893122.77 | AL83: =AL81+AL82 -> 893122.77
C84: Balance Sheet Check | E84: =E83-E35 -> 0 | F84: =F83-F35 -> 0 | G84: =G83-G35 -> 0 | H84: =H83-H35 -> 0 | I84: =I83-I35 -> 0 | J84: =J83-J35 -> 0 | K84: =K83-K35 -> 0 | L84: =L83-L35 -> 0 | ... Y84: =Y83-Y35 -> 0 | AA84: =AA83-AA35 -> 0 | AB84: =AB83-AB35 -> 0 | AC84: =AC83-AC35 -> 0 | AD84: =AD83-AD35 -> 0 | AE84: =AE83-AE35 -> 0 | AF84: =AF83-AF35 -> 0 | AG84: =AG83-AG35 -> 0 | AI84: =AI83-AI35 -> 0 | AK84: =AK83-AK35 -> 0 | AL84: =AL83-AL35 -> 0

Sheet Drivers
A1: Nimbus Cloud Solutions
A2: {=IFERROR(MID(CELL("filename",A1),FIND("]",CELL("filename",A1))+1,LEN(CELL("filename",A1))),"")} -> Drivers | O2: Annual | T2: Quarterly | AH2: Monthly
A3: ='Error Check'!D12 -> Model Functioning Properly | P3: =IF(P$5<=LatestMonthOfActuals,"Actual","Projected") -> Actual | Q3: =IF(Q$5<=LatestMonthOfActuals,"Actual","Projected") -> Projected | R3: =IF(R$5<=LatestMonthOfActuals,"Actual","Projected") -> Projected | U3: =IF(U$5<=LatestMonthOfActuals,"Actual","Projected") -> Actual | V3: =IF(V$5<=LatestMonthOfActuals,"Actual","Projected") -> Actual | W3: =IF(W$5<=LatestMonthOfActuals,"Actual","Projected") -> Actual | X3: =IF(X$5<=LatestMonthOfActuals,"Actual","Projected") -> Actual | Y3: =IF(Y$5<=LatestMonthOfActuals,"Actual","Projected") -> Actual | Z3: =IF(Z$5<=LatestMonthOfActuals,"Actual","Projected") -> Actual | AA3: =IF(AA$5<=LatestMonthOfActuals,"Actual","Projected") -> Actual | AB3: =IF(AB$5<=LatestMonthOfActuals,"Actual","Projected") -> Projected | ... AF3: =IF(AF$5<=LatestMonthOfActuals,"Actual","Projected") -> Projected | AI3: =IF(AI$5<=LatestMonthOfActuals,"Actual","Projected") -> Actual | AJ3: =IF(AJ$5<=LatestMonthOfActuals,"Actual","Projected") -> Actual | AK3: =IF(AK$5<=LatestMonthOfActuals,"Actual","Projected") -> Actual | AL3: =IF(AL$5<=LatestMonthOfActuals,"Actual","Projected") -> Actual | AM3: =IF(AM$5<=LatestMonthOfActuals,"Actual","Projected") -> Actual | AN3: =IF(AN$5<=LatestMonthOfActuals,"Actual","Projected") -> Actual | AO3: =IF(AO$5<=LatestMonthOfActuals,"Actual","Projected") -> Actual | AP3: =IF(AP$5<=LatestMonthOfActuals,"Actual","Projected") -> Actual | ... BS3: =IF(BS$5<=LatestMonthOfActuals,"Actual","Projected") -> Projected
P4: =Start_Date -> 45292 | Q4: =P5+1 -> 45658 | R4: =Q5+1 -> 46023 | U4: =Start_Date -> 45292 | V4: =U5+1 -> 45383 | W4: =V5+1 -> 45474 | X4: =W5+1 -> 45566 | Y4: =X5+1 -> 45658 | Z4: =Y5+1 -> 45748 | AA4: =Z5+1 -> 45839 | AB4: =AA5+1 -> 45931 | AC4: =AB5+1 -> 46023 | ... AF4: =AE5+1 -> 46296 | AI4: =EOMONTH(AI5,-1)+1 -> 45261 | AJ4: =Start_Date -> 45292 | AK4: =EOMONTH(AK5,-1)+1 -> 45323 | AL4: =EOMONTH(AL5,-1)+1 -> 45352 | AM4: =EOMONTH(AM5,-1)+1 -> 45383 | AN4: =EOMONTH(AN5,-1)+1 -> 45413 | AO4: =EOMONTH(AO5,-1)+1 -> 45444 | AP4: =EOMONTH(AP5,-1)+1 -> 45474 | AQ4: =EOMONTH(AQ5,-1)+1 -> 45505 | AR4: =EOMONTH(AR5,-1)+1 -> 45536 | ... BS4: =EOMONTH(BS5,-1)+1 -> 46357
P5: =EOMONTH(DATE(YEAR(Start_Date),1,1),Fiscal_Offset+IF(U6<YEAR(Start_Date),-1,11)) -> 45657 | Q5: =MIN(EOMONTH(P5,12),End_Date) -> 46022 | R5: =MIN(EOMONTH(Q5,12),End_Date) -> 46387 | U5: =EOMONTH(DATE(YEAR(Start_Date),1,1),MOD(ROUNDUP(MONTH(EOMONTH(Start_Date,-Fiscal_Offset))/3,0)*3+Fiscal_Offset-1,12)) -> 45382 | V5: =MIN(EOMONTH(V$4,2),End_Date) -> 45473 | W5: =MIN(EOMONTH(W$4,2),End_Date) -> 45565 | X5: =MIN(EOMONTH(X$4,2),End_Date) -> 45657 | Y5: =MIN(EOMONTH(Y$4,2),End_Date) -> 45747 | Z5: =MIN(EOMONTH(Z$4,2),End_Date) -> 45838 | AA5: =MIN(EOMONTH(AA$4,2),End_Date) -> 45930 | AB5: =MIN(EOMONTH(AB$4,2),End_Date) -> 46022 | AC5: =MIN(EOMONTH(AC$4,2),End_Date) -> 46112 | ... AF5: =MIN(EOMONTH(AF$4,2),End_Date) -> 46387 | AI5: =EOMONTH(AJ5,-1) -> 45291 | AJ5: =EOM_Start_Date -> 45322 | AK5: =EOMONTH(AJ5,1) -> 45351 | AL5: =EOMONTH(AK5,1) -> 45382 | AM5: =EOMONTH(AL5,1) -> 45412 | AN5: =EOMONTH(AM5,1) -> 45443 | AO5: =EOMONTH(AN5,1) -> 45473 | AP5: =EOMONTH(AO5,1) -> 45504 | AQ5: =EOMONTH(AP5,1) -> 45535 | AR5: =EOMONTH(AQ5,1) -> 45565 | ... BS5: =EOMONTH(BR5,1) -> 46387
P6: =YEAR(EOMONTH(P5,-Fiscal_Offset)) -> 2024 | Q6: =YEAR(EOMONTH(Q5,-Fiscal_Offset)) -> 2025 | R6: =YEAR(EOMONTH(R5,-Fiscal_Offset)) -> 2026 | U6: =YEAR(EOMONTH(U5,-Fiscal_Offset)) -> 2024 | V6: =YEAR(EOMONTH(V5,-Fiscal_Offset)) -> 2024 | W6: =YEAR(EOMONTH(W5,-Fiscal_Offset)) -> 2024 | X6: =YEAR(EOMONTH(X5,-Fiscal_Offset)) -> 2024 | Y6: =YEAR(EOMONTH(Y5,-Fiscal_Offset)) -> 2025 | Z6: =YEAR(EOMONTH(Z5,-Fiscal_Offset)) -> 2025 | AA6: =YEAR(EOMONTH(AA5,-Fiscal_Offset)) -> 2025 | AB6: =YEAR(EOMONTH(AB5,-Fiscal_Offset)) -> 2025 | ... AF6: =YEAR(EOMONTH(AF5,-Fiscal_Offset)) -> 2026 | AI6: =YEAR(EOMONTH(AI4,-Fiscal_Offset)) -> 2023 | AJ6: =YEAR(EOMONTH(AJ5,-Fiscal_Offset)) -> 2024 | AK6: =YEAR(EOMONTH(AK5,-Fiscal_Offset)) -> 2024 | AL6: =YEAR(EOMONTH(AL5,-Fiscal_Offset)) -> 2024 | AM6: =YEAR(EOMONTH(AM5,-Fiscal_Offset)) -> 2024 | AN6: =YEAR(EOMONTH(AN5,-Fiscal_Offset)) -> 2024 | AO6: =YEAR(EOMONTH(AO5,-Fiscal_Offset)) -> 2024 | AP6: =YEAR(EOMONTH(AP5,-Fiscal_Offset)) -> 2024 | AQ6: =YEAR(EOMONTH(AQ5,-Fiscal_Offset)) -> 2024 | ... BS6: =YEAR(EOMONTH(BS5,-Fiscal_Offset)) -> 2026
P7: ="Q"& ROUNDUP(MONTH(EOMONTH(P5,-Fiscal_Offset))/3,0) -> Q4 | Q7: ="Q"& ROUNDUP(MONTH(EOMONTH(Q5,-Fiscal_Offset))/3,0) -> Q4 | R7: ="Q"& ROUNDUP(MONTH(EOMONTH(R5,-Fiscal_Offset))/3,0) -> Q4 | U7: ="Q"& ROUNDUP(MONTH(EOMONTH(U5,-Fiscal_Offset))/3,0) -> Q1 | V7: ="Q"& ROUNDUP(MONTH(EOMONTH(V5,-Fiscal_Offset))/3,0) -> Q2 | W7: ="Q"& ROUNDUP(MONTH(EOMONTH(W5,-Fiscal_Offset))/3,0) -> Q3 | X7: ="Q"& ROUNDUP(MONTH(EOMONTH(X5,-Fiscal_Offset))/3,0) -> Q4 | Y7: ="Q"& ROUNDUP(MONTH(EOMONTH(Y5,-Fiscal_Offset))/3,0) -> Q1 | Z7: ="Q"& ROUNDUP(MONTH(EOMONTH(Z5,-Fiscal_Offset))/3,0) -> Q2 | AA7: ="Q"& ROUNDUP(MONTH(EOMONTH(AA5,-Fiscal_Offset))/3,0) -> Q3 | AB7: ="Q"& ROUNDUP(MONTH(EOMONTH(AB5,-Fiscal_Offset))/3,0) -> Q4 | ... AF7: ="Q"& ROUNDUP(MONTH(EOMONTH(AF5,-Fiscal_Offset))/3,0) -> Q4 | AI7: ="Q"& ROUNDUP(MONTH(EOMONTH(AI5,-Fiscal_Offset))/3,0) -> Q4 | AJ7: ="Q"& ROUNDUP(MONTH(EOMONTH(AJ5,-Fiscal_Offset))/3,0) -> Q1 | AK7: ="Q"& ROUNDUP(MONTH(EOMONTH(AK5,-Fiscal_Offset))/3,0) -> Q1 | AL7: ="Q"& ROUNDUP(MONTH(EOMONTH(AL5,-Fiscal_Offset))/3,0) -> Q1 | AM7: ="Q"& ROUNDUP(MONTH(EOMONTH(AM5,-Fiscal_Offset))/3,0) -> Q2 | AN7: ="Q"& ROUNDUP(MONTH(EOMONTH(AN5,-Fiscal_Offset))/3,0) -> Q2 | AO7: ="Q"& ROUNDUP(MONTH(EOMONTH(AO5,-Fiscal_Offset))/3,0) -> Q2 | AP7: ="Q"& ROUNDUP(MONTH(EOMONTH(AP5,-Fiscal_Offset))/3,0) -> Q3 | ... BS7: ="Q"& ROUNDUP(MONTH(EOMONTH(BS5,-Fiscal_Offset))/3,0) -> Q4
E8: Driver | F8: Assumption | G8: Drivers Section | H8: Summary Grouping | I8: Cash Flow Grouping | J8: Cash Flow Section | K8: Account Type | L8: Account ID | P8: =P6 -> 2024 | Q8: =Q6 -> 2025 | R8: =R6 -> 2026 | U8: =CONCATENATE(CONCATENATE(U$7," ",U$6)) -> Q1 2024 | V8: =CONCATENATE(CONCATENATE(V$7," ",V$6)) -> Q2 2024 | W8: =CONCATENATE(CONCATENATE(W$7," ",W$6)) -> Q3 2024 | X8: =CONCATENATE(CONCATENATE(X$7," ",X$6)) -> Q4 2024 | Y8: =CONCATENATE(CONCATENATE(Y$7," ",Y$6)) -> Q1 2025 | Z8: =CONCATENATE(CONCATENATE(Z$7," ",Z$6)) -> Q2 2025 | AA8: =CONCATENATE(CONCATENATE(AA$7," ",AA$6)) -> Q3 2025 | AB8: =CONCATENATE(CONCATENATE(AB$7," ",AB$6)) -> Q4 2025 | ... AF8: =CONCATENATE(CONCATENATE(AF$7," ",AF$6)) -> Q4 2026 | AI8: =AI5 -> 45291 | AJ8: =AJ5 -> 45322 | AK8: =AK5 -> 45351 | AL8: =AL5 -> 45382 | AM8: =AM5 -> 45412 | AN8: =AN5 -> 45443 | AO8: =AO5 -> 45473 | AP8: =AP5 -> 45504 | ... BS8: =BS5 -> 46387
B9: Income Statement
C10: Revenue | P10: =SUM(P11:P14) -> 594395 | Q10: =SUM(Q11:Q14) -> 916705.59 | R10: =SUM(R11:R14) -> 1150828.1 | U10: =SUM(U11:U14) -> 141336 | V10: =SUM(V11:V14) -> 143829 | W10: =SUM(W11:W14) -> 148291 | X10: =SUM(X11:X14) -> 160939 | Y10: =SUM(Y11:Y14) -> 186307.22 | Z10: =SUM(Z11:Z14) -> 224373.97 | AA10: =SUM(AA11:AA14) -> 249669.37 | AB10: =SUM(AB11:AB14) -> 256355.03 | ... AF10: =SUM(AF11:AF14) -> 306058.74 | AI10: =IF(AI$5<=LatestMonthOfActuals,SUMIFS(AI11:AI14,$K11:$K14,"Account"),SUMIFS(AI11:AI14,$K11:$K14,"<>Sub-Account")) -> 40000 | AJ10: =IF(AJ$5<=LatestMonthOfActuals,SUMIFS(AJ11:AJ14,$K11:$K14,"Account"),SUMIFS(AJ11:AJ14,$K11:$K14,"<>Sub-Account")) -> 48456.5 | AK10: =IF(AK$5<=LatestMonthOfActuals,SUMIFS(AK11:AK14,$K11:$K14,"Account"),SUMIFS(AK11:AK14,$K11:$K14,"<>Sub-Account")) -> 42000 | AL10: =IF(AL$5<=LatestMonthOfActuals,SUMIFS(AL11:AL14,$K11:$K14,"Account"),SUMIFS(AL11:AL14,$K11:$K14,"<>Sub-Account")) -> 50879.5 | AM10: =IF(AM$5<=LatestMonthOfActuals,SUMIFS(AM11:AM14,$K11:$K14,"Account"),SUMIFS(AM11:AM14,$K11:$K14,"<>Sub-Account")) -> 44100 | AN10: =IF(AN$5<=LatestMonthOfActuals,SUMIFS(AN11:AN14,$K11:$K14,"Account"),SUMIFS(AN11:AN14,$K11:$K14,"<>Sub-Account")) -> 53424 | AO10: =IF(AO$5<=LatestMonthOfActuals,SUMIFS(AO11:AO14,$K11:$K14,"Account"),SUMIFS(AO11:AO14,$K11:$K14,"<>Sub-Account")) -> 46305 | AP10: =IF(AP$5<=LatestMonthOfActuals,SUMIFS(AP11:AP14,$K11:$K14,"Account"),SUMIFS(AP11:AP14,$K11:$K14,"<>Sub-Account")) -> 48620 | ... BS10: =IF(BS$5<=LatestMonthOfActuals,SUMIFS(BS11:BS14,$K11:$K14,"Account"),SUMIFS(BS11:BS14,$K11:$K14,"<>Sub-Account")) -> 103476.19
D12: 40100 Sales | E12: Average 6 months with a buffer | F12: 0.05 | G12: =IFERROR(INDEX(PBC_ACCOUNT_LIST[Drivers Section],MATCH(Drivers!L12,PBC_ACCOUNT_LIST[Id],0)),"") -> Revenue | H12: =IFERROR(INDEX(PBC_ACCOUNT_LIST[Summary Grouping],MATCH(Drivers!L12,PBC_ACCOUNT_LIST[Id],0)),"") -> Revenue | J12: =IFERROR(INDEX(PBC_ACCOUNT_LIST[Cash Flow Section],MATCH(Drivers!L12,PBC_ACCOUNT_LIST[Id],0)),"") -> 0 | K12: Account | L12: 199 | P12: =SUMIFS($AI12:$BS12,$AI$4:$BS$4,">="&P$4,$AI$5:$BS$5,"<="&P$5) -> 594395 | Q12: =SUMIFS($AI12:$BS12,$AI$4:$BS$4,">="&Q$4,$AI$5:$BS$5,"<="&Q$5) -> 916218.92 | R12: =SUMIFS($AI12:$BS12,$AI$4:$BS$4,">="&R$4,$AI$5:$BS$5,"<="&R$5) -> 1150240.4 | U12: =SUMIFS($AI12:$BS12,$AI$4:$BS$4,">="&U$4,$AI$5:$BS$5,"<="&U$5) -> 141336 | V12: =SUMIFS($AI12:$BS12,$AI$4:$BS$4,">="&V$4,$AI$5:$BS$5,"<="&V$5) -> 143829 | W12: =SUMIFS($AI12:$BS12,$AI$4:$BS$4,">="&W$4,$AI$5:$BS$5,"<="&W$5) -> 148291 | X12: =SUMIFS($AI12:$BS12,$AI$4:$BS$4,">="&X$4,$AI$5:$BS$5,"<="&X$5) -> 160939 | Y12: =SUMIFS($AI12:$BS12,$AI$4:$BS$4,">="&Y$4,$AI$5:$BS$5,"<="&Y$5) -> 186307.22 | Z12: =SUMIFS($AI12:$BS12,$AI$4:$BS$4,">="&Z$4,$AI$5:$BS$5,"<="&Z$5) -> 224073.97 | AA12: =SUMIFS($AI12:$BS12,$AI$4:$BS$4,">="&AA$4,$AI$5:$BS$5,"<="&AA$5) -> 249669.37 | AB12: =SUMIFS($AI12:$BS12,$AI$4:$BS$4,">="&AB$4,$AI$5:$BS$5,"<="&AB$5) -> 256168.36 | ... AF12: =SUMIFS($AI12:$BS12,$AI$4:$BS$4,">="&AF$4,$AI$5:$BS$5,"<="&AF$5) -> 305896.01 | AI12: =SUMIFS(PBC_PROFIT_AND_LOSS[AccountBalance], PBC_PROFIT_AND_LOSS[Id],$L12,PBC_PROFIT_AND_LOSS[Date],AI$5) -> 40000 | AJ12: =SUMIFS(PBC_PROFIT_AND_LOSS[AccountBalance], PBC_PROFIT_AND_LOSS[Id],$L12,PBC_PROFIT_AND_LOSS[Date],AJ$5) -> 48456.5 | AK12: =SUMIFS(PBC_PROFIT_AND_LOSS[AccountBalance], PBC_PROFIT_AND_LOSS[Id],$L12,PBC_PROFIT_AND_LOSS[Date],AK$5) -> 42000 | AL12: =SUMIFS(PBC_PROFIT_AND_LOSS[AccountBalance], PBC_PROFIT_AND_LOSS[Id],$L12,PBC_PROFIT_AND_LOSS[Date],AL$5) -> 50879.5 | AM12: =SUMIFS(PBC_PROFIT_AND_LOSS[AccountBalance], PBC_PROFIT_AND_LOSS[Id],$L12,PBC_PROFIT_AND_LOSS[Date],AM$5) -> 44100 | AN12: =SUMIFS(PBC_PROFIT_AND_LOSS[AccountBalance], PBC_PROFIT_AND_LOSS[Id],$L12,PBC_PROFIT_AND_LOSS[Date],AN$5) -> 53424 | AO12: =SUMIFS(PBC_PROFIT_AND_LOSS[AccountBalance], PBC_PROFIT_AND_LOSS[Id],$L12,PBC_PROFIT_AND_LOSS[Date],AO$5) -> 46305 | AP12: =SUMIFS(PBC_PROFIT_AND_LOSS[AccountBalance], PBC_PROFIT_AND_LOSS[Id],$L12,PBC_PROFIT_AND_LOSS[Date],AP$5) -> 48620 | ... BD12: =SUMIFS(PBC_PROFIT_AND_LOSS[AccountBalance], PBC_PROFIT_AND_LOSS[Id],$L12,PBC_PROFIT_AND_LOSS[Date],BD$5) -> 87314.98 | BE12: =AVERAGE(AY12:BD12) * (1 + $F12) -> 82905.084 | BF12: =AVERAGE(AZ12:BE12) * (1 + $F12) -> 85441.024 | BG12: =AVERAGE(BA12:BF12) * (1 + $F12) -> 87822.254 | BH12: =AVERAGE(BB12:BG12) * (1 + $F12) -> 88521.603 | BI12: =AVERAGE(BC12:BH12) * (1 + $F12) -> 90153.363 | BJ12: =AVERAGE(BD12:BI12) * (1 + $F12) -> 91377.704 | BK12: =AVERAGE(BE12:BJ12) * (1 + $F12) -> 92088.681 | BL12: =AVERAGE(BF12:BK12) * (1 + $F12) -> 93695.81 | ... BS12: =AVERAGE(BM12:BR12) * (1 + $F12) -> 103421.75
D13: Sales of Product Income | E13: Average 6 months with a buffer | F13: 0.05 | G13: =IFERROR(INDEX(PBC_ACCOUNT_LIST[Drivers Section],MATCH(Drivers!L13,PBC_ACCOUNT_LIST[Id],0)),"") -> Revenue | H13: =IFERROR(INDEX(PBC_ACCOUNT_LIST[Summary Grouping],MATCH(Drivers!L13,PBC_ACCOUNT_LIST[Id],0)),"") -> Revenue | J13: =IFERROR(INDEX(PBC_ACCOUNT_LIST[Cash Flow Section],MATCH(Drivers!L13,PBC_ACCOUNT_LIST[Id],0)),"") -> 0 | K13: Account | L13: 73 | P13: =SUMIFS($AI13:$BS13,$AI$4:$BS$4,">="&P$4,$AI$5:$BS$5,"<="&P$5) -> 0 | Q13: =SUMIFS($AI13:$BS13,$AI$4:$BS$4,">="&Q$4,$AI$5:$BS$5,"<="&Q$5) -> 486.67031 | R13: =SUMIFS($AI13:$BS13,$AI$4:$BS$4,">="&R$4,$AI$5:$BS$5,"<="&R$5) -> 587.74614 | U13: =SUMIFS($AI13:$BS13,$AI$4:$BS$4,">="&U$4,$AI$5:$BS$5,"<="&U$5) -> 0 | V13: =SUMIFS($AI13:$BS13,$AI$4:$BS$4,">="&V$4,$AI$5:$BS$5,"<="&V$5) -> 0 | W13: =SUMIFS($AI13:$BS13,$AI$4:$BS$4,">="&W$4,$AI$5:$BS$5,"<="&W$5) -> 0 | X13: =SUMIFS($AI13:$BS13,$AI$4:$BS$4,">="&X$4,$AI$5:$BS$5,"<="&X$5) -> 0 | Y13: =SUMIFS($AI13:$BS13,$AI$4:$BS$4,">="&Y$4,$AI$5:$BS$5,"<="&Y$5) -> 0 | Z13: =SUMIFS($AI13:$BS13,$AI$4:$BS$4,">="&Z$4,$AI$5:$BS$5,"<="&Z$5) -> 300 | AA13: =SUMIFS($AI13:$BS13,$AI$4:$BS$4,">="&AA$4,$AI$5:$BS$5,"<="&AA$5) -> 0 | AB13: =SUMIFS($AI13:$BS13,$AI$4:$BS$4,">="&AB$4,$AI$5:$BS$5,"<="&AB$5) -> 186.67031 | ... AF13: =SUMIFS($AI13:$BS13,$AI$4:$BS$4,">="&AF$4,$AI$5:$BS$5,"<="&AF$5) -> 162.72724 | AI13: =SUMIFS(PBC_PROFIT_AND_LOSS[AccountBalance], PBC_PROFIT_AND_LOSS[Id],$L13,PBC_PROFIT_AND_LOSS[Date],AI$5) -> 0 | AJ13: =SUMIFS(PBC_PROFIT_AND_LOSS[AccountBalance], PBC_PROFIT_AND_LOSS[Id],$L13,PBC_PROFIT_AND_LOSS[Date],AJ$5) -> 0 | AK13: =SUMIFS(PBC_PROFIT_AND_LOSS[AccountBalance], PBC_PROFIT_AND_LOSS[Id],$L13,PBC_PROFIT_AND_LOSS[Date],AK$5) -> 0 | AL13: =SUMIFS(PBC_PROFIT_AND_LOSS[AccountBalance], PBC_PROFIT_AND_LOSS[Id],$L13,PBC_PROFIT_AND_LOSS[Date],AL$5) -> 0 | AM13: =SUMIFS(PBC_PROFIT_AND_LOSS[AccountBalance], PBC_PROFIT_AND_LOSS[Id],$L13,PBC_PROFIT_AND_LOSS[Date],AM$5) -> 0 | AN13: =SUMIFS(PBC_PROFIT_AND_LOSS[AccountBalance], PBC_PROFIT_AND_LOSS[Id],$L13,PBC_PROFIT_AND_LOSS[Date],AN$5) -> 0 | AO13: =SUMIFS(PBC_PROFIT_AND_LOSS[AccountBalance], PBC_PROFIT_AND_LOSS[Id],$L13,PBC_PROFIT_AND_LOSS[Date],AO$5) -> 0 | AP13: =SUMIFS(PBC_PROFIT_AND_LOSS[AccountBalance], PBC_PROFIT_AND_LOSS[Id],$L13,PBC_PROFIT_AND_LOSS[Date],AP$5) -> 0 | ... BD13: =SUMIFS(PBC_PROFIT_AND_LOSS[AccountBalance], PBC_PROFIT_AND_LOSS[Id],$L13,PBC_PROFIT_AND_LOSS[Date],BD$5) -> 0 | BE13: =AVERAGE(AY13:BD13) * (1 + $F13) -> 52.5 | BF13: =AVERAGE(AZ13:BE13) * (1 + $F13) -> 61.6875 | BG13: =AVERAGE(BA13:BF13) * (1 + $F13) -> 72.482813 | BH13: =AVERAGE(BB13:BG13) * (1 + $F13) -> 32.667305 | BI13: =AVERAGE(BC13:BH13) * (1 + $F13) -> 38.384083 | BJ13: =AVERAGE(BD13:BI13) * (1 + $F13) -> 45.101298 | BK13: =AVERAGE(BE13:BJ13) * (1 + $F13) -> 52.994025 | BL13: =AVERAGE(BF13:BK13) * (1 + $F13) -> 53.080479 | ... BS13: =AVERAGE(BM13:BR13) * (1 + $F13) -> 54.438993
C15: COGS | P15: =SUM(P16:P21) -> 53271.66 | Q15: =SUM(Q16:Q21) -> 84550.553 | R15: =SUM(R16:R21) -> 105524.29 | U15: =SUM(U16:U21) -> 11366 | V15: =SUM(V16:V21) -> 12551.5 | W15: =SUM(W16:W21) -> 14075.5 | X15: =SUM(X16:X21) -> 15278.66 | Y15: =SUM(Y16:Y21) -> 17685.42 | Z15: =SUM(Z16:Z21) -> 20775.48 | AA15: =SUM(AA16:AA21) -> 22702.08 | AB15: =SUM(AB16:AB21) -> 23387.573 | ... AF15: =SUM(AF16:AF21) -> 28052.139 | AI15: =IF(AI$5<=LatestMonthOfActuals,SUMIFS(AI16:AI21,$K16:$K21,"Account"),SUMIFS(AI16:AI21,$K16:$K21,"<>Sub-Account")) -> 3797.5 | AJ15: =IF(AJ$5<=LatestMonthOfActuals,SUMIFS(AJ16:AJ21,$K16:$K21,"Account"),SUMIFS(AJ16:AJ21,$K16:$K21,"<>Sub-Account")) -> 3599 | AK15: =IF(AK$5<=LatestMonthOfActuals,SUMIFS(AK16:AK21,$K16:$K21,"Account"),SUMIFS(AK16:AK21,$K16:$K21,"<>Sub-Account")) -> 3988 | AL15: =IF(AL$5<=LatestMonthOfActuals,SUMIFS(AL16:AL21,$K16:$K21,"Account"),SUMIFS(AL16:AL21,$K16:$K21,"<>Sub-Account")) -> 3779 | AM15: =IF(AM$5<=LatestMonthOfActuals,SUMIFS(AM16:AM21,$K16:$K21,"Account"),SUMIFS(AM16:AM21,$K16:$K21,"<>Sub-Account")) -> 4186.5 | AN15: =IF(AN$5<=LatestMonthOfActuals,SUMIFS(AN16:AN21,$K16:$K21,"Account"),SUMIFS(AN16:AN21,$K16:$K21,"<>Sub-Account")) -> 3968.5 | AO15: =IF(AO$5<=LatestMonthOfActuals,SUMIFS(AO16:AO21,$K16:$K21,"Account"),SUMIFS(AO16:AO21,$K16:$K21,"<>Sub-Account")) -> 4396.5 | AP15: =IF(AP$5<=LatestMonthOfActuals,SUMIFS(AP16:AP21,$K16:$K21,"Account"),SUMIFS(AP16:AP21,$K16:$K21,"<>Sub-Account")) -> 4615 | ... BS15: =IF(BS$5<=LatestMonthOfActuals,SUMIFS(BS16:BS21,$K16:$K21,"Account"),SUMIFS(BS16:BS21,$K16:$K21,"<>Sub-Account")) -> 9486.1006
D17: 50100 Web Domain & Hosting Fees | E17: Average 6 months with a buffer | F17: 0.05 | G17: =IFERROR(INDEX(PBC_ACCOUNT_LIST[Drivers Section],MATCH(Drivers!L17,PBC_ACCOUNT_LIST[Id],0)),"") -> COGS | H17: =IFERROR(INDEX(PBC_ACCOUNT_LIST[Summary Grouping],MATCH(Drivers!L17,PBC_ACCOUNT_LIST[Id],0)),"") -> COGS | J17: =IFERROR(INDEX(PBC_ACCOUNT_LIST[Cash Flow Section],MATCH(Drivers!L17,PBC_ACCOUNT_LIST[Id],0)),"") -> 0 | K17: Account | L17: 164 | P17: =SUMIFS($AI17:$BS17,$AI$4:$BS$4,">="&P$4,$AI$5:$BS$5,"<="&P$5) -> 42018 | Q17: =SUMIFS($AI17:$BS17,$AI$4:$BS$4,">="&Q$4,$AI$5:$BS$5,"<="&Q$5) -> 67468.766 | R17: =SUMIFS($AI17:$BS17,$AI$4:$BS$4,">="&R$4,$AI$5:$BS$5,"<="&R$5) -> 84751.277 | U17: =SUMIFS($AI17:$BS17,$AI$4:$BS$4,">="&U$4,$AI$5:$BS$5,"<="&U$5) -> 8997 | V17: =SUMIFS($AI17:$BS17,$AI$4:$BS$4,">="&V$4,$AI$5:$BS$5,"<="&V$5) -> 9907 | W17: =SUMIFS($AI17:$BS17,$AI$4:$BS$4,">="&W$4,$AI$5:$BS$5,"<="&W$5) -> 11084 | X17: =SUMIFS($AI17:$BS17,$AI$4:$BS$4,">="&X$4,$AI$5:$BS$5,"<="&X$5) -> 12030 | Y17: =SUMIFS($AI17:$BS17,$AI$4:$BS$4,">="&Y$4,$AI$5:$BS$5,"<="&Y$5) -> 13925.61 | Z17: =SUMIFS($AI17:$BS17,$AI$4:$BS$4,">="&Z$4,$AI$5:$BS$5,"<="&Z$5) -> 16122.12 | AA17: =SUMIFS($AI17:$BS17,$AI$4:$BS$4,">="&AA$4,$AI$5:$BS$5,"<="&AA$5) -> 18662.88 | AB17: =SUMIFS($AI17:$BS17,$AI$4:$BS$4,">="&AB$4,$AI$5:$BS$5,"<="&AB$5) -> 18758.156 | ... AF17: =SUMIFS($AI17:$BS17,$AI$4:$BS$4,">="&AF$4,$AI$5:$BS$5,"<="&AF$5) -> 22525.397 | AI17: =SUMIFS(PBC_PROFIT_AND_LOSS[AccountBalance], PBC_PROFIT_AND_LOSS[Id],$L17,PBC_PROFIT_AND_LOSS[Date],AI$5) -> 2990 | AJ17: =SUMIFS(PBC_PROFIT_AND_LOSS[AccountBalance], PBC_PROFIT_AND_LOSS[Id],$L17,PBC_PROFIT_AND_LOSS[Date],AJ$5) -> 2857 | AK17: =SUMIFS(PBC_PROFIT_AND_LOSS[AccountBalance], PBC_PROFIT_AND_LOSS[Id],$L17,PBC_PROFIT_AND_LOSS[Date],AK$5) -> 3140 | AL17: =SUMIFS(PBC_PROFIT_AND_LOSS[AccountBalance], PBC_PROFIT_AND_LOSS[Id],$L17,PBC_PROFIT_AND_LOSS[Date],AL$5) -> 3000 | AM17: =SUMIFS(PBC_PROFIT_AND_LOSS[AccountBalance], PBC_PROFIT_AND_LOSS[Id],$L17,PBC_PROFIT_AND_LOSS[Date],AM$5) -> 3296 | AN17: =SUMIFS(PBC_PROFIT_AND_LOSS[AccountBalance], PBC_PROFIT_AND_LOSS[Id],$L17,PBC_PROFIT_AND_LOSS[Date],AN$5) -> 3150 | AO17: =SUMIFS(PBC_PROFIT_AND_LOSS[AccountBalance], PBC_PROFIT_AND_LOSS[Id],$L17,PBC_PROFIT_AND_LOSS[Date],AO$5) -> 3461 | AP17: =SUMIFS(PBC_PROFIT_AND_LOSS[AccountBalance], PBC_PROFIT_AND_LOSS[Id],$L17,PBC_PROFIT_AND_LOSS[Date],AP$5) -> 3634 | ... BD17: =SUMIFS(PBC_PROFIT_AND_LOSS[AccountBalance], PBC_PROFIT_AND_LOSS[Id],$L17,PBC_PROFIT_AND_LOSS[Date],BD$5) -> 6526.83 | BE17: =AVERAGE(AY17:BD17) * (1 + $F17) -> 6087.375 | BF17: =AVERAGE(AZ17:BE17) * (1 + $F17) -> 6257.7156 | BG17: =AVERAGE(BA17:BF17) * (1 + $F17) -> 6413.0659 | BH17: =AVERAGE(BB17:BG17) * (1 + $F17) -> 6548.6814 | BI17: =AVERAGE(BC17:BH17) * (1 + $F17) -> 6658.6971 | BJ17: =AVERAGE(BD17:BI17) * (1 + $F17) -> 6736.1639 | BK17: =AVERAGE(BE17:BJ17) * (1 + $F17) -> 6772.7973 | BL17: =AVERAGE(BF17:BK17) * (1 + $F17) -> 6892.7462 | ... BS17: =AVERAGE(BM17:BR17) * (1 + $F17) -> 7616.9221
D18: 50200 Merchant Account Fees | E18: Average 6 months with a buffer | F18: 0.05 | G18: =IFERROR(INDEX(PBC_ACCOUNT_LIST[Drivers Section],MATCH(Drivers!L18,PBC_ACCOUNT_LIST[Id],0)),"") -> COGS | H18: =IFERROR(INDEX(PBC_ACCOUNT_LIST[Summary Grouping],MATCH(Drivers!L18,PBC_ACCOUNT_LIST[Id],0)),"") -> COGS | J18: =IFERROR(INDEX(PBC_ACCOUNT_LIST[Cash Flow Section],MATCH(Drivers!L18,PBC_ACCOUNT_LIST[Id],0)),"") -> 0 | K18: Account | L18: 165 | P18: =SUMIFS($AI18:$BS18,$AI$4:$BS$4,">="&P$4,$AI$5:$BS$5,"<="&P$5) -> 11253.66 | Q18: =SUMIFS($AI18:$BS18,$AI$4:$BS$4,">="&Q$4,$AI$5:$BS$5,"<="&Q$5) -> 18217.351 | R18: =SUMIFS($AI18:$BS18,$AI$4:$BS$4,">="&R$4,$AI$5:$BS$5,"<="&R$5) -> 22884.008 | U18: =SUMIFS($AI18:$BS18,$AI$4:$BS$4,">="&U$4,$AI$5:$BS$5,"<="&U$5) -> 2369 | V18: =SUMIFS($AI18:$BS18,$AI$4:$BS$4,">="&V$4,$AI$5:$BS$5,"<="&V$5) -> 2644.5 | W18: =SUMIFS($AI18:$BS18,$AI$4:$BS$4,">="&W$4,$AI$5:$BS$5,"<="&W$5) -> 2991.5 | X18: =SUMIFS($AI18:$BS18,$AI$4:$BS$4,">="&X$4,$AI$5:$BS$5,"<="&X$5) -> 3248.66 | Y18: =SUMIFS($AI18:$BS18,$AI$4:$BS$4,">="&Y$4,$AI$5:$BS$5,"<="&Y$5) -> 3759.81 | Z18: =SUMIFS($AI18:$BS18,$AI$4:$BS$4,">="&Z$4,$AI$5:$BS$5,"<="&Z$5) -> 4353.36 | AA18: =SUMIFS($AI18:$BS18,$AI$4:$BS$4,">="&AA$4,$AI$5:$BS$5,"<="&AA$5) -> 5039.2 | AB18: =SUMIFS($AI18:$BS18,$AI$4:$BS$4,">="&AB$4,$AI$5:$BS$5,"<="&AB$5) -> 5064.9806 | ... AF18: =SUMIFS($AI18:$BS18,$AI$4:$BS$4,">="&AF$4,$AI$5:$BS$5,"<="&AF$5) -> 6082.1668 | AI18: =SUMIFS(PBC_PROFIT_AND_LOSS[AccountBalance], PBC_PROFIT_AND_LOSS[Id],$L18,PBC_PROFIT_AND_LOSS[Date],AI$5) -> 807.5 | AJ18: =SUMIFS(PBC_PROFIT_AND_LOSS[AccountBalance], PBC_PROFIT_AND_LOSS[Id],$L18,PBC_PROFIT_AND_LOSS[Date],AJ$5) -> 742 | AK18: =SUMIFS(PBC_PROFIT_AND_LOSS[AccountBalance], PBC_PROFIT_AND_LOSS[Id],$L18,PBC_PROFIT_AND_LOSS[Date],AK$5) -> 848 | AL18: =SUMIFS(PBC_PROFIT_AND_LOSS[AccountBalance], PBC_PROFIT_AND_LOSS[Id],$L18,PBC_PROFIT_AND_LOSS[Date],AL$5) -> 779 | AM18: =SUMIFS(PBC_PROFIT_AND_LOSS[AccountBalance], PBC_PROFIT_AND_LOSS[Id],$L18,PBC_PROFIT_AND_LOSS[Date],AM$5) -> 890.5 | AN18: =SUMIFS(PBC_PROFIT_AND_LOSS[AccountBalance], PBC_PROFIT_AND_LOSS[Id],$L18,PBC_PROFIT_AND_LOSS[Date],AN$5) -> 818.5 | AO18: =SUMIFS(PBC_PROFIT_AND_LOSS[AccountBalance], PBC_PROFIT_AND_LOSS[Id],$L18,PBC_PROFIT_AND_LOSS[Date],AO$5) -> 935.5 | AP18: =SUMIFS(PBC_PROFIT_AND_LOSS[AccountBalance], PBC_PROFIT_AND_LOSS[Id],$L18,PBC_PROFIT_AND_LOSS[Date],AP$5) -> 981 | ... BD18: =SUMIFS(PBC_PROFIT_AND_LOSS[AccountBalance], PBC_PROFIT_AND_LOSS[Id],$L18,PBC_PROFIT_AND_LOSS[Date],BD$5) -> 1762.32 | BE18: =AVERAGE(AY18:BD18) * (1 + $F18) -> 1643.698 | BF18: =AVERAGE(AZ18:BE18) * (1 + $F18) -> 1689.6702 | BG18: =AVERAGE(BA18:BF18) * (1 + $F18) -> 1731.6124 | BH18: =AVERAGE(BB18:BG18) * (1 + $F18) -> 1768.2316 | BI18: =AVERAGE(BC18:BH18) * (1 + $F18) -> 1797.9381 | BJ18: =AVERAGE(BD18:BI18) * (1 + $F18) -> 1818.8573 | BK18: =AVERAGE(BE18:BJ18) * (1 + $F18) -> 1828.7513 | BL18: =AVERAGE(BF18:BK18) * (1 + $F18) -> 1861.1357 | ... BS18: =AVERAGE(BM18:BR18) * (1 + $F18) -> 2056.6735
D19: Cost of goods sold | E19: Average 6 months with a buffer | F19: 0.05 | G19: =IFERROR(INDEX(PBC_ACCOUNT_LIST[Drivers Section],MATCH(Drivers!L19,PBC_ACCOUNT_LIST[Id],0)),"") -> COGS | H19: =IFERROR(INDEX(PBC_ACCOUNT_LIST[Summary Grouping],MATCH(Drivers!L19,PBC_ACCOUNT_LIST[Id],0)),"") -> COGS | J19: =IFERROR(INDEX(PBC_ACCOUNT_LIST[Cash Flow Section],MATCH(Drivers!L19,PBC_ACCOUNT_LIST[Id],0)),"") -> 0 | K19: Account | L19: 24 | P19: =SUMIFS($AI19:$BS19,$AI$4:$BS$4,">="&P$4,$AI$5:$BS$5,"<="&P$5) -> 0 | Q19: =SUMIFS($AI19:$BS19,$AI$4:$BS$4,">="&Q$4,$AI$5:$BS$5,"<="&Q$5) -> 486.67031 | R19: =SUMIFS($AI19:$BS19,$AI$4:$BS$4,">="&R$4,$AI$5:$BS$5,"<="&R$5) -> 587.74614 | U19: =SUMIFS($AI19:$BS19,$AI$4:$BS$4,">="&U$4,$AI$5:$BS$5,"<="&U$5) -> 0 | V19: =SUMIFS($AI19:$BS19,$AI$4:$BS$4,">="&V$4,$AI$5:$BS$5,"<="&V$5) -> 0 | W19: =SUMIFS($AI19:$BS19,$AI$4:$BS$4,">="&W$4,$AI$5:$BS$5,"<="&W$5) -> 0 | X19: =SUMIFS($AI19:$BS19,$AI$4:$BS$4,">="&X$4,$AI$5:$BS$5,"<="&X$5) -> 0 | Y19: =SUMIFS($AI19:$BS19,$AI$4:$BS$4,">="&Y$4,$AI$5:$BS$5,"<="&Y$5) -> 0 | Z19: =SUMIFS($AI19:$BS19,$AI$4:$BS$4,">="&Z$4,$AI$5:$BS$5,"<="&Z$5) -> 300 | AA19: =SUMIFS($AI19:$BS19,$AI$4:$BS$4,">="&AA$4,$AI$5:$BS$5,"<="&AA$5) -> 0 | AB19: =SUMIFS($AI19:$BS19,$AI$4:$BS$4,">="&AB$4,$AI$5:$BS$5,"<="&AB$5) -> 186.67031 | ... AF19: =SUMIFS($AI19:$BS19,$AI$4:$BS$4,">="&AF$4,$AI$5:$BS$5,"<="&AF$5) -> 162.72724 | AI19: =SUMIFS(PBC_PROFIT_AND_LOSS[AccountBalance], PBC_PROFIT_AND_LOSS[Id],$L19,PBC_PROFIT_AND_LOSS[Date],AI$5) -> 0 | AJ19: =SUMIFS(PBC_PROFIT_AND_LOSS[AccountBalance], PBC_PROFIT_AND_LOSS[Id],$L19,PBC_PROFIT_AND_LOSS[Date],AJ$5) -> 0 | AK19: =SUMIFS(PBC_PROFIT_AND_LOSS[AccountBalance], PBC_PROFIT_AND_LOSS[Id],$L19,PBC_PROFIT_AND_LOSS[Date],AK$5) -> 0 | AL19: =SUMIFS(PBC_PROFIT_AND_LOSS[AccountBalance], PBC_PROFIT_AND_LOSS[Id],$L19,PBC_PROFIT_AND_LOSS[Date],AL$5) -> 0 | AM19: =SUMIFS(PBC_PROFIT_AND_LOSS[AccountBalance], PBC_PROFIT_AND_LOSS[Id],$L19,PBC_PROFIT_AND_LOSS[Date],AM$5) -> 0 | AN19: =SUMIFS(PBC_PROFIT_AND_LOSS[AccountBalance], PBC_PROFIT_AND_LOSS[Id],$L19,PBC_PROFIT_AND_LOSS[Date],AN$5) -> 0 | AO19: =SUMIFS(PBC_PROFIT_AND_LOSS[AccountBalance], PBC_PROFIT_AND_LOSS[Id],$L19,PBC_PROFIT_AND_LOSS[Date],AO$5) -> 0 | AP19: =SUMIFS(PBC_PROFIT_AND_LOSS[AccountBalance], PBC_PROFIT_AND_LOSS[Id],$L19,PBC_PROFIT_AND_LOSS[Date],AP$5) -> 0 | ... BD19: =SUMIFS(PBC_PROFIT_AND_LOSS[AccountBalance], PBC_PROFIT_AND_LOSS[Id],$L19,PBC_PROFIT_AND_LOSS[Date],BD$5) -> 0 | BE19: =AVERAGE(AY19:BD19) * (1 + $F19) -> 52.5 | BF19: =AVERAGE(AZ19:BE19) * (1 + $F19) -> 61.6875 | BG19: =AVERAGE(BA19:BF19) * (1 + $F19) -> 72.482813 | BH19: =AVERAGE(BB19:BG19) * (1 + $F19) -> 32.667305 | BI19: =AVERAGE(BC19:BH19) * (1 + $F19) -> 38.384083 | BJ19: =AVERAGE(BD19:BI19) * (1 + $F19) -> 45.101298 | BK19: =AVERAGE(BE19:BJ19) * (1 + $F19) -> 52.994025 | BL19: =AVERAGE(BF19:BK19) * (1 + $F19) -> 53.080479 | ... BS19: =AVERAGE(BM19:BR19) * (1 + $F19) -> 54.438993
D20: Inventory Shrinkage | E20: Average 6 months with a buffer | F20: 0.05 | G20: =IFERROR(INDEX(PBC_ACCOUNT_LIST[Drivers Section],MATCH(Drivers!L20,PBC_ACCOUNT_LIST[Id],0)),"") -> COGS | H20: =IFERROR(INDEX(PBC_ACCOUNT_LIST[Summary Grouping],MATCH(Drivers!L20,PBC_ACCOUNT_LIST[Id],0)),"") -> COGS | J20: =IFERROR(INDEX(PBC_ACCOUNT_LIST[Cash Flow Section],MATCH(Drivers!L20,PBC_ACCOUNT_LIST[Id],0)),"") -> 0 | K20: Account | L20: 207 | P20: =SUMIFS($AI20:$BS20,$AI$4:$BS$4,">="&P$4,$AI$5:$BS$5,"<="&P$5) -> 0 | Q20: =SUMIFS($AI20:$BS20,$AI$4:$BS$4,">="&Q$4,$AI$5:$BS$5,"<="&Q$5) -> -1622.2344 | R20: =SUMIFS($AI20:$BS20,$AI$4:$BS$4,">="&R$4,$AI$5:$BS$5,"<="&R$5) -> -2698.7436 | U20: =SUMIFS($AI20:$BS20,$AI$4:$BS$4,">="&U$4,$AI$5:$BS$5,"<="&U$5) -> 0 | V20: =SUMIFS($AI20:$BS20,$AI$4:$BS$4,">="&V$4,$AI$5:$BS$5,"<="&V$5) -> 0 | W20: =SUMIFS($AI20:$BS20,$AI$4:$BS$4,">="&W$4,$AI$5:$BS$5,"<="&W$5) -> 0 | X20: =SUMIFS($AI20:$BS20,$AI$4:$BS$4,">="&X$4,$AI$5:$BS$5,"<="&X$5) -> 0 | Y20: =SUMIFS($AI20:$BS20,$AI$4:$BS$4,">="&Y$4,$AI$5:$BS$5,"<="&Y$5) -> 0 | Z20: =SUMIFS($AI20:$BS20,$AI$4:$BS$4,">="&Z$4,$AI$5:$BS$5,"<="&Z$5) -> 0 | AA20: =SUMIFS($AI20:$BS20,$AI$4:$BS$4,">="&AA$4,$AI$5:$BS$5,"<="&AA$5) -> -1000 | AB20: =SUMIFS($AI20:$BS20,$AI$4:$BS$4,">="&AB$4,$AI$5:$BS$5,"<="&AB$5) -> -622.23438 | ... AF20: =SUMIFS($AI20:$BS20,$AI$4:$BS$4,">="&AF$4,$AI$5:$BS$5,"<="&AF$5) -> -718.15269 | AI20: =SUMIFS(PBC_PROFIT_AND_LOSS[AccountBalance], PBC_PROFIT_AND_LOSS[Id],$L20,PBC_PROFIT_AND_LOSS[Date],AI$5) -> 0 | AJ20: =SUMIFS(PBC_PROFIT_AND_LOSS[AccountBalance], PBC_PROFIT_AND_LOSS[Id],$L20,PBC_PROFIT_AND_LOSS[Date],AJ$5) -> 0 | AK20: =SUMIFS(PBC_PROFIT_AND_LOSS[AccountBalance], PBC_PROFIT_AND_LOSS[Id],$L20,PBC_PROFIT_AND_LOSS[Date],AK$5) -> 0 | AL20: =SUMIFS(PBC_PROFIT_AND_LOSS[AccountBalance], PBC_PROFIT_AND_LOSS[Id],$L20,PBC_PROFIT_AND_LOSS[Date],AL$5) -> 0 | AM20: =SUMIFS(PBC_PROFIT_AND_LOSS[AccountBalance], PBC_PROFIT_AND_LOSS[Id],$L20,PBC_PROFIT_AND_LOSS[Date],AM$5) -> 0 | AN20: =SUMIFS(PBC_PROFIT_AND_LOSS[AccountBalance], PBC_PROFIT_AND_LOSS[Id],$L20,PBC_PROFIT_AND_LOSS[Date],AN$5) -> 0 | AO20: =SUMIFS(PBC_PROFIT_AND_LOSS[AccountBalance], PBC_PROFIT_AND_LOSS[Id],$L20,PBC_PROFIT_AND_LOSS[Date],AO$5) -> 0 | AP20: =SUMIFS(PBC_PROFIT_AND_LOSS[AccountBalance], PBC_PROFIT_AND_LOSS[Id],$L20,PBC_PROFIT_AND_LOSS[Date],AP$5) -> 0 | ... BD20: =SUMIFS(PBC_PROFIT_AND_LOSS[AccountBalance], PBC_PROFIT_AND_LOSS[Id],$L20,PBC_PROFIT_AND_LOSS[Date],BD$5) -> 0 | BE20: =AVERAGE(AY20:BD20) * (1 + $F20) -> -175 | BF20: =AVERAGE(AZ20:BE20) * (1 + $F20) -> -205.625 | BG20: =AVERAGE(BA20:BF20) * (1 + $F20) -> -241.60938 | BH20: =AVERAGE(BB20:BG20) * (1 + $F20) -> -283.89102 | BI20: =AVERAGE(BC20:BH20) * (1 + $F20) -> -158.57194 | BJ20: =AVERAGE(BD20:BI20) * (1 + $F20) -> -186.32203 | BK20: =AVERAGE(BE20:BJ20) * (1 + $F20) -> -218.92839 | BL20: =AVERAGE(BF20:BK20) * (1 + $F20) -> -226.61586 | ... BS20: =AVERAGE(BM20:BR20) * (1 + $F20) -> -241.93405
C22: Gross Profit | P22: =P10-P15 -> 541123.34 | Q22: =Q10-Q15 -> 832155.04 | R22: =R10-R15 -> 1045303.8 | U22: =U10-U15 -> 129970 | V22: =V10-V15 -> 131277.5 | W22: =W10-W15 -> 134215.5 | X22: =X10-X15 -> 145660.34 | Y22: =Y10-Y15 -> 168621.8 | Z22: =Z10-Z15 -> 203598.49 | AA22: =AA10-AA15 -> 226967.29 | AB22: =AB10-AB15 -> 232967.46 | ... AF22: =AF10-AF15 -> 278006.6 | AI22: =AI10-AI15 -> 36202.5 | AJ22: =AJ10-AJ15 -> 44857.5 | AK22: =AK10-AK15 -> 38012 | AL22: =AL10-AL15 -> 47100.5 | AM22: =AM10-AM15 -> 39913.5 | AN22: =AN10-AN15 -> 49455.5 | AO22: =AO10-AO15 -> 41908.5 | AP22: =AP10-AP15 -> 44005 | ... BS22: =BS10-BS15 -> 93990.093
D23: Gross Margin | P23: =IFERROR(P22/P10,0) -> 0.91037667 | Q23: =IFERROR(Q22/Q10,0) -> 0.90776695 | R23: =IFERROR(R22/R10,0) -> 0.90830578 | U23: =IFERROR(U22/U10,0) -> 0.91958171 | V23: =IFERROR(V22/V10,0) -> 0.91273318 | W23: =IFERROR(W22/W10,0) -> 0.9050819 | X23: =IFERROR(X22/X10,0) -> 0.90506552 | Y23: =IFERROR(Y22/Y10,0) -> 0.90507389 | Z23: =IFERROR(Z22/Z10,0) -> 0.90740691 | AA23: =IFERROR(AA22/AA10,0) -> 0.90907143 | AB23: =IFERROR(AB22/AB10,0) -> 0.90876882 | ... AF23: =IFERROR(AF22/AF10,0) -> 0.90834394 | AI23: =IFERROR(AI22/AI10,0) -> 0.9050625 | AJ23: =IFERROR(AJ22/AJ10,0) -> 0.9257272 | AK23: =IFERROR(AK22/AK10,0) -> 0.90504762 | AL23: =IFERROR(AL22/AL10,0) -> 0.92572647 | AM23: =IFERROR(AM22/AM10,0) -> 0.90506803 | AN23: =IFERROR(AN22/AN10,0) -> 0.92571691 | AO23: =IFERROR(AO22/AO10,0) -> 0.90505345 | AP23: =IFERROR(AP22/AP10,0) -> 0.90508021 | ... BS23: =IFERROR(BS22/BS10,0) -> 0.90832577
C25: Opex | P25: =SUM(P26:P50) -> 1836654.3 | Q25: =SUM(Q26:Q50) -> 3135703.5 | R25: =SUM(R26:R50) -> 3938807.8 | U25: =SUM(U26:U50) -> 342976.5 | V25: =SUM(V26:V50) -> 419934.5 | W25: =SUM(W26:W50) -> 514914.5 | X25: =SUM(X26:X50) -> 558828.84 | Y25: =SUM(Y26:Y50) -> 646917.29 | Z25: =SUM(Z26:Z50) -> 749887.28 | AA25: =SUM(AA26:AA50) -> 866929.28 | AB25: =SUM(AB26:AB50) -> 871969.63 | ... AF25: =SUM(AF26:AF50) -> 1046887.4 | AI25: =IF(AI$5<=LatestMonthOfActuals,SUMIFS(AI26:AI50,$K26:$K50,"Account"),SUMIFS(AI26:AI50,$K26:$K50,"<>Sub-Account")) -> 138892 | AJ25: =IF(AJ$5<=LatestMonthOfActuals,SUMIFS(AJ26:AJ50,$K26:$K50,"Account"),SUMIFS(AJ26:AJ50,$K26:$K50,"<>Sub-Account")) -> 96166.5 | AK25: =IF(AK$5<=LatestMonthOfActuals,SUMIFS(AK26:AK50,$K26:$K50,"Account"),SUMIFS(AK26:AK50,$K26:$K50,"<>Sub-Account")) -> 145836 | AL25: =IF(AL$5<=LatestMonthOfActuals,SUMIFS(AL26:AL50,$K26:$K50,"Account"),SUMIFS(AL26:AL50,$K26:$K50,"<>Sub-Account")) -> 100974 | AM25: =IF(AM$5<=LatestMonthOfActuals,SUMIFS(AM26:AM50,$K26:$K50,"Account"),SUMIFS(AM26:AM50,$K26:$K50,"<>Sub-Account")) -> 153128 | AN25: =IF(AN$5<=LatestMonthOfActuals,SUMIFS(AN26:AN50,$K26:$K50,"Account"),SUMIFS(AN26:AN50,$K26:$K50,"<>Sub-Account")) -> 106022 | AO25: =IF(AO$5<=LatestMonthOfActuals,SUMIFS(AO26:AO50,$K26:$K50,"Account"),SUMIFS(AO26:AO50,$K26:$K50,"<>Sub-Account")) -> 160784.5 | AP25: =IF(AP$5<=LatestMonthOfActuals,SUMIFS(AP26:AP50,$K26:$K50,"Account"),SUMIFS(AP26:AP50,$K26:$K50,"<>Sub-Account")) -> 168825 | ... BS25: =IF(BS$5<=LatestMonthOfActuals,SUMIFS(BS26:BS50,$K26:$K50,"Account"),SUMIFS(BS26:BS50,$K26:$K50,"<>Sub-Account")) -> 354001.13
D27: 60100 Advertising & Marketing | E27: Average 6 months with a buffer | F27: 0.05 | G27: =IFERROR(INDEX(PBC_ACCOUNT_LIST[Drivers Section],MATCH(Drivers!L27,PBC_ACCOUNT_LIST[Id],0)),"") -> Opex | H27: =IFERROR(INDEX(PBC_ACCOUNT_LIST[Summary Grouping],MATCH(Drivers!L27,PBC_ACCOUNT_LIST[Id],0)),"") -> Marketing & Advertising | J27: =IFERROR(INDEX(PBC_ACCOUNT_LIST[Cash Flow Section],MATCH(Drivers!L27,PBC_ACCOUNT_LIST[Id],0)),"") -> 0 | K27: Account | L27: 200 | P27: =SUMIFS($AI27:$BS27,$AI$4:$BS$4,">="&P$4,$AI$5:$BS$5,"<="&P$5) -> 212414 | Q27: =SUMIFS($AI27:$BS27,$AI$4:$BS$4,">="&Q$4,$AI$5:$BS$5,"<="&Q$5) -> 356884.76 | R27: =SUMIFS($AI27:$BS27,$AI$4:$BS$4,">="&R$4,$AI$5:$BS$5,"<="&R$5) -> 448296.78 | U27: =SUMIFS($AI27:$BS27,$AI$4:$BS$4,">="&U$4,$AI$5:$BS$5,"<="&U$5) -> 41182 | V27: =SUMIFS($AI27:$BS27,$AI$4:$BS$4,">="&V$4,$AI$5:$BS$5,"<="&V$5) -> 48962 | W27: =SUMIFS($AI27:$BS27,$AI$4:$BS$4,">="&W$4,$AI$5:$BS$5,"<="&W$5) -> 58634 | X27: =SUMIFS($AI27:$BS27,$AI$4:$BS$4,">="&X$4,$AI$5:$BS$5,"<="&X$5) -> 63636 | Y27: =SUMIFS($AI27:$BS27,$AI$4:$BS$4,">="&Y$4,$AI$5:$BS$5,"<="&Y$5) -> 73666.37 | Z27: =SUMIFS($AI27:$BS27,$AI$4:$BS$4,">="&Z$4,$AI$5:$BS$5,"<="&Z$5) -> 85277.35 | AA27: =SUMIFS($AI27:$BS27,$AI$4:$BS$4,">="&AA$4,$AI$5:$BS$5,"<="&AA$5) -> 98719 | AB27: =SUMIFS($AI27:$BS27,$AI$4:$BS$4,">="&AB$4,$AI$5:$BS$5,"<="&AB$5) -> 99222.042 | ... AF27: =SUMIFS($AI27:$BS27,$AI$4:$BS$4,">="&AF$4,$AI$5:$BS$5,"<="&AF$5) -> 119149.38 | AI27: =SUMIFS(PBC_PROFIT_AND_LOSS[AccountBalance], PBC_PROFIT_AND_LOSS[Id],$L27,PBC_PROFIT_AND_LOSS[Date],AI$5) -> 15816 | AJ27: =SUMIFS(PBC_PROFIT_AND_LOSS[AccountBalance], PBC_PROFIT_AND_LOSS[Id],$L27,PBC_PROFIT_AND_LOSS[Date],AJ$5) -> 11988 | AK27: =SUMIFS(PBC_PROFIT_AND_LOSS[AccountBalance], PBC_PROFIT_AND_LOSS[Id],$L27,PBC_PROFIT_AND_LOSS[Date],AK$5) -> 16607 | AL27: =SUMIFS(PBC_PROFIT_AND_LOSS[AccountBalance], PBC_PROFIT_AND_LOSS[Id],$L27,PBC_PROFIT_AND_LOSS[Date],AL$5) -> 12587 | AM27: =SUMIFS(PBC_PROFIT_AND_LOSS[AccountBalance], PBC_PROFIT_AND_LOSS[Id],$L27,PBC_PROFIT_AND_LOSS[Date],AM$5) -> 17437 | AN27: =SUMIFS(PBC_PROFIT_AND_LOSS[AccountBalance], PBC_PROFIT_AND_LOSS[Id],$L27,PBC_PROFIT_AND_LOSS[Date],AN$5) -> 13216 | AO27: =SUMIFS(PBC_PROFIT_AND_LOSS[AccountBalance], PBC_PROFIT_AND_LOSS[Id],$L27,PBC_PROFIT_AND_LOSS[Date],AO$5) -> 18309 | AP27: =SUMIFS(PBC_PROFIT_AND_LOSS[AccountBalance], PBC_PROFIT_AND_LOSS[Id],$L27,PBC_PROFIT_AND_LOSS[Date],AP$5) -> 19224 | ... BD27: =SUMIFS(PBC_PROFIT_AND_LOSS[AccountBalance], PBC_PROFIT_AND_LOSS[Id],$L27,PBC_PROFIT_AND_LOSS[Date],BD$5) -> 34524.25 | BE27: =AVERAGE(AY27:BD27) * (1 + $F27) -> 32199.361 | BF27: =AVERAGE(AZ27:BE27) * (1 + $F27) -> 33100.324 | BG27: =AVERAGE(BA27:BF27) * (1 + $F27) -> 33922.356 | BH27: =AVERAGE(BB27:BG27) * (1 + $F27) -> 34639.682 | BI27: =AVERAGE(BC27:BH27) * (1 + $F27) -> 35221.588 | BJ27: =AVERAGE(BD27:BI27) * (1 + $F27) -> 35631.323 | BK27: =AVERAGE(BE27:BJ27) * (1 + $F27) -> 35825.061 | BL27: =AVERAGE(BF27:BK27) * (1 + $F27) -> 36459.559 | ... BS27: =AVERAGE(BM27:BR27) * (1 + $F27) -> 40290.148
D28: 60200 Bank Charges & Fees | E28: Average 6 months with a buffer | F28: 0.05 | G28: =IFERROR(INDEX(PBC_ACCOUNT_LIST[Drivers Section],MATCH(Drivers!L28,PBC_ACCOUNT_LIST[Id],0)),"") -> Opex | H28: =IFERROR(INDEX(PBC_ACCOUNT_LIST[Summary Grouping],MATCH(Drivers!L28,PBC_ACCOUNT_LIST[Id],0)),"") -> Office & Other G&A | J28: =IFERROR(INDEX(PBC_ACCOUNT_LIST[Cash Flow Section],MATCH(Drivers!L28,PBC_ACCOUNT_LIST[Id],0)),"") -> 0 | K28: Account | L28: 166 | P28: =SUMIFS($AI28:$BS28,$AI$4:$BS$4,">="&P$4,$AI$5:$BS$5,"<="&P$5) -> 14737.66 | Q28: =SUMIFS($AI28:$BS28,$AI$4:$BS$4,">="&Q$4,$AI$5:$BS$5,"<="&Q$5) -> 24565.472 | R28: =SUMIFS($AI28:$BS28,$AI$4:$BS$4,">="&R$4,$AI$5:$BS$5,"<="&R$5) -> 30854.729 | U28: =SUMIFS($AI28:$BS28,$AI$4:$BS$4,">="&U$4,$AI$5:$BS$5,"<="&U$5) -> 2912.5 | V28: =SUMIFS($AI28:$BS28,$AI$4:$BS$4,">="&V$4,$AI$5:$BS$5,"<="&V$5) -> 3412.5 | W28: =SUMIFS($AI28:$BS28,$AI$4:$BS$4,">="&W$4,$AI$5:$BS$5,"<="&W$5) -> 4034.5 | X28: =SUMIFS($AI28:$BS28,$AI$4:$BS$4,">="&X$4,$AI$5:$BS$5,"<="&X$5) -> 4378.16 | Y28: =SUMIFS($AI28:$BS28,$AI$4:$BS$4,">="&Y$4,$AI$5:$BS$5,"<="&Y$5) -> 5072.28 | Z28: =SUMIFS($AI28:$BS28,$AI$4:$BS$4,">="&Z$4,$AI$5:$BS$5,"<="&Z$5) -> 5869.62 | AA28: =SUMIFS($AI28:$BS28,$AI$4:$BS$4,">="&AA$4,$AI$5:$BS$5,"<="&AA$5) -> 6794.42 | AB28: =SUMIFS($AI28:$BS28,$AI$4:$BS$4,">="&AB$4,$AI$5:$BS$5,"<="&AB$5) -> 6829.1523 | ... AF28: =SUMIFS($AI28:$BS28,$AI$4:$BS$4,">="&AF$4,$AI$5:$BS$5,"<="&AF$5) -> 8200.644 | AI28: =SUMIFS(PBC_PROFIT_AND_LOSS[AccountBalance], PBC_PROFIT_AND_LOSS[Id],$L28,PBC_PROFIT_AND_LOSS[Date],AI$5) -> 1088.5 | AJ28: =SUMIFS(PBC_PROFIT_AND_LOSS[AccountBalance], PBC_PROFIT_AND_LOSS[Id],$L28,PBC_PROFIT_AND_LOSS[Date],AJ$5) -> 863.5 | AK28: =SUMIFS(PBC_PROFIT_AND_LOSS[AccountBalance], PBC_PROFIT_AND_LOSS[Id],$L28,PBC_PROFIT_AND_LOSS[Date],AK$5) -> 1143 | AL28: =SUMIFS(PBC_PROFIT_AND_LOSS[AccountBalance], PBC_PROFIT_AND_LOSS[Id],$L28,PBC_PROFIT_AND_LOSS[Date],AL$5) -> 906 | AM28: =SUMIFS(PBC_PROFIT_AND_LOSS[AccountBalance], PBC_PROFIT_AND_LOSS[Id],$L28,PBC_PROFIT_AND_LOSS[Date],AM$5) -> 1200 | AN28: =SUMIFS(PBC_PROFIT_AND_LOSS[AccountBalance], PBC_PROFIT_AND_LOSS[Id],$L28,PBC_PROFIT_AND_LOSS[Date],AN$5) -> 952 | AO28: =SUMIFS(PBC_PROFIT_AND_LOSS[AccountBalance], PBC_PROFIT_AND_LOSS[Id],$L28,PBC_PROFIT_AND_LOSS[Date],AO$5) -> 1260.5 | AP28: =SUMIFS(PBC_PROFIT_AND_LOSS[AccountBalance], PBC_PROFIT_AND_LOSS[Id],$L28,PBC_PROFIT_AND_LOSS[Date],AP$5) -> 1323 | ... BD28: =SUMIFS(PBC_PROFIT_AND_LOSS[AccountBalance], PBC_PROFIT_AND_LOSS[Id],$L28,PBC_PROFIT_AND_LOSS[Date],BD$5) -> 2376.16 | BE28: =AVERAGE(AY28:BD28) * (1 + $F28) -> 2216.207 | BF28: =AVERAGE(AZ28:BE28) * (1 + $F28) -> 2278.1932 | BG28: =AVERAGE(BA28:BF28) * (1 + $F28) -> 2334.752 | BH28: =AVERAGE(BB28:BG28) * (1 + $F28) -> 2384.1251 | BI28: =AVERAGE(BC28:BH28) * (1 + $F28) -> 2424.1783 | BJ28: =AVERAGE(BD28:BI28) * (1 + $F28) -> 2452.3827 | BK28: =AVERAGE(BE28:BJ28) * (1 + $F28) -> 2465.7217 | BL28: =AVERAGE(BF28:BK28) * (1 + $F28) -> 2509.3868 | ... BS28: =AVERAGE(BM28:BR28) * (1 + $F28) -> 2773.0328
D29: 60300 Conferences & Events | E29: Average 6 months with a buffer | F29: 0.05 | G29: =IFERROR(INDEX(PBC_ACCOUNT_LIST[Drivers Section],MATCH(Drivers!L29,PBC_ACCOUNT_LIST[Id],0)),"") -> Opex | H29: =IFERROR(INDEX(PBC_ACCOUNT_LIST[Summary Grouping],MATCH(Drivers!L29,PBC_ACCOUNT_LIST[Id],0)),"") -> Marketing & Advertising | J29: =IFERROR(INDEX(PBC_ACCOUNT_LIST[Cash Flow Section],MATCH(Drivers!L29,PBC_ACCOUNT_LIST[Id],0)),"") -> 0 | K29: Account | L29: 167 | P29: =SUMIFS($AI29:$BS29,$AI$4:$BS$4,">="&P$4,$AI$5:$BS$5,"<="&P$5) -> 339253 | Q29: =SUMIFS($AI29:$BS29,$AI$4:$BS$4,">="&Q$4,$AI$5:$BS$5,"<="&Q$5) -> 590267.45 | R29: =SUMIFS($AI29:$BS29,$AI$4:$BS$4,">="&R$4,$AI$5:$BS$5,"<="&R$5) -> 741460.24 | U29: =SUMIFS($AI29:$BS29,$AI$4:$BS$4,">="&U$4,$AI$5:$BS$5,"<="&U$5) -> 60265 | V29: =SUMIFS($AI29:$BS29,$AI$4:$BS$4,">="&V$4,$AI$5:$BS$5,"<="&V$5) -> 76761 | W29: =SUMIFS($AI29:$BS29,$AI$4:$BS$4,">="&W$4,$AI$5:$BS$5,"<="&W$5) -> 96978 | X29: =SUMIFS($AI29:$BS29,$AI$4:$BS$4,">="&X$4,$AI$5:$BS$5,"<="&X$5) -> 105249 | Y29: =SUMIFS($AI29:$BS29,$AI$4:$BS$4,">="&Y$4,$AI$5:$BS$5,"<="&Y$5) -> 121839.5 | Z29: =SUMIFS($AI29:$BS29,$AI$4:$BS$4,">="&Z$4,$AI$5:$BS$5,"<="&Z$5) -> 141043.37 | AA29: =SUMIFS($AI29:$BS29,$AI$4:$BS$4,">="&AA$4,$AI$5:$BS$5,"<="&AA$5) -> 163276.46 | AB29: =SUMIFS($AI29:$BS29,$AI$4:$BS$4,">="&AB$4,$AI$5:$BS$5,"<="&AB$5) -> 164108.12 | ... AF29: =SUMIFS($AI29:$BS29,$AI$4:$BS$4,">="&AF$4,$AI$5:$BS$5,"<="&AF$5) -> 197067.05 | AI29: =SUMIFS(PBC_PROFIT_AND_LOSS[AccountBalance], PBC_PROFIT_AND_LOSS[Id],$L29,PBC_PROFIT_AND_LOSS[Date],AI$5) -> 26158.5 | AJ29: =SUMIFS(PBC_PROFIT_AND_LOSS[AccountBalance], PBC_PROFIT_AND_LOSS[Id],$L29,PBC_PROFIT_AND_LOSS[Date],AJ$5) -> 15999 | AK29: =SUMIFS(PBC_PROFIT_AND_LOSS[AccountBalance], PBC_PROFIT_AND_LOSS[Id],$L29,PBC_PROFIT_AND_LOSS[Date],AK$5) -> 27467 | AL29: =SUMIFS(PBC_PROFIT_AND_LOSS[AccountBalance], PBC_PROFIT_AND_LOSS[Id],$L29,PBC_PROFIT_AND_LOSS[Date],AL$5) -> 16799 | AM29: =SUMIFS(PBC_PROFIT_AND_LOSS[AccountBalance], PBC_PROFIT_AND_LOSS[Id],$L29,PBC_PROFIT_AND_LOSS[Date],AM$5) -> 28840 | AN29: =SUMIFS(PBC_PROFIT_AND_LOSS[AccountBalance], PBC_PROFIT_AND_LOSS[Id],$L29,PBC_PROFIT_AND_LOSS[Date],AN$5) -> 17639 | AO29: =SUMIFS(PBC_PROFIT_AND_LOSS[AccountBalance], PBC_PROFIT_AND_LOSS[Id],$L29,PBC_PROFIT_AND_LOSS[Date],AO$5) -> 30282 | AP29: =SUMIFS(PBC_PROFIT_AND_LOSS[AccountBalance], PBC_PROFIT_AND_LOSS[Id],$L29,PBC_PROFIT_AND_LOSS[Date],AP$5) -> 31796 | ... BD29: =SUMIFS(PBC_PROFIT_AND_LOSS[AccountBalance], PBC_PROFIT_AND_LOSS[Id],$L29,PBC_PROFIT_AND_LOSS[Date],BD$5) -> 57101.44 | BE29: =AVERAGE(AY29:BD29) * (1 + $F29) -> 53255.97 | BF29: =AVERAGE(AZ29:BE29) * (1 + $F29) -> 54746.265 | BG29: =AVERAGE(BA29:BF29) * (1 + $F29) -> 56105.886 | BH29: =AVERAGE(BB29:BG29) * (1 + $F29) -> 57292.302 | BI29: =AVERAGE(BC29:BH29) * (1 + $F29) -> 58254.734 | BJ29: =AVERAGE(BD29:BI29) * (1 + $F29) -> 58932.405 | BK29: =AVERAGE(BE29:BJ29) * (1 + $F29) -> 59252.823 | BL29: =AVERAGE(BF29:BK29) * (1 + $F29) -> 60302.273 | ... BS29: =AVERAGE(BM29:BR29) * (1 + $F29) -> 66637.871
D30: 60400 Dues & Subscriptions | E30: Average 6 months with a buffer | F30: 0.05 | G30: =IFERROR(INDEX(PBC_ACCOUNT_LIST[Drivers Section],MATCH(Drivers!L30,PBC_ACCOUNT_LIST[Id],0)),"") -> Opex | H30: =IFERROR(INDEX(PBC_ACCOUNT_LIST[Summary Grouping],MATCH(Drivers!L30,PBC_ACCOUNT_LIST[Id],0)),"") -> Office & Other G&A | J30: =IFERROR(INDEX(PBC_ACCOUNT_LIST[Cash Flow Section],MATCH(Drivers!L30,PBC_ACCOUNT_LIST[Id],0)),"") -> 0 | K30: Account | L30: 168 | P30: =SUMIFS($AI30:$BS30,$AI$4:$BS$4,">="&P$4,$AI$5:$BS$5,"<="&P$5) -> 343319 | Q30: =SUMIFS($AI30:$BS30,$AI$4:$BS$4,">="&Q$4,$AI$5:$BS$5,"<="&Q$5) -> 564775.5 | R30: =SUMIFS($AI30:$BS30,$AI$4:$BS$4,">="&R$4,$AI$5:$BS$5,"<="&R$5) -> 709437.9 | U30: =SUMIFS($AI30:$BS30,$AI$4:$BS$4,">="&U$4,$AI$5:$BS$5,"<="&U$5) -> 69834 | V30: =SUMIFS($AI30:$BS30,$AI$4:$BS$4,">="&V$4,$AI$5:$BS$5,"<="&V$5) -> 79992 | W30: =SUMIFS($AI30:$BS30,$AI$4:$BS$4,">="&W$4,$AI$5:$BS$5,"<="&W$5) -> 92790 | X30: =SUMIFS($AI30:$BS30,$AI$4:$BS$4,">="&X$4,$AI$5:$BS$5,"<="&X$5) -> 100703 | Y30: =SUMIFS($AI30:$BS30,$AI$4:$BS$4,">="&Y$4,$AI$5:$BS$5,"<="&Y$5) -> 116577.27 | Z30: =SUMIFS($AI30:$BS30,$AI$4:$BS$4,">="&Z$4,$AI$5:$BS$5,"<="&Z$5) -> 134952.96 | AA30: =SUMIFS($AI30:$BS30,$AI$4:$BS$4,">="&AA$4,$AI$5:$BS$5,"<="&AA$5) -> 156224.51 | AB30: =SUMIFS($AI30:$BS30,$AI$4:$BS$4,">="&AB$4,$AI$5:$BS$5,"<="&AB$5) -> 157020.76 | ... AF30: =SUMIFS($AI30:$BS30,$AI$4:$BS$4,">="&AF$4,$AI$5:$BS$5,"<="&AF$5) -> 188556.08 | AI30: =SUMIFS(PBC_PROFIT_AND_LOSS[AccountBalance], PBC_PROFIT_AND_LOSS[Id],$L30,PBC_PROFIT_AND_LOSS[Date],AI$5) -> 25029 | AJ30: =SUMIFS(PBC_PROFIT_AND_LOSS[AccountBalance], PBC_PROFIT_AND_LOSS[Id],$L30,PBC_PROFIT_AND_LOSS[Date],AJ$5) -> 21246 | AK30: =SUMIFS(PBC_PROFIT_AND_LOSS[AccountBalance], PBC_PROFIT_AND_LOSS[Id],$L30,PBC_PROFIT_AND_LOSS[Date],AK$5) -> 26280 | AL30: =SUMIFS(PBC_PROFIT_AND_LOSS[AccountBalance], PBC_PROFIT_AND_LOSS[Id],$L30,PBC_PROFIT_AND_LOSS[Date],AL$5) -> 22308 | AM30: =SUMIFS(PBC_PROFIT_AND_LOSS[AccountBalance], PBC_PROFIT_AND_LOSS[Id],$L30,PBC_PROFIT_AND_LOSS[Date],AM$5) -> 27594 | AN30: =SUMIFS(PBC_PROFIT_AND_LOSS[AccountBalance], PBC_PROFIT_AND_LOSS[Id],$L30,PBC_PROFIT_AND_LOSS[Date],AN$5) -> 23424 | AO30: =SUMIFS(PBC_PROFIT_AND_LOSS[AccountBalance], PBC_PROFIT_AND_LOSS[Id],$L30,PBC_PROFIT_AND_LOSS[Date],AO$5) -> 28974 | AP30: =SUMIFS(PBC_PROFIT_AND_LOSS[AccountBalance], PBC_PROFIT_AND_LOSS[Id],$L30,PBC_PROFIT_AND_LOSS[Date],AP$5) -> 30423 | ... BD30: =SUMIFS(PBC_PROFIT_AND_LOSS[AccountBalance], PBC_PROFIT_AND_LOSS[Id],$L30,PBC_PROFIT_AND_LOSS[Date],BD$5) -> 54635.22 | BE30: =AVERAGE(AY30:BD30) * (1 + $F30) -> 50956.057 | BF30: =AVERAGE(AZ30:BE30) * (1 + $F30) -> 52381.967 | BG30: =AVERAGE(BA30:BF30) * (1 + $F30) -> 53682.737 | BH30: =AVERAGE(BB30:BG30) * (1 + $F30) -> 54817.922 | BI30: =AVERAGE(BC30:BH30) * (1 + $F30) -> 55738.803 | BJ30: =AVERAGE(BD30:BI30) * (1 + $F30) -> 56387.224 | BK30: =AVERAGE(BE30:BJ30) * (1 + $F30) -> 56693.824 | BL30: =AVERAGE(BF30:BK30) * (1 + $F30) -> 57697.933 | ... BS30: =AVERAGE(BM30:BR30) * (1 + $F30) -> 63759.901
D31: 60500 Insurance | E31: Average 6 months with a buffer | F31: 0.05 | G31: =IFERROR(INDEX(PBC_ACCOUNT_LIST[Drivers Section],MATCH(Drivers!L31,PBC_ACCOUNT_LIST[Id],0)),"") -> Opex | H31: =IFERROR(INDEX(PBC_ACCOUNT_LIST[Summary Grouping],MATCH(Drivers!L31,PBC_ACCOUNT_LIST[Id],0)),"") -> Office & Other G&A | J31: =IFERROR(INDEX(PBC_ACCOUNT_LIST[Cash Flow Section],MATCH(Drivers!L31,PBC_ACCOUNT_LIST[Id],0)),"") -> 0 | K31: Account | L31: 201 | P31: =SUMIFS($AI31:$BS31,$AI$4:$BS$4,">="&P$4,$AI$5:$BS$5,"<="&P$5) -> 12408 | Q31: =SUMIFS($AI31:$BS31,$AI$4:$BS$4,">="&Q$4,$AI$5:$BS$5,"<="&Q$5) -> 21926.551 | R31: =SUMIFS($AI31:$BS31,$AI$4:$BS$4,">="&R$4,$AI$5:$BS$5,"<="&R$5) -> 27543.33 | U31: =SUMIFS($AI31:$BS31,$AI$4:$BS$4,">="&U$4,$AI$5:$BS$5,"<="&U$5) -> 2113 | V31: =SUMIFS($AI31:$BS31,$AI$4:$BS$4,">="&V$4,$AI$5:$BS$5,"<="&V$5) -> 2784 | W31: =SUMIFS($AI31:$BS31,$AI$4:$BS$4,">="&W$4,$AI$5:$BS$5,"<="&W$5) -> 3602 | X31: =SUMIFS($AI31:$BS31,$AI$4:$BS$4,">="&X$4,$AI$5:$BS$5,"<="&X$5) -> 3909 | Y31: =SUMIFS($AI31:$BS31,$AI$4:$BS$4,">="&Y$4,$AI$5:$BS$5,"<="&Y$5) -> 4525.7 | Z31: =SUMIFS($AI31:$BS31,$AI$4:$BS$4,">="&Z$4,$AI$5:$BS$5,"<="&Z$5) -> 5239.35 | AA31: =SUMIFS($AI31:$BS31,$AI$4:$BS$4,">="&AA$4,$AI$5:$BS$5,"<="&AA$5) -> 6065.32 | AB31: =SUMIFS($AI31:$BS31,$AI$4:$BS$4,">="&AB$4,$AI$5:$BS$5,"<="&AB$5) -> 6096.1805 | ... AF31: =SUMIFS($AI31:$BS31,$AI$4:$BS$4,">="&AF$4,$AI$5:$BS$5,"<="&AF$5) -> 7320.5303 | AI31: =SUMIFS(PBC_PROFIT_AND_LOSS[AccountBalance], PBC_PROFIT_AND_LOSS[Id],$L31,PBC_PROFIT_AND_LOSS[Date],AI$5) -> 972 | AJ31: =SUMIFS(PBC_PROFIT_AND_LOSS[AccountBalance], PBC_PROFIT_AND_LOSS[Id],$L31,PBC_PROFIT_AND_LOSS[Date],AJ$5) -> 533 | AK31: =SUMIFS(PBC_PROFIT_AND_LOSS[AccountBalance], PBC_PROFIT_AND_LOSS[Id],$L31,PBC_PROFIT_AND_LOSS[Date],AK$5) -> 1020 | AL31: =SUMIFS(PBC_PROFIT_AND_LOSS[AccountBalance], PBC_PROFIT_AND_LOSS[Id],$L31,PBC_PROFIT_AND_LOSS[Date],AL$5) -> 560 | AM31: =SUMIFS(PBC_PROFIT_AND_LOSS[AccountBalance], PBC_PROFIT_AND_LOSS[Id],$L31,PBC_PROFIT_AND_LOSS[Date],AM$5) -> 1071 | AN31: =SUMIFS(PBC_PROFIT_AND_LOSS[AccountBalance], PBC_PROFIT_AND_LOSS[Id],$L31,PBC_PROFIT_AND_LOSS[Date],AN$5) -> 588 | AO31: =SUMIFS(PBC_PROFIT_AND_LOSS[AccountBalance], PBC_PROFIT_AND_LOSS[Id],$L31,PBC_PROFIT_AND_LOSS[Date],AO$5) -> 1125 | AP31: =SUMIFS(PBC_PROFIT_AND_LOSS[AccountBalance], PBC_PROFIT_AND_LOSS[Id],$L31,PBC_PROFIT_AND_LOSS[Date],AP$5) -> 1181 | ... BD31: =SUMIFS(PBC_PROFIT_AND_LOSS[AccountBalance], PBC_PROFIT_AND_LOSS[Id],$L31,PBC_PROFIT_AND_LOSS[Date],BD$5) -> 2121.18 | BE31: =AVERAGE(AY31:BD31) * (1 + $F31) -> 1978.3173 | BF31: =AVERAGE(AZ31:BE31) * (1 + $F31) -> 2033.6728 | BG31: =AVERAGE(BA31:BF31) * (1 + $F31) -> 2084.1905 | BH31: =AVERAGE(BB31:BG31) * (1 + $F31) -> 2128.2626 | BI31: =AVERAGE(BC31:BH31) * (1 + $F31) -> 2164.0138 | BJ31: =AVERAGE(BD31:BI31) * (1 + $F31) -> 2189.1865 | BK31: =AVERAGE(BE31:BJ31) * (1 + $F31) -> 2201.0876 | BL31: =AVERAGE(BF31:BK31) * (1 + $F31) -> 2240.0724 | ... BS31: =AVERAGE(BM31:BR31) * (1 + $F31) -> 2475.4244
D32: 60610 Office Supplies & Software | E32: Average 6 months with a buffer | F32: 0.05 | G32: =IFERROR(INDEX(PBC_ACCOUNT_LIST[Drivers Section],MATCH(Drivers!L32,PBC_ACCOUNT_LIST[Id],0)),"") -> Opex | H32: =IFERROR(INDEX(PBC_ACCOUNT_LIST[Summary Grouping],MATCH(Drivers!L32,PBC_ACCOUNT_LIST[Id],0)),"") -> Office & Other G&A | J32: =IFERROR(INDEX(PBC_ACCOUNT_LIST[Cash Flow Section],MATCH(Drivers!L32,PBC_ACCOUNT_LIST[Id],0)),"") -> 0 | K32: Account | L32: 170 | P32: =SUMIFS($AI32:$BS32,$AI$4:$BS$4,">="&P$4,$AI$5:$BS$5,"<="&P$5) -> 29372 | Q32: =SUMIFS($AI32:$BS32,$AI$4:$BS$4,">="&Q$4,$AI$5:$BS$5,"<="&Q$5) -> 47917.526 | R32: =SUMIFS($AI32:$BS32,$AI$4:$BS$4,">="&R$4,$AI$5:$BS$5,"<="&R$5) -> 60191.371 | U32: =SUMIFS($AI32:$BS32,$AI$4:$BS$4,">="&U$4,$AI$5:$BS$5,"<="&U$5) -> 6084 | V32: =SUMIFS($AI32:$BS32,$AI$4:$BS$4,">="&V$4,$AI$5:$BS$5,"<="&V$5) -> 6872 | W32: =SUMIFS($AI32:$BS32,$AI$4:$BS$4,">="&W$4,$AI$5:$BS$5,"<="&W$5) -> 7872 | X32: =SUMIFS($AI32:$BS32,$AI$4:$BS$4,">="&X$4,$AI$5:$BS$5,"<="&X$5) -> 8544 | Y32: =SUMIFS($AI32:$BS32,$AI$4:$BS$4,">="&Y$4,$AI$5:$BS$5,"<="&Y$5) -> 9890.43 | Z32: =SUMIFS($AI32:$BS32,$AI$4:$BS$4,">="&Z$4,$AI$5:$BS$5,"<="&Z$5) -> 11450.25 | AA32: =SUMIFS($AI32:$BS32,$AI$4:$BS$4,">="&AA$4,$AI$5:$BS$5,"<="&AA$5) -> 13254.55 | AB32: =SUMIFS($AI32:$BS32,$AI$4:$BS$4,">="&AB$4,$AI$5:$BS$5,"<="&AB$5) -> 13322.296 | ... AF32: =SUMIFS($AI32:$BS32,$AI$4:$BS$4,">="&AF$4,$AI$5:$BS$5,"<="&AF$5) -> 15997.808 | AI32: =SUMIFS(PBC_PROFIT_AND_LOSS[AccountBalance], PBC_PROFIT_AND_LOSS[Id],$L32,PBC_PROFIT_AND_LOSS[Date],AI$5) -> 2123.5 | AJ32: =SUMIFS(PBC_PROFIT_AND_LOSS[AccountBalance], PBC_PROFIT_AND_LOSS[Id],$L32,PBC_PROFIT_AND_LOSS[Date],AJ$5) -> 1880 | AK32: =SUMIFS(PBC_PROFIT_AND_LOSS[AccountBalance], PBC_PROFIT_AND_LOSS[Id],$L32,PBC_PROFIT_AND_LOSS[Date],AK$5) -> 2230 | AL32: =SUMIFS(PBC_PROFIT_AND_LOSS[AccountBalance], PBC_PROFIT_AND_LOSS[Id],$L32,PBC_PROFIT_AND_LOSS[Date],AL$5) -> 1974 | AM32: =SUMIFS(PBC_PROFIT_AND_LOSS[AccountBalance], PBC_PROFIT_AND_LOSS[Id],$L32,PBC_PROFIT_AND_LOSS[Date],AM$5) -> 2341 | AN32: =SUMIFS(PBC_PROFIT_AND_LOSS[AccountBalance], PBC_PROFIT_AND_LOSS[Id],$L32,PBC_PROFIT_AND_LOSS[Date],AN$5) -> 2073 | AO32: =SUMIFS(PBC_PROFIT_AND_LOSS[AccountBalance], PBC_PROFIT_AND_LOSS[Id],$L32,PBC_PROFIT_AND_LOSS[Date],AO$5) -> 2458 | AP32: =SUMIFS(PBC_PROFIT_AND_LOSS[AccountBalance], PBC_PROFIT_AND_LOSS[Id],$L32,PBC_PROFIT_AND_LOSS[Date],AP$5) -> 2581 | ... BD32: =SUMIFS(PBC_PROFIT_AND_LOSS[AccountBalance], PBC_PROFIT_AND_LOSS[Id],$L32,PBC_PROFIT_AND_LOSS[Date],BD$5) -> 4635.41 | BE32: =AVERAGE(AY32:BD32) * (1 + $F32) -> 4323.34 | BF32: =AVERAGE(AZ32:BE32) * (1 + $F32) -> 4444.3245 | BG32: =AVERAGE(BA32:BF32) * (1 + $F32) -> 4554.6313 | BH32: =AVERAGE(BB32:BG32) * (1 + $F32) -> 4650.948 | BI32: =AVERAGE(BC32:BH32) * (1 + $F32) -> 4729.0834 | BJ32: =AVERAGE(BD32:BI32) * (1 + $F32) -> 4784.104 | BK32: =AVERAGE(BE32:BJ32) * (1 + $F32) -> 4810.1255 | BL32: =AVERAGE(BF32:BK32) * (1 + $F32) -> 4895.3129 | ... BS32: =AVERAGE(BM32:BR32) * (1 + $F32) -> 5409.6294
D33: 60620 Rent & Lease | E33: Average 6 months with a buffer | F33: 0.05 | G33: =IFERROR(INDEX(PBC_ACCOUNT_LIST[Drivers Section],MATCH(Drivers!L33,PBC_ACCOUNT_LIST[Id],0)),"") -> Opex | H33: =IFERROR(INDEX(PBC_ACCOUNT_LIST[Summary Grouping],MATCH(Drivers!L33,PBC_ACCOUNT_LIST[Id],0)),"") -> Office & Other G&A | J33: =IFERROR(INDEX(PBC_ACCOUNT_LIST[Cash Flow Section],MATCH(Drivers!L33,PBC_ACCOUNT_LIST[Id],0)),"") -> 0 | K33: Account | L33: 171 | P33: =SUMIFS($AI33:$BS33,$AI$4:$BS$4,">="&P$4,$AI$5:$BS$5,"<="&P$5) -> 143016 | Q33: =SUMIFS($AI33:$BS33,$AI$4:$BS$4,">="&Q$4,$AI$5:$BS$5,"<="&Q$5) -> 233941.21 | R33: =SUMIFS($AI33:$BS33,$AI$4:$BS$4,">="&R$4,$AI$5:$BS$5,"<="&R$5) -> 293863 | U33: =SUMIFS($AI33:$BS33,$AI$4:$BS$4,">="&U$4,$AI$5:$BS$5,"<="&U$5) -> 29451 | V33: =SUMIFS($AI33:$BS33,$AI$4:$BS$4,">="&V$4,$AI$5:$BS$5,"<="&V$5) -> 33416 | W33: =SUMIFS($AI33:$BS33,$AI$4:$BS$4,">="&W$4,$AI$5:$BS$5,"<="&W$5) -> 38436 | X33: =SUMIFS($AI33:$BS33,$AI$4:$BS$4,">="&X$4,$AI$5:$BS$5,"<="&X$5) -> 41713 | Y33: =SUMIFS($AI33:$BS33,$AI$4:$BS$4,">="&Y$4,$AI$5:$BS$5,"<="&Y$5) -> 48288.51 | Z33: =SUMIFS($AI33:$BS33,$AI$4:$BS$4,">="&Z$4,$AI$5:$BS$5,"<="&Z$5) -> 55900.45 | AA33: =SUMIFS($AI33:$BS33,$AI$4:$BS$4,">="&AA$4,$AI$5:$BS$5,"<="&AA$5) -> 64711.14 | AB33: =SUMIFS($AI33:$BS33,$AI$4:$BS$4,">="&AB$4,$AI$5:$BS$5,"<="&AB$5) -> 65041.11 | ... AF33: =SUMIFS($AI33:$BS33,$AI$4:$BS$4,">="&AF$4,$AI$5:$BS$5,"<="&AF$5) -> 78103.605 | AI33: =SUMIFS(PBC_PROFIT_AND_LOSS[AccountBalance], PBC_PROFIT_AND_LOSS[Id],$L33,PBC_PROFIT_AND_LOSS[Date],AI$5) -> 10367 | AJ33: =SUMIFS(PBC_PROFIT_AND_LOSS[AccountBalance], PBC_PROFIT_AND_LOSS[Id],$L33,PBC_PROFIT_AND_LOSS[Date],AJ$5) -> 9056 | AK33: =SUMIFS(PBC_PROFIT_AND_LOSS[AccountBalance], PBC_PROFIT_AND_LOSS[Id],$L33,PBC_PROFIT_AND_LOSS[Date],AK$5) -> 10886 | AL33: =SUMIFS(PBC_PROFIT_AND_LOSS[AccountBalance], PBC_PROFIT_AND_LOSS[Id],$L33,PBC_PROFIT_AND_LOSS[Date],AL$5) -> 9509 | AM33: =SUMIFS(PBC_PROFIT_AND_LOSS[AccountBalance], PBC_PROFIT_AND_LOSS[Id],$L33,PBC_PROFIT_AND_LOSS[Date],AM$5) -> 11430 | AN33: =SUMIFS(PBC_PROFIT_AND_LOSS[AccountBalance], PBC_PROFIT_AND_LOSS[Id],$L33,PBC_PROFIT_AND_LOSS[Date],AN$5) -> 9984 | AO33: =SUMIFS(PBC_PROFIT_AND_LOSS[AccountBalance], PBC_PROFIT_AND_LOSS[Id],$L33,PBC_PROFIT_AND_LOSS[Date],AO$5) -> 12002 | AP33: =SUMIFS(PBC_PROFIT_AND_LOSS[AccountBalance], PBC_PROFIT_AND_LOSS[Id],$L33,PBC_PROFIT_AND_LOSS[Date],AP$5) -> 12602 | ... BD33: =SUMIFS(PBC_PROFIT_AND_LOSS[AccountBalance], PBC_PROFIT_AND_LOSS[Id],$L33,PBC_PROFIT_AND_LOSS[Date],BD$5) -> 22630.94 | BE33: =AVERAGE(AY33:BD33) * (1 + $F33) -> 21107.028 | BF33: =AVERAGE(AZ33:BE33) * (1 + $F33) -> 21697.658 | BG33: =AVERAGE(BA33:BF33) * (1 + $F33) -> 22236.423 | BH33: =AVERAGE(BB33:BG33) * (1 + $F33) -> 22706.644 | BI33: =AVERAGE(BC33:BH33) * (1 + $F33) -> 23088.094 | BJ33: =AVERAGE(BD33:BI33) * (1 + $F33) -> 23356.688 | BK33: =AVERAGE(BE33:BJ33) * (1 + $F33) -> 23483.694 | BL33: =AVERAGE(BF33:BK33) * (1 + $F33) -> 23899.61 | ... BS33: =AVERAGE(BM33:BR33) * (1 + $F33) -> 26410.593
D34: 60630 Utilities | E34: Average 6 months with a buffer | F34: 0.05 | G34: =IFERROR(INDEX(PBC_ACCOUNT_LIST[Drivers Section],MATCH(Drivers!L34,PBC_ACCOUNT_LIST[Id],0)),"") -> Opex | H34: =IFERROR(INDEX(PBC_ACCOUNT_LIST[Summary Grouping],MATCH(Drivers!L34,PBC_ACCOUNT_LIST[Id],0)),"") -> Office & Other G&A | J34: =IFERROR(INDEX(PBC_ACCOUNT_LIST[Cash Flow Section],MATCH(Drivers!L34,PBC_ACCOUNT_LIST[Id],0)),"") -> 0 | K34: Account | L34: 203 | P34: =SUMIFS($AI34:$BS34,$AI$4:$BS$4,">="&P$4,$AI$5:$BS$5,"<="&P$5) -> 17607 | Q34: =SUMIFS($AI34:$BS34,$AI$4:$BS$4,">="&Q$4,$AI$5:$BS$5,"<="&Q$5) -> 30783.286 | R34: =SUMIFS($AI34:$BS34,$AI$4:$BS$4,">="&R$4,$AI$5:$BS$5,"<="&R$5) -> 38669.369 | U34: =SUMIFS($AI34:$BS34,$AI$4:$BS$4,">="&U$4,$AI$5:$BS$5,"<="&U$5) -> 3088 | V34: =SUMIFS($AI34:$BS34,$AI$4:$BS$4,">="&V$4,$AI$5:$BS$5,"<="&V$5) -> 3973 | W34: =SUMIFS($AI34:$BS34,$AI$4:$BS$4,">="&W$4,$AI$5:$BS$5,"<="&W$5) -> 5057 | X34: =SUMIFS($AI34:$BS34,$AI$4:$BS$4,">="&X$4,$AI$5:$BS$5,"<="&X$5) -> 5489 | Y34: =SUMIFS($AI34:$BS34,$AI$4:$BS$4,">="&Y$4,$AI$5:$BS$5,"<="&Y$5) -> 6353.65 | Z34: =SUMIFS($AI34:$BS34,$AI$4:$BS$4,">="&Z$4,$AI$5:$BS$5,"<="&Z$5) -> 7355.53 | AA34: =SUMIFS($AI34:$BS34,$AI$4:$BS$4,">="&AA$4,$AI$5:$BS$5,"<="&AA$5) -> 8515.41 | AB34: =SUMIFS($AI34:$BS34,$AI$4:$BS$4,">="&AB$4,$AI$5:$BS$5,"<="&AB$5) -> 8558.6963 | ... AF34: =SUMIFS($AI34:$BS34,$AI$4:$BS$4,">="&AF$4,$AI$5:$BS$5,"<="&AF$5) -> 10277.635 | AI34: =SUMIFS(PBC_PROFIT_AND_LOSS[AccountBalance], PBC_PROFIT_AND_LOSS[Id],$L34,PBC_PROFIT_AND_LOSS[Date],AI$5) -> 1364 | AJ34: =SUMIFS(PBC_PROFIT_AND_LOSS[AccountBalance], PBC_PROFIT_AND_LOSS[Id],$L34,PBC_PROFIT_AND_LOSS[Date],AJ$5) -> 808 | AK34: =SUMIFS(PBC_PROFIT_AND_LOSS[AccountBalance], PBC_PROFIT_AND_LOSS[Id],$L34,PBC_PROFIT_AND_LOSS[Date],AK$5) -> 1432 | AL34: =SUMIFS(PBC_PROFIT_AND_LOSS[AccountBalance], PBC_PROFIT_AND_LOSS[Id],$L34,PBC_PROFIT_AND_LOSS[Date],AL$5) -> 848 | AM34: =SUMIFS(PBC_PROFIT_AND_LOSS[AccountBalance], PBC_PROFIT_AND_LOSS[Id],$L34,PBC_PROFIT_AND_LOSS[Date],AM$5) -> 1504 | AN34: =SUMIFS(PBC_PROFIT_AND_LOSS[AccountBalance], PBC_PROFIT_AND_LOSS[Id],$L34,PBC_PROFIT_AND_LOSS[Date],AN$5) -> 890 | AO34: =SUMIFS(PBC_PROFIT_AND_LOSS[AccountBalance], PBC_PROFIT_AND_LOSS[Id],$L34,PBC_PROFIT_AND_LOSS[Date],AO$5) -> 1579 | AP34: =SUMIFS(PBC_PROFIT_AND_LOSS[AccountBalance], PBC_PROFIT_AND_LOSS[Id],$L34,PBC_PROFIT_AND_LOSS[Date],AP$5) -> 1658 | ... BD34: =SUMIFS(PBC_PROFIT_AND_LOSS[AccountBalance], PBC_PROFIT_AND_LOSS[Id],$L34,PBC_PROFIT_AND_LOSS[Date],BD$5) -> 2978.03 | BE34: =AVERAGE(AY34:BD34) * (1 + $F34) -> 2777.4145 | BF34: =AVERAGE(AZ34:BE34) * (1 + $F34) -> 2855.187 | BG34: =AVERAGE(BA34:BF34) * (1 + $F34) -> 2926.0948 | BH34: =AVERAGE(BB34:BG34) * (1 + $F34) -> 2987.9686 | BI34: =AVERAGE(BC34:BH34) * (1 + $F34) -> 3038.1601 | BJ34: =AVERAGE(BD34:BI34) * (1 + $F34) -> 3073.4996 | BK34: =AVERAGE(BE34:BJ34) * (1 + $F34) -> 3090.2068 | BL34: =AVERAGE(BF34:BK34) * (1 + $F34) -> 3144.9455 | ... BS34: =AVERAGE(BM34:BR34) * (1 + $F34) -> 3475.3642
D35: 60700 Professional Services | E35: Average 6 months with a buffer | F35: 0.05 | G35: =IFERROR(INDEX(PBC_ACCOUNT_LIST[Drivers Section],MATCH(Drivers!L35,PBC_ACCOUNT_LIST[Id],0)),"") -> Opex | H35: =IFERROR(INDEX(PBC_ACCOUNT_LIST[Summary Grouping],MATCH(Drivers!L35,PBC_ACCOUNT_LIST[Id],0)),"") -> Professional Services | J35: =IFERROR(INDEX(PBC_ACCOUNT_LIST[Cash Flow Section],MATCH(Drivers!L35,PBC_ACCOUNT_LIST[Id],0)),"") -> 0 | K35: Account | L35: 172 | P35: =SUMIFS($AI35:$BS35,$AI$4:$BS$4,">="&P$4,$AI$5:$BS$5,"<="&P$5) -> 0 | Q35: =SUMIFS($AI35:$BS35,$AI$4:$BS$4,">="&Q$4,$AI$5:$BS$5,"<="&Q$5) -> 0 | R35: =SUMIFS($AI35:$BS35,$AI$4:$BS$4,">="&R$4,$AI$5:$BS$5,"<="&R$5) -> 0 | U35: =SUMIFS($AI35:$BS35,$AI$4:$BS$4,">="&U$4,$AI$5:$BS$5,"<="&U$5) -> 0 | V35: =SUMIFS($AI35:$BS35,$AI$4:$BS$4,">="&V$4,$AI$5:$BS$5,"<="&V$5) -> 0 | W35: =SUMIFS($AI35:$BS35,$AI$4:$BS$4,">="&W$4,$AI$5:$BS$5,"<="&W$5) -> 0 | X35: =SUMIFS($AI35:$BS35,$AI$4:$BS$4,">="&X$4,$AI$5:$BS$5,"<="&X$5) -> 0 | Y35: =SUMIFS($AI35:$BS35,$AI$4:$BS$4,">="&Y$4,$AI$5:$BS$5,"<="&Y$5) -> 0 | Z35: =SUMIFS($AI35:$BS35,$AI$4:$BS$4,">="&Z$4,$AI$5:$BS$5,"<="&Z$5) -> 0 | AA35: =SUMIFS($AI35:$BS35,$AI$4:$BS$4,">="&AA$4,$AI$5:$BS$5,"<="&AA$5) -> 0 | AB35: =SUMIFS($AI35:$BS35,$AI$4:$BS$4,">="&AB$4,$AI$5:$BS$5,"<="&AB$5) -> 0 | ... AF35: =SUMIFS($AI35:$BS35,$AI$4:$BS$4,">="&AF$4,$AI$5:$BS$5,"<="&AF$5) -> 0 | AI35: =SUMIFS(PBC_PROFIT_AND_LOSS[AccountBalance], PBC_PROFIT_AND_LOSS[Id],$L35,PBC_PROFIT_AND_LOSS[Date],AI$5) -> 0 | AJ35: =SUMIFS(PBC_PROFIT_AND_LOSS[AccountBalance], PBC_PROFIT_AND_LOSS[Id],$L35,PBC_PROFIT_AND_LOSS[Date],AJ$5) -> 0 | AK35: =SUMIFS(PBC_PROFIT_AND_LOSS[AccountBalance], PBC_PROFIT_AND_LOSS[Id],$L35,PBC_PROFIT_AND_LOSS[Date],AK$5) -> 0 | AL35: =SUMIFS(PBC_PROFIT_AND_LOSS[AccountBalance], PBC_PROFIT_AND_LOSS[Id],$L35,PBC_PROFIT_AND_LOSS[Date],AL$5) -> 0 | AM35: =SUMIFS(PBC_PROFIT_AND_LOSS[AccountBalance], PBC_PROFIT_AND_LOSS[Id],$L35,PBC_PROFIT_AND_LOSS[Date],AM$5) -> 0 | AN35: =SUMIFS(PBC_PROFIT_AND_LOSS[AccountBalance], PBC_PROFIT_AND_LOSS[Id],$L35,PBC_PROFIT_AND_LOSS[Date],AN$5) -> 0 | AO35: =SUMIFS(PBC_PROFIT_AND_LOSS[AccountBalance], PBC_PROFIT_AND_LOSS[Id],$L35,PBC_PROFIT_AND_LOSS[Date],AO$5) -> 0 | AP35: =SUMIFS(PBC_PROFIT_AND_LOSS[AccountBalance], PBC_PROFIT_AND_LOSS[Id],$L35,PBC_PROFIT_AND_LOSS[Date],AP$5) -> 0 | ... BD35: =SUMIFS(PBC_PROFIT_AND_LOSS[AccountBalance], PBC_PROFIT_AND_LOSS[Id],$L35,PBC_PROFIT_AND_LOSS[Date],BD$5) -> 0 | BE35: =AVERAGE(AY35:BD35) * (1 + $F35) -> 0 | BF35: =AVERAGE(AZ35:BE35) * (1 + $F35) -> 0 | BG35: =AVERAGE(BA35:BF35) * (1 + $F35) -> 0 | BH35: =AVERAGE(BB35:BG35) * (1 + $F35) -> 0 | BI35: =AVERAGE(BC35:BH35) * (1 + $F35) -> 0 | BJ35: =AVERAGE(BD35:BI35) * (1 + $F35) -> 0 | BK35: =AVERAGE(BE35:BJ35) * (1 + $F35) -> 0 | BL35: =AVERAGE(BF35:BK35) * (1 + $F35) -> 0 | ... BS35: =AVERAGE(BM35:BR35) * (1 + $F35) -> 0
D36: 60710 Accounting Fees | E36: Average 6 months with a buffer | F36: 0.05 | G36: =IFERROR(INDEX(PBC_ACCOUNT_LIST[Drivers Section],MATCH(Drivers!L36,PBC_ACCOUNT_LIST[Id],0)),"") -> Opex | H36: =IFERROR(INDEX(PBC_ACCOUNT_LIST[Summary Grouping],MATCH(Drivers!L36,PBC_ACCOUNT_LIST[Id],0)),"") -> Professional Services | J36: =IFERROR(INDEX(PBC_ACCOUNT_LIST[Cash Flow Section],MATCH(Drivers!L36,PBC_ACCOUNT_LIST[Id],0)),"") -> 0 | K36: Account | L36: 173 | P36: =SUMIFS($AI36:$BS36,$AI$4:$BS$4,">="&P$4,$AI$5:$BS$5,"<="&P$5) -> 38365 | Q36: =SUMIFS($AI36:$BS36,$AI$4:$BS$4,">="&Q$4,$AI$5:$BS$5,"<="&Q$5) -> 63405.696 | R36: =SUMIFS($AI36:$BS36,$AI$4:$BS$4,">="&R$4,$AI$5:$BS$5,"<="&R$5) -> 79647.14 | U36: =SUMIFS($AI36:$BS36,$AI$4:$BS$4,">="&U$4,$AI$5:$BS$5,"<="&U$5) -> 7723 | V36: =SUMIFS($AI36:$BS36,$AI$4:$BS$4,">="&V$4,$AI$5:$BS$5,"<="&V$5) -> 8918 | W36: =SUMIFS($AI36:$BS36,$AI$4:$BS$4,">="&W$4,$AI$5:$BS$5,"<="&W$5) -> 10418 | X36: =SUMIFS($AI36:$BS36,$AI$4:$BS$4,">="&X$4,$AI$5:$BS$5,"<="&X$5) -> 11306 | Y36: =SUMIFS($AI36:$BS36,$AI$4:$BS$4,">="&Y$4,$AI$5:$BS$5,"<="&Y$5) -> 13087.61 | Z36: =SUMIFS($AI36:$BS36,$AI$4:$BS$4,">="&Z$4,$AI$5:$BS$5,"<="&Z$5) -> 15150.63 | AA36: =SUMIFS($AI36:$BS36,$AI$4:$BS$4,">="&AA$4,$AI$5:$BS$5,"<="&AA$5) -> 17539.11 | AB36: =SUMIFS($AI36:$BS36,$AI$4:$BS$4,">="&AB$4,$AI$5:$BS$5,"<="&AB$5) -> 17628.346 | ... AF36: =SUMIFS($AI36:$BS36,$AI$4:$BS$4,">="&AF$4,$AI$5:$BS$5,"<="&AF$5) -> 21168.803 | AI36: =SUMIFS(PBC_PROFIT_AND_LOSS[AccountBalance], PBC_PROFIT_AND_LOSS[Id],$L36,PBC_PROFIT_AND_LOSS[Date],AI$5) -> 2810 | AJ36: =SUMIFS(PBC_PROFIT_AND_LOSS[AccountBalance], PBC_PROFIT_AND_LOSS[Id],$L36,PBC_PROFIT_AND_LOSS[Date],AJ$5) -> 2328 | AK36: =SUMIFS(PBC_PROFIT_AND_LOSS[AccountBalance], PBC_PROFIT_AND_LOSS[Id],$L36,PBC_PROFIT_AND_LOSS[Date],AK$5) -> 2950 | AL36: =SUMIFS(PBC_PROFIT_AND_LOSS[AccountBalance], PBC_PROFIT_AND_LOSS[Id],$L36,PBC_PROFIT_AND_LOSS[Date],AL$5) -> 2445 | AM36: =SUMIFS(PBC_PROFIT_AND_LOSS[AccountBalance], PBC_PROFIT_AND_LOSS[Id],$L36,PBC_PROFIT_AND_LOSS[Date],AM$5) -> 3098 | AN36: =SUMIFS(PBC_PROFIT_AND_LOSS[AccountBalance], PBC_PROFIT_AND_LOSS[Id],$L36,PBC_PROFIT_AND_LOSS[Date],AN$5) -> 2567 | AO36: =SUMIFS(PBC_PROFIT_AND_LOSS[AccountBalance], PBC_PROFIT_AND_LOSS[Id],$L36,PBC_PROFIT_AND_LOSS[Date],AO$5) -> 3253 | AP36: =SUMIFS(PBC_PROFIT_AND_LOSS[AccountBalance], PBC_PROFIT_AND_LOSS[Id],$L36,PBC_PROFIT_AND_LOSS[Date],AP$5) -> 3416 | ... BD36: =SUMIFS(PBC_PROFIT_AND_LOSS[AccountBalance], PBC_PROFIT_AND_LOSS[Id],$L36,PBC_PROFIT_AND_LOSS[Date],BD$5) -> 6133.82 | BE36: =AVERAGE(AY36:BD36) * (1 + $F36) -> 5720.7045 | BF36: =AVERAGE(AZ36:BE36) * (1 + $F36) -> 5880.7778 | BG36: =AVERAGE(BA36:BF36) * (1 + $F36) -> 6026.8639 | BH36: =AVERAGE(BB36:BG36) * (1 + $F36) -> 6154.3048 | BI36: =AVERAGE(BC36:BH36) * (1 + $F36) -> 6257.6852 | BJ36: =AVERAGE(BD36:BI36) * (1 + $F36) -> 6330.4773 | BK36: =AVERAGE(BE36:BJ36) * (1 + $F36) -> 6364.8924 | BL36: =AVERAGE(BF36:BK36) * (1 + $F36) -> 6477.6252 | ... BS36: =AVERAGE(BM36:BR36) * (1 + $F36) -> 7158.1933
D37: 60730 Legal Fees | E37: Average 6 months with a buffer | F37: 0.05 | G37: =IFERROR(INDEX(PBC_ACCOUNT_LIST[Drivers Section],MATCH(Drivers!L37,PBC_ACCOUNT_LIST[Id],0)),"") -> Opex | H37: =IFERROR(INDEX(PBC_ACCOUNT_LIST[Summary Grouping],MATCH(Drivers!L37,PBC_ACCOUNT_LIST[Id],0)),"") -> Professional Services | J37: =IFERROR(INDEX(PBC_ACCOUNT_LIST[Cash Flow Section],MATCH(Drivers!L37,PBC_ACCOUNT_LIST[Id],0)),"") -> 0 | K37: Account | L37: 175 | P37: =SUMIFS($AI37:$BS37,$AI$4:$BS$4,">="&P$4,$AI$5:$BS$5,"<="&P$5) -> 60342 | Q37: =SUMIFS($AI37:$BS37,$AI$4:$BS$4,">="&Q$4,$AI$5:$BS$5,"<="&Q$5) -> 107235.68 | R37: =SUMIFS($AI37:$BS37,$AI$4:$BS$4,">="&R$4,$AI$5:$BS$5,"<="&R$5) -> 134703.75 | U37: =SUMIFS($AI37:$BS37,$AI$4:$BS$4,">="&U$4,$AI$5:$BS$5,"<="&U$5) -> 10109 | V37: =SUMIFS($AI37:$BS37,$AI$4:$BS$4,">="&V$4,$AI$5:$BS$5,"<="&V$5) -> 13493 | W37: =SUMIFS($AI37:$BS37,$AI$4:$BS$4,">="&W$4,$AI$5:$BS$5,"<="&W$5) -> 17619 | X37: =SUMIFS($AI37:$BS37,$AI$4:$BS$4,">="&X$4,$AI$5:$BS$5,"<="&X$5) -> 19121 | Y37: =SUMIFS($AI37:$BS37,$AI$4:$BS$4,">="&Y$4,$AI$5:$BS$5,"<="&Y$5) -> 22134.37 | Z37: =SUMIFS($AI37:$BS37,$AI$4:$BS$4,">="&Z$4,$AI$5:$BS$5,"<="&Z$5) -> 25624.25 | AA37: =SUMIFS($AI37:$BS37,$AI$4:$BS$4,">="&AA$4,$AI$5:$BS$5,"<="&AA$5) -> 29662.86 | AB37: =SUMIFS($AI37:$BS37,$AI$4:$BS$4,">="&AB$4,$AI$5:$BS$5,"<="&AB$5) -> 29814.195 | ... AF37: =SUMIFS($AI37:$BS37,$AI$4:$BS$4,">="&AF$4,$AI$5:$BS$5,"<="&AF$5) -> 35801.884 | AI37: =SUMIFS(PBC_PROFIT_AND_LOSS[AccountBalance], PBC_PROFIT_AND_LOSS[Id],$L37,PBC_PROFIT_AND_LOSS[Date],AI$5) -> 4752 | AJ37: =SUMIFS(PBC_PROFIT_AND_LOSS[AccountBalance], PBC_PROFIT_AND_LOSS[Id],$L37,PBC_PROFIT_AND_LOSS[Date],AJ$5) -> 2497 | AK37: =SUMIFS(PBC_PROFIT_AND_LOSS[AccountBalance], PBC_PROFIT_AND_LOSS[Id],$L37,PBC_PROFIT_AND_LOSS[Date],AK$5) -> 4990 | AL37: =SUMIFS(PBC_PROFIT_AND_LOSS[AccountBalance], PBC_PROFIT_AND_LOSS[Id],$L37,PBC_PROFIT_AND_LOSS[Date],AL$5) -> 2622 | AM37: =SUMIFS(PBC_PROFIT_AND_LOSS[AccountBalance], PBC_PROFIT_AND_LOSS[Id],$L37,PBC_PROFIT_AND_LOSS[Date],AM$5) -> 5239 | AN37: =SUMIFS(PBC_PROFIT_AND_LOSS[AccountBalance], PBC_PROFIT_AND_LOSS[Id],$L37,PBC_PROFIT_AND_LOSS[Date],AN$5) -> 2753 | AO37: =SUMIFS(PBC_PROFIT_AND_LOSS[AccountBalance], PBC_PROFIT_AND_LOSS[Id],$L37,PBC_PROFIT_AND_LOSS[Date],AO$5) -> 5501 | AP37: =SUMIFS(PBC_PROFIT_AND_LOSS[AccountBalance], PBC_PROFIT_AND_LOSS[Id],$L37,PBC_PROFIT_AND_LOSS[Date],AP$5) -> 5777 | ... BD37: =SUMIFS(PBC_PROFIT_AND_LOSS[AccountBalance], PBC_PROFIT_AND_LOSS[Id],$L37,PBC_PROFIT_AND_LOSS[Date],BD$5) -> 10373.77 | BE37: =AVERAGE(AY37:BD37) * (1 + $F37) -> 9675.2442 | BF37: =AVERAGE(AZ37:BE37) * (1 + $F37) -> 9946.012 | BG37: =AVERAGE(BA37:BF37) * (1 + $F37) -> 10192.939 | BH37: =AVERAGE(BB37:BG37) * (1 + $F37) -> 10408.485 | BI37: =AVERAGE(BC37:BH37) * (1 + $F37) -> 10583.34 | BJ37: =AVERAGE(BD37:BI37) * (1 + $F37) -> 10706.463 | BK37: =AVERAGE(BE37:BJ37) * (1 + $F37) -> 10764.685 | BL37: =AVERAGE(BF37:BK37) * (1 + $F37) -> 10955.337 | ... BS37: =AVERAGE(BM37:BR37) * (1 + $F37) -> 12106.342
D38: 60740 Recruiting Fees | E38: Average 6 months with a buffer | F38: 0.05 | G38: =IFERROR(INDEX(PBC_ACCOUNT_LIST[Drivers Section],MATCH(Drivers!L38,PBC_ACCOUNT_LIST[Id],0)),"") -> Opex | H38: =IFERROR(INDEX(PBC_ACCOUNT_LIST[Summary Grouping],MATCH(Drivers!L38,PBC_ACCOUNT_LIST[Id],0)),"") -> Professional Services | J38: =IFERROR(INDEX(PBC_ACCOUNT_LIST[Cash Flow Section],MATCH(Drivers!L38,PBC_ACCOUNT_LIST[Id],0)),"") -> 0 | K38: Account | L38: 176 | P38: =SUMIFS($AI38:$BS38,$AI$4:$BS$4,">="&P$4,$AI$5:$BS$5,"<="&P$5) -> 75708 | Q38: =SUMIFS($AI38:$BS38,$AI$4:$BS$4,">="&Q$4,$AI$5:$BS$5,"<="&Q$5) -> 133189.61 | R38: =SUMIFS($AI38:$BS38,$AI$4:$BS$4,">="&R$4,$AI$5:$BS$5,"<="&R$5) -> 167304.62 | U38: =SUMIFS($AI38:$BS38,$AI$4:$BS$4,">="&U$4,$AI$5:$BS$5,"<="&U$5) -> 13051 | V38: =SUMIFS($AI38:$BS38,$AI$4:$BS$4,">="&V$4,$AI$5:$BS$5,"<="&V$5) -> 17026 | W38: =SUMIFS($AI38:$BS38,$AI$4:$BS$4,">="&W$4,$AI$5:$BS$5,"<="&W$5) -> 21883 | X38: =SUMIFS($AI38:$BS38,$AI$4:$BS$4,">="&X$4,$AI$5:$BS$5,"<="&X$5) -> 23748 | Y38: =SUMIFS($AI38:$BS38,$AI$4:$BS$4,">="&Y$4,$AI$5:$BS$5,"<="&Y$5) -> 27492.74 | Z38: =SUMIFS($AI38:$BS38,$AI$4:$BS$4,">="&Z$4,$AI$5:$BS$5,"<="&Z$5) -> 31825.12 | AA38: =SUMIFS($AI38:$BS38,$AI$4:$BS$4,">="&AA$4,$AI$5:$BS$5,"<="&AA$5) -> 36842.07 | AB38: =SUMIFS($AI38:$BS38,$AI$4:$BS$4,">="&AB$4,$AI$5:$BS$5,"<="&AB$5) -> 37029.677 | ... AF38: =SUMIFS($AI38:$BS38,$AI$4:$BS$4,">="&AF$4,$AI$5:$BS$5,"<="&AF$5) -> 44466.617 | AI38: =SUMIFS(PBC_PROFIT_AND_LOSS[AccountBalance], PBC_PROFIT_AND_LOSS[Id],$L38,PBC_PROFIT_AND_LOSS[Date],AI$5) -> 5903 | AJ38: =SUMIFS(PBC_PROFIT_AND_LOSS[AccountBalance], PBC_PROFIT_AND_LOSS[Id],$L38,PBC_PROFIT_AND_LOSS[Date],AJ$5) -> 3343 | AK38: =SUMIFS(PBC_PROFIT_AND_LOSS[AccountBalance], PBC_PROFIT_AND_LOSS[Id],$L38,PBC_PROFIT_AND_LOSS[Date],AK$5) -> 6198 | AL38: =SUMIFS(PBC_PROFIT_AND_LOSS[AccountBalance], PBC_PROFIT_AND_LOSS[Id],$L38,PBC_PROFIT_AND_LOSS[Date],AL$5) -> 3510 | AM38: =SUMIFS(PBC_PROFIT_AND_LOSS[AccountBalance], PBC_PROFIT_AND_LOSS[Id],$L38,PBC_PROFIT_AND_LOSS[Date],AM$5) -> 6508 | AN38: =SUMIFS(PBC_PROFIT_AND_LOSS[AccountBalance], PBC_PROFIT_AND_LOSS[Id],$L38,PBC_PROFIT_AND_LOSS[Date],AN$5) -> 3685 | AO38: =SUMIFS(PBC_PROFIT_AND_LOSS[AccountBalance], PBC_PROFIT_AND_LOSS[Id],$L38,PBC_PROFIT_AND_LOSS[Date],AO$5) -> 6833 | AP38: =SUMIFS(PBC_PROFIT_AND_LOSS[AccountBalance], PBC_PROFIT_AND_LOSS[Id],$L38,PBC_PROFIT_AND_LOSS[Date],AP$5) -> 7175 | ... BD38: =SUMIFS(PBC_PROFIT_AND_LOSS[AccountBalance], PBC_PROFIT_AND_LOSS[Id],$L38,PBC_PROFIT_AND_LOSS[Date],BD$5) -> 12884.5 | BE38: =AVERAGE(AY38:BD38) * (1 + $F38) -> 12016.758 | BF38: =AVERAGE(AZ38:BE38) * (1 + $F38) -> 12353.066 | BG38: =AVERAGE(BA38:BF38) * (1 + $F38) -> 12659.852 | BH38: =AVERAGE(BB38:BG38) * (1 + $F38) -> 12927.556 | BI38: =AVERAGE(BC38:BH38) * (1 + $F38) -> 13144.719 | BJ38: =AVERAGE(BD38:BI38) * (1 + $F38) -> 13297.629 | BK38: =AVERAGE(BE38:BJ38) * (1 + $F38) -> 13369.927 | BL38: =AVERAGE(BF38:BK38) * (1 + $F38) -> 13606.731 | ... BS38: =AVERAGE(BM38:BR38) * (1 + $F38) -> 15036.307
... D49: Purchases | E49: Average 6 months with a buffer | F49: 0.05 | G49: =IFERROR(INDEX(PBC_ACCOUNT_LIST[Drivers Section],MATCH(Drivers!L49,PBC_ACCOUNT_LIST[Id],0)),"") -> Opex | H49: =IFERROR(INDEX(PBC_ACCOUNT_LIST[Summary Grouping],MATCH(Drivers!L49,PBC_ACCOUNT_LIST[Id],0)),"") -> Office & Other G&A | J49: =IFERROR(INDEX(PBC_ACCOUNT_LIST[Cash Flow Section],MATCH(Drivers!L49,PBC_ACCOUNT_LIST[Id],0)),"") -> 0 | K49: Account | L49: 206 | P49: =SUMIFS($AI49:$BS49,$AI$4:$BS$4,">="&P$4,$AI$5:$BS$5,"<="&P$5) -> 0 | Q49: =SUMIFS($AI49:$BS49,$AI$4:$BS$4,">="&Q$4,$AI$5:$BS$5,"<="&Q$5) -> 1622.2344 | R49: =SUMIFS($AI49:$BS49,$AI$4:$BS$4,">="&R$4,$AI$5:$BS$5,"<="&R$5) -> 1959.1538 | U49: =SUMIFS($AI49:$BS49,$AI$4:$BS$4,">="&U$4,$AI$5:$BS$5,"<="&U$5) -> 0 | V49: =SUMIFS($AI49:$BS49,$AI$4:$BS$4,">="&V$4,$AI$5:$BS$5,"<="&V$5) -> 0 | W49: =SUMIFS($AI49:$BS49,$AI$4:$BS$4,">="&W$4,$AI$5:$BS$5,"<="&W$5) -> 0 | X49: =SUMIFS($AI49:$BS49,$AI$4:$BS$4,">="&X$4,$AI$5:$BS$5,"<="&X$5) -> 0 | Y49: =SUMIFS($AI49:$BS49,$AI$4:$BS$4,">="&Y$4,$AI$5:$BS$5,"<="&Y$5) -> 0 | Z49: =SUMIFS($AI49:$BS49,$AI$4:$BS$4,">="&Z$4,$AI$5:$BS$5,"<="&Z$5) -> 1000 | AA49: =SUMIFS($AI49:$BS49,$AI$4:$BS$4,">="&AA$4,$AI$5:$BS$5,"<="&AA$5) -> 0 | AB49: =SUMIFS($AI49:$BS49,$AI$4:$BS$4,">="&AB$4,$AI$5:$BS$5,"<="&AB$5) -> 622.23438 | ... AF49: =SUMIFS($AI49:$BS49,$AI$4:$BS$4,">="&AF$4,$AI$5:$BS$5,"<="&AF$5) -> 542.42414 | AI49: =SUMIFS(PBC_PROFIT_AND_LOSS[AccountBalance], PBC_PROFIT_AND_LOSS[Id],$L49,PBC_PROFIT_AND_LOSS[Date],AI$5) -> 0 | AJ49: =SUMIFS(PBC_PROFIT_AND_LOSS[AccountBalance], PBC_PROFIT_AND_LOSS[Id],$L49,PBC_PROFIT_AND_LOSS[Date],AJ$5) -> 0 | AK49: =SUMIFS(PBC_PROFIT_AND_LOSS[AccountBalance], PBC_PROFIT_AND_LOSS[Id],$L49,PBC_PROFIT_AND_LOSS[Date],AK$5) -> 0 | AL49: =SUMIFS(PBC_PROFIT_AND_LOSS[AccountBalance], PBC_PROFIT_AND_LOSS[Id],$L49,PBC_PROFIT_AND_LOSS[Date],AL$5) -> 0 | AM49: =SUMIFS(PBC_PROFIT_AND_LOSS[AccountBalance], PBC_PROFIT_AND_LOSS[Id],$L49,PBC_PROFIT_AND_LOSS[Date],AM$5) -> 0 | AN49: =SUMIFS(PBC_PROFIT_AND_LOSS[AccountBalance], PBC_PROFIT_AND_LOSS[Id],$L49,PBC_PROFIT_AND_LOSS[Date],AN$5) -> 0 | AO49: =SUMIFS(PBC_PROFIT_AND_LOSS[AccountBalance], PBC_PROFIT_AND_LOSS[Id],$L49,PBC_PROFIT_AND_LOSS[Date],AO$5) -> 0 | AP49: =SUMIFS(PBC_PROFIT_AND_LOSS[AccountBalance], PBC_PROFIT_AND_LOSS[Id],$L49,PBC_PROFIT_AND_LOSS[Date],AP$5) -> 0 | ... BD49: =SUMIFS(PBC_PROFIT_AND_LOSS[AccountBalance], PBC_PROFIT_AND_LOSS[Id],$L49,PBC_PROFIT_AND_LOSS[Date],BD$5) -> 0 | BE49: =AVERAGE(AY49:BD49) * (1 + $F49) -> 175 | BF49: =AVERAGE(AZ49:BE49) * (1 + $F49) -> 205.625 | BG49: =AVERAGE(BA49:BF49) * (1 + $F49) -> 241.60938 | BH49: =AVERAGE(BB49:BG49) * (1 + $F49) -> 108.89102 | BI49: =AVERAGE(BC49:BH49) * (1 + $F49) -> 127.94694 | BJ49: =AVERAGE(BD49:BI49) * (1 + $F49) -> 150.33766 | BK49: =AVERAGE(BE49:BJ49) * (1 + $F49) -> 176.64675 | BL49: =AVERAGE(BF49:BK49) * (1 + $F49) -> 176.93493 | ... BS49: =AVERAGE(BM49:BR49) * (1 + $F49) -> 181.46331
C51: Net Operating Income | P51: =P22-P25 -> -1295531 | Q51: =Q22-Q25 -> -2303548.4 | R51: =R22-R25 -> -2893504 | U51: =U22-U25 -> -213006.5 | V51: =V22-V25 -> -288657 | W51: =W22-W25 -> -380699 | X51: =X22-X25 -> -413168.5 | Y51: =Y22-Y25 -> -478295.49 | Z51: =Z22-Z25 -> -546288.79 | AA51: =AA22-AA25 -> -639961.99 | AB51: =AB22-AB25 -> -639002.17 | ... AF51: =AF22-AF25 -> -768880.77 | AI51: =AI22-AI25 -> -102689.5 | AJ51: =AJ22-AJ25 -> -51309 | AK51: =AK22-AK25 -> -107824 | AL51: =AL22-AL25 -> -53873.5 | AM51: =AM22-AM25 -> -113214.5 | AN51: =AN22-AN25 -> -56566.5 | AO51: =AO22-AO25 -> -118876 | AP51: =AP22-AP25 -> -124820 | ... BS51: =BS22-BS25 -> -260011.04
C53: Other Income | P53: =SUM(P54:P57) -> 0 | Q53: =SUM(Q54:Q57) -> 0 | R53: =SUM(R54:R57) -> 0 | U53: =SUM(U54:U57) -> 0 | V53: =SUM(V54:V57) -> 0 | W53: =SUM(W54:W57) -> 0 | X53: =SUM(X54:X57) -> 0 | Y53: =SUM(Y54:Y57) -> 0 | Z53: =SUM(Z54:Z57) -> 0 | AA53: =SUM(AA54:AA57) -> 0 | AB53: =SUM(AB54:AB57) -> 0 | ... AF53: =SUM(AF54:AF57) -> 0 | AI53: =IF(AI$5<=LatestMonthOfActuals,SUMIFS(AI54:AI57,$K54:$K57,"Account"),SUMIFS(AI54:AI57,$K54:$K57,"<>Sub-Account")) -> 0 | AJ53: =IF(AJ$5<=LatestMonthOfActuals,SUMIFS(AJ54:AJ57,$K54:$K57,"Account"),SUMIFS(AJ54:AJ57,$K54:$K57,"<>Sub-Account")) -> 0 | AK53: =IF(AK$5<=LatestMonthOfActuals,SUMIFS(AK54:AK57,$K54:$K57,"Account"),SUMIFS(AK54:AK57,$K54:$K57,"<>Sub-Account")) -> 0 | AL53: =IF(AL$5<=LatestMonthOfActuals,SUMIFS(AL54:AL57,$K54:$K57,"Account"),SUMIFS(AL54:AL57,$K54:$K57,"<>Sub-Account")) -> 0 | AM53: =IF(AM$5<=LatestMonthOfActuals,SUMIFS(AM54:AM57,$K54:$K57,"Account"),SUMIFS(AM54:AM57,$K54:$K57,"<>Sub-Account")) -> 0 | AN53: =IF(AN$5<=LatestMonthOfActuals,SUMIFS(AN54:AN57,$K54:$K57,"Account"),SUMIFS(AN54:AN57,$K54:$K57,"<>Sub-Account")) -> 0 | AO53: =IF(AO$5<=LatestMonthOfActuals,SUMIFS(AO54:AO57,$K54:$K57,"Account"),SUMIFS(AO54:AO57,$K54:$K57,"<>Sub-Account")) -> 0 | AP53: =IF(AP$5<=LatestMonthOfActuals,SUMIFS(AP54:AP57,$K54:$K57,"Account"),SUMIFS(AP54:AP57,$K54:$K57,"<>Sub-Account")) -> 0 | ... BS53: =IF(BS$5<=LatestMonthOfActuals,SUMIFS(BS54:BS57,$K54:$K57,"Account"),SUMIFS(BS54:BS57,$K54:$K57,"<>Sub-Account")) -> 0
D55: 80100 Interest Income | E55: Average 6 months with a buffer | F55: 0.05 | G55: =IFERROR(INDEX(PBC_ACCOUNT_LIST[Drivers Section],MATCH(Drivers!L55,PBC_ACCOUNT_LIST[Id],0)),"") -> Other Income | H55: =IFERROR(INDEX(PBC_ACCOUNT_LIST[Summary Grouping],MATCH(Drivers!L55,PBC_ACCOUNT_LIST[Id],0)),"") -> Other Income | J55: =IFERROR(INDEX(PBC_ACCOUNT_LIST[Cash Flow Section],MATCH(Drivers!L55,PBC_ACCOUNT_LIST[Id],0)),"") -> 0 | K55: Account | L55: 189 | P55: =SUMIFS($AI55:$BS55,$AI$4:$BS$4,">="&P$4,$AI$5:$BS$5,"<="&P$5) -> 0 | Q55: =SUMIFS($AI55:$BS55,$AI$4:$BS$4,">="&Q$4,$AI$5:$BS$5,"<="&Q$5) -> 0 | R55: =SUMIFS($AI55:$BS55,$AI$4:$BS$4,">="&R$4,$AI$5:$BS$5,"<="&R$5) -> 0 | U55: =SUMIFS($AI55:$BS55,$AI$4:$BS$4,">="&U$4,$AI$5:$BS$5,"<="&U$5) -> 0 | V55: =SUMIFS($AI55:$BS55,$AI$4:$BS$4,">="&V$4,$AI$5:$BS$5,"<="&V$5) -> 0 | W55: =SUMIFS($AI55:$BS55,$AI$4:$BS$4,">="&W$4,$AI$5:$BS$5,"<="&W$5) -> 0 | X55: =SUMIFS($AI55:$BS55,$AI$4:$BS$4,">="&X$4,$AI$5:$BS$5,"<="&X$5) -> 0 | Y55: =SUMIFS($AI55:$BS55,$AI$4:$BS$4,">="&Y$4,$AI$5:$BS$5,"<="&Y$5) -> 0 | Z55: =SUMIFS($AI55:$BS55,$AI$4:$BS$4,">="&Z$4,$AI$5:$BS$5,"<="&Z$5) -> 0 | AA55: =SUMIFS($AI55:$BS55,$AI$4:$BS$4,">="&AA$4,$AI$5:$BS$5,"<="&AA$5) -> 0 | AB55: =SUMIFS($AI55:$BS55,$AI$4:$BS$4,">="&AB$4,$AI$5:$BS$5,"<="&AB$5) -> 0 | ... AF55: =SUMIFS($AI55:$BS55,$AI$4:$BS$4,">="&AF$4,$AI$5:$BS$5,"<="&AF$5) -> 0 | AI55: =SUMIFS(PBC_PROFIT_AND_LOSS[AccountBalance], PBC_PROFIT_AND_LOSS[Id],$L55,PBC_PROFIT_AND_LOSS[Date],AI$5) -> 0 | AJ55: =SUMIFS(PBC_PROFIT_AND_LOSS[AccountBalance], PBC_PROFIT_AND_LOSS[Id],$L55,PBC_PROFIT_AND_LOSS[Date],AJ$5) -> 0 | AK55: =SUMIFS(PBC_PROFIT_AND_LOSS[AccountBalance], PBC_PROFIT_AND_LOSS[Id],$L55,PBC_PROFIT_AND_LOSS[Date],AK$5) -> 0 | AL55: =SUMIFS(PBC_PROFIT_AND_LOSS[AccountBalance], PBC_PROFIT_AND_LOSS[Id],$L55,PBC_PROFIT_AND_LOSS[Date],AL$5) -> 0 | AM55: =SUMIFS(PBC_PROFIT_AND_LOSS[AccountBalance], PBC_PROFIT_AND_LOSS[Id],$L55,PBC_PROFIT_AND_LOSS[Date],AM$5) -> 0 | AN55: =SUMIFS(PBC_PROFIT_AND_LOSS[AccountBalance], PBC_PROFIT_AND_LOSS[Id],$L55,PBC_PROFIT_AND_LOSS[Date],AN$5) -> 0 | AO55: =SUMIFS(PBC_PROFIT_AND_LOSS[AccountBalance], PBC_PROFIT_AND_LOSS[Id],$L55,PBC_PROFIT_AND_LOSS[Date],AO$5) -> 0 | AP55: =SUMIFS(PBC_PROFIT_AND_LOSS[AccountBalance], PBC_PROFIT_AND_LOSS[Id],$L55,PBC_PROFIT_AND_LOSS[Date],AP$5) -> 0 | ... BD55: =SUMIFS(PBC_PROFIT_AND_LOSS[AccountBalance], PBC_PROFIT_AND_LOSS[Id],$L55,PBC_PROFIT_AND_LOSS[Date],BD$5) -> 0 | BE55: =AVERAGE(AY55:BD55) * (1 + $F55) -> 0 | BF55: =AVERAGE(AZ55:BE55) * (1 + $F55) -> 0 | BG55: =AVERAGE(BA55:BF55) * (1 + $F55) -> 0 | BH55: =AVERAGE(BB55:BG55) * (1 + $F55) -> 0 | BI55: =AVERAGE(BC55:BH55) * (1 + $F55) -> 0 | BJ55: =AVERAGE(BD55:BI55) * (1 + $F55) -> 0 | BK55: =AVERAGE(BE55:BJ55) * (1 + $F55) -> 0 | BL55: =AVERAGE(BF55:BK55) * (1 + $F55) -> 0 | ... BS55: =AVERAGE(BM55:BR55) * (1 + $F55) -> 0
D56: 80200 Other Income | E56: Average 6 months with a buffer | F56: 0.05 | G56: =IFERROR(INDEX(PBC_ACCOUNT_LIST[Drivers Section],MATCH(Drivers!L56,PBC_ACCOUNT_LIST[Id],0)),"") -> Other Income | H56: =IFERROR(INDEX(PBC_ACCOUNT_LIST[Summary Grouping],MATCH(Drivers!L56,PBC_ACCOUNT_LIST[Id],0)),"") -> Other Income | J56: =IFERROR(INDEX(PBC_ACCOUNT_LIST[Cash Flow Section],MATCH(Drivers!L56,PBC_ACCOUNT_LIST[Id],0)),"") -> 0 | K56: Account | L56: 190 | P56: =SUMIFS($AI56:$BS56,$AI$4:$BS$4,">="&P$4,$AI$5:$BS$5,"<="&P$5) -> 0 | Q56: =SUMIFS($AI56:$BS56,$AI$4:$BS$4,">="&Q$4,$AI$5:$BS$5,"<="&Q$5) -> 0 | R56: =SUMIFS($AI56:$BS56,$AI$4:$BS$4,">="&R$4,$AI$5:$BS$5,"<="&R$5) -> 0 | U56: =SUMIFS($AI56:$BS56,$AI$4:$BS$4,">="&U$4,$AI$5:$BS$5,"<="&U$5) -> 0 | V56: =SUMIFS($AI56:$BS56,$AI$4:$BS$4,">="&V$4,$AI$5:$BS$5,"<="&V$5) -> 0 | W56: =SUMIFS($AI56:$BS56,$AI$4:$BS$4,">="&W$4,$AI$5:$BS$5,"<="&W$5) -> 0 | X56: =SUMIFS($AI56:$BS56,$AI$4:$BS$4,">="&X$4,$AI$5:$BS$5,"<="&X$5) -> 0 | Y56: =SUMIFS($AI56:$BS56,$AI$4:$BS$4,">="&Y$4,$AI$5:$BS$5,"<="&Y$5) -> 0 | Z56: =SUMIFS($AI56:$BS56,$AI$4:$BS$4,">="&Z$4,$AI$5:$BS$5,"<="&Z$5) -> 0 | AA56: =SUMIFS($AI56:$BS56,$AI$4:$BS$4,">="&AA$4,$AI$5:$BS$5,"<="&AA$5) -> 0 | AB56: =SUMIFS($AI56:$BS56,$AI$4:$BS$4,">="&AB$4,$AI$5:$BS$5,"<="&AB$5) -> 0 | ... AF56: =SUMIFS($AI56:$BS56,$AI$4:$BS$4,">="&AF$4,$AI$5:$BS$5,"<="&AF$5) -> 0 | AI56: =SUMIFS(PBC_PROFIT_AND_LOSS[AccountBalance], PBC_PROFIT_AND_LOSS[Id],$L56,PBC_PROFIT_AND_LOSS[Date],AI$5) -> 0 | AJ56: =SUMIFS(PBC_PROFIT_AND_LOSS[AccountBalance], PBC_PROFIT_AND_LOSS[Id],$L56,PBC_PROFIT_AND_LOSS[Date],AJ$5) -> 0 | AK56: =SUMIFS(PBC_PROFIT_AND_LOSS[AccountBalance], PBC_PROFIT_AND_LOSS[Id],$L56,PBC_PROFIT_AND_LOSS[Date],AK$5) -> 0 | AL56: =SUMIFS(PBC_PROFIT_AND_LOSS[AccountBalance], PBC_PROFIT_AND_LOSS[Id],$L56,PBC_PROFIT_AND_LOSS[Date],AL$5) -> 0 | AM56: =SUMIFS(PBC_PROFIT_AND_LOSS[AccountBalance], PBC_PROFIT_AND_LOSS[Id],$L56,PBC_PROFIT_AND_LOSS[Date],AM$5) -> 0 | AN56: =SUMIFS(PBC_PROFIT_AND_LOSS[AccountBalance], PBC_PROFIT_AND_LOSS[Id],$L56,PBC_PROFIT_AND_LOSS[Date],AN$5) -> 0 | AO56: =SUMIFS(PBC_PROFIT_AND_LOSS[AccountBalance], PBC_PROFIT_AND_LOSS[Id],$L56,PBC_PROFIT_AND_LOSS[Date],AO$5) -> 0 | AP56: =SUMIFS(PBC_PROFIT_AND_LOSS[AccountBalance], PBC_PROFIT_AND_LOSS[Id],$L56,PBC_PROFIT_AND_LOSS[Date],AP$5) -> 0 | ... BD56: =SUMIFS(PBC_PROFIT_AND_LOSS[AccountBalance], PBC_PROFIT_AND_LOSS[Id],$L56,PBC_PROFIT_AND_LOSS[Date],BD$5) -> 0 | BE56: =AVERAGE(AY56:BD56) * (1 + $F56) -> 0 | BF56: =AVERAGE(AZ56:BE56) * (1 + $F56) -> 0 | BG56: =AVERAGE(BA56:BF56) * (1 + $F56) -> 0 | BH56: =AVERAGE(BB56:BG56) * (1 + $F56) -> 0 | BI56: =AVERAGE(BC56:BH56) * (1 + $F56) -> 0 | BJ56: =AVERAGE(BD56:BI56) * (1 + $F56) -> 0 | BK56: =AVERAGE(BE56:BJ56) * (1 + $F56) -> 0 | BL56: =AVERAGE(BF56:BK56) * (1 + $F56) -> 0 | ... BS56: =AVERAGE(BM56:BR56) * (1 + $F56) -> 0
C58: Other Expenses | P58: =SUM(P59:P62) -> 257951.5 | Q58: =SUM(Q59:Q62) -> 261767.65 | R58: =SUM(R59:R62) -> 301947.68 | U58: =SUM(U59:U62) -> 64487.5 | V58: =SUM(V59:V62) -> 64488 | W58: =SUM(W59:W62) -> 64488 | X58: =SUM(X59:X62) -> 64488 | Y58: =SUM(Y59:Y62) -> 64486.74 | Z58: =SUM(Z59:Z62) -> 64486.74 | AA58: =SUM(AA59:AA62) -> 64486.26 | AB58: =SUM(AB59:AB62) -> 68307.908 | ... AF58: =SUM(AF59:AF62) -> 80340.111 | AI58: =IF(AI$5<=LatestMonthOfActuals,SUMIFS(AI59:AI62,$K59:$K62,"Account"),SUMIFS(AI59:AI62,$K59:$K62,"<>Sub-Account")) -> 21495.5 | AJ58: =IF(AJ$5<=LatestMonthOfActuals,SUMIFS(AJ59:AJ62,$K59:$K62,"Account"),SUMIFS(AJ59:AJ62,$K59:$K62,"<>Sub-Account")) -> 21495.5 | AK58: =IF(AK$5<=LatestMonthOfActuals,SUMIFS(AK59:AK62,$K59:$K62,"Account"),SUMIFS(AK59:AK62,$K59:$K62,"<>Sub-Account")) -> 21496 | AL58: =IF(AL$5<=LatestMonthOfActuals,SUMIFS(AL59:AL62,$K59:$K62,"Account"),SUMIFS(AL59:AL62,$K59:$K62,"<>Sub-Account")) -> 21496 | AM58: =IF(AM$5<=LatestMonthOfActuals,SUMIFS(AM59:AM62,$K59:$K62,"Account"),SUMIFS(AM59:AM62,$K59:$K62,"<>Sub-Account")) -> 21496 | AN58: =IF(AN$5<=LatestMonthOfActuals,SUMIFS(AN59:AN62,$K59:$K62,"Account"),SUMIFS(AN59:AN62,$K59:$K62,"<>Sub-Account")) -> 21496 | AO58: =IF(AO$5<=LatestMonthOfActuals,SUMIFS(AO59:AO62,$K59:$K62,"Account"),SUMIFS(AO59:AO62,$K59:$K62,"<>Sub-Account")) -> 21496 | AP58: =IF(AP$5<=LatestMonthOfActuals,SUMIFS(AP59:AP62,$K59:$K62,"Account"),SUMIFS(AP59:AP62,$K59:$K62,"<>Sub-Account")) -> 21496 | ... BS58: =IF(BS$5<=LatestMonthOfActuals,SUMIFS(BS59:BS62,$K59:$K62,"Account"),SUMIFS(BS59:BS62,$K59:$K62,"<>Sub-Account")) -> 27152.156
D60: 90100 Depreciation Expense | E60: Average 6 months with a buffer | F60: 0.05 | G60: =IFERROR(INDEX(PBC_ACCOUNT_LIST[Drivers Section],MATCH(Drivers!L60,PBC_ACCOUNT_LIST[Id],0)),"") -> Other Expenses | H60: =IFERROR(INDEX(PBC_ACCOUNT_LIST[Summary Grouping],MATCH(Drivers!L60,PBC_ACCOUNT_LIST[Id],0)),"") -> Other Expenses | J60: =IFERROR(INDEX(PBC_ACCOUNT_LIST[Cash Flow Section],MATCH(Drivers!L60,PBC_ACCOUNT_LIST[Id],0)),"") -> 0 | K60: Account | L60: 191 | P60: =SUMIFS($AI60:$BS60,$AI$4:$BS$4,">="&P$4,$AI$5:$BS$5,"<="&P$5) -> 36612 | Q60: =SUMIFS($AI60:$BS60,$AI$4:$BS$4,">="&Q$4,$AI$5:$BS$5,"<="&Q$5) -> 37150.27 | R60: =SUMIFS($AI60:$BS60,$AI$4:$BS$4,">="&R$4,$AI$5:$BS$5,"<="&R$5) -> 42852.767 | U60: =SUMIFS($AI60:$BS60,$AI$4:$BS$4,">="&U$4,$AI$5:$BS$5,"<="&U$5) -> 9153 | V60: =SUMIFS($AI60:$BS60,$AI$4:$BS$4,">="&V$4,$AI$5:$BS$5,"<="&V$5) -> 9153 | W60: =SUMIFS($AI60:$BS60,$AI$4:$BS$4,">="&W$4,$AI$5:$BS$5,"<="&W$5) -> 9153 | X60: =SUMIFS($AI60:$BS60,$AI$4:$BS$4,">="&X$4,$AI$5:$BS$5,"<="&X$5) -> 9153 | Y60: =SUMIFS($AI60:$BS60,$AI$4:$BS$4,">="&Y$4,$AI$5:$BS$5,"<="&Y$5) -> 9151.98 | Z60: =SUMIFS($AI60:$BS60,$AI$4:$BS$4,">="&Z$4,$AI$5:$BS$5,"<="&Z$5) -> 9151.98 | AA60: =SUMIFS($AI60:$BS60,$AI$4:$BS$4,">="&AA$4,$AI$5:$BS$5,"<="&AA$5) -> 9151.98 | AB60: =SUMIFS($AI60:$BS60,$AI$4:$BS$4,">="&AB$4,$AI$5:$BS$5,"<="&AB$5) -> 9694.3301 | ... AF60: =SUMIFS($AI60:$BS60,$AI$4:$BS$4,">="&AF$4,$AI$5:$BS$5,"<="&AF$5) -> 11401.962 | AI60: =SUMIFS(PBC_PROFIT_AND_LOSS[AccountBalance], PBC_PROFIT_AND_LOSS[Id],$L60,PBC_PROFIT_AND_LOSS[Date],AI$5) -> 3051 | AJ60: =SUMIFS(PBC_PROFIT_AND_LOSS[AccountBalance], PBC_PROFIT_AND_LOSS[Id],$L60,PBC_PROFIT_AND_LOSS[Date],AJ$5) -> 3051 | AK60: =SUMIFS(PBC_PROFIT_AND_LOSS[AccountBalance], PBC_PROFIT_AND_LOSS[Id],$L60,PBC_PROFIT_AND_LOSS[Date],AK$5) -> 3051 | AL60: =SUMIFS(PBC_PROFIT_AND_LOSS[AccountBalance], PBC_PROFIT_AND_LOSS[Id],$L60,PBC_PROFIT_AND_LOSS[Date],AL$5) -> 3051 | AM60: =SUMIFS(PBC_PROFIT_AND_LOSS[AccountBalance], PBC_PROFIT_AND_LOSS[Id],$L60,PBC_PROFIT_AND_LOSS[Date],AM$5) -> 3051 | AN60: =SUMIFS(PBC_PROFIT_AND_LOSS[AccountBalance], PBC_PROFIT_AND_LOSS[Id],$L60,PBC_PROFIT_AND_LOSS[Date],AN$5) -> 3051 | AO60: =SUMIFS(PBC_PROFIT_AND_LOSS[AccountBalance], PBC_PROFIT_AND_LOSS[Id],$L60,PBC_PROFIT_AND_LOSS[Date],AO$5) -> 3051 | AP60: =SUMIFS(PBC_PROFIT_AND_LOSS[AccountBalance], PBC_PROFIT_AND_LOSS[Id],$L60,PBC_PROFIT_AND_LOSS[Date],AP$5) -> 3051 | ... BD60: =SUMIFS(PBC_PROFIT_AND_LOSS[AccountBalance], PBC_PROFIT_AND_LOSS[Id],$L60,PBC_PROFIT_AND_LOSS[Date],BD$5) -> 3050.66 | BE60: =AVERAGE(AY60:BD60) * (1 + $F60) -> 3203.193 | BF60: =AVERAGE(AZ60:BE60) * (1 + $F60) -> 3229.8863 | BG60: =AVERAGE(BA60:BF60) * (1 + $F60) -> 3261.2509 | BH60: =AVERAGE(BB60:BG60) * (1 + $F60) -> 3298.1043 | BI60: =AVERAGE(BC60:BH60) * (1 + $F60) -> 3341.407 | BJ60: =AVERAGE(BD60:BI60) * (1 + $F60) -> 3392.2878 | BK60: =AVERAGE(BE60:BJ60) * (1 + $F60) -> 3452.0726 | BL60: =AVERAGE(BF60:BK60) * (1 + $F60) -> 3495.6265 | ... BS60: =AVERAGE(BM60:BR60) * (1 + $F60) -> 3853.4656
D61: 90200 Interest Expense | E61: Average 6 months with a buffer | F61: 0.05 | G61: =IFERROR(INDEX(PBC_ACCOUNT_LIST[Drivers Section],MATCH(Drivers!L61,PBC_ACCOUNT_LIST[Id],0)),"") -> Other Expenses | H61: =IFERROR(INDEX(PBC_ACCOUNT_LIST[Summary Grouping],MATCH(Drivers!L61,PBC_ACCOUNT_LIST[Id],0)),"") -> Other Expenses | J61: =IFERROR(INDEX(PBC_ACCOUNT_LIST[Cash Flow Section],MATCH(Drivers!L61,PBC_ACCOUNT_LIST[Id],0)),"") -> 0 | K61: Account | L61: 192 | P61: =SUMIFS($AI61:$BS61,$AI$4:$BS$4,">="&P$4,$AI$5:$BS$5,"<="&P$5) -> 221339.5 | Q61: =SUMIFS($AI61:$BS61,$AI$4:$BS$4,">="&Q$4,$AI$5:$BS$5,"<="&Q$5) -> 224617.38 | R61: =SUMIFS($AI61:$BS61,$AI$4:$BS$4,">="&R$4,$AI$5:$BS$5,"<="&R$5) -> 259094.91 | U61: =SUMIFS($AI61:$BS61,$AI$4:$BS$4,">="&U$4,$AI$5:$BS$5,"<="&U$5) -> 55334.5 | V61: =SUMIFS($AI61:$BS61,$AI$4:$BS$4,">="&V$4,$AI$5:$BS$5,"<="&V$5) -> 55335 | W61: =SUMIFS($AI61:$BS61,$AI$4:$BS$4,">="&W$4,$AI$5:$BS$5,"<="&W$5) -> 55335 | X61: =SUMIFS($AI61:$BS61,$AI$4:$BS$4,">="&X$4,$AI$5:$BS$5,"<="&X$5) -> 55335 | Y61: =SUMIFS($AI61:$BS61,$AI$4:$BS$4,">="&Y$4,$AI$5:$BS$5,"<="&Y$5) -> 55334.76 | Z61: =SUMIFS($AI61:$BS61,$AI$4:$BS$4,">="&Z$4,$AI$5:$BS$5,"<="&Z$5) -> 55334.76 | AA61: =SUMIFS($AI61:$BS61,$AI$4:$BS$4,">="&AA$4,$AI$5:$BS$5,"<="&AA$5) -> 55334.28 | AB61: =SUMIFS($AI61:$BS61,$AI$4:$BS$4,">="&AB$4,$AI$5:$BS$5,"<="&AB$5) -> 58613.578 | ... AF61: =SUMIFS($AI61:$BS61,$AI$4:$BS$4,">="&AF$4,$AI$5:$BS$5,"<="&AF$5) -> 68938.149 | AI61: =SUMIFS(PBC_PROFIT_AND_LOSS[AccountBalance], PBC_PROFIT_AND_LOSS[Id],$L61,PBC_PROFIT_AND_LOSS[Date],AI$5) -> 18444.5 | AJ61: =SUMIFS(PBC_PROFIT_AND_LOSS[AccountBalance], PBC_PROFIT_AND_LOSS[Id],$L61,PBC_PROFIT_AND_LOSS[Date],AJ$5) -> 18444.5 | AK61: =SUMIFS(PBC_PROFIT_AND_LOSS[AccountBalance], PBC_PROFIT_AND_LOSS[Id],$L61,PBC_PROFIT_AND_LOSS[Date],AK$5) -> 18445 | AL61: =SUMIFS(PBC_PROFIT_AND_LOSS[AccountBalance], PBC_PROFIT_AND_LOSS[Id],$L61,PBC_PROFIT_AND_LOSS[Date],AL$5) -> 18445 | AM61: =SUMIFS(PBC_PROFIT_AND_LOSS[AccountBalance], PBC_PROFIT_AND_LOSS[Id],$L61,PBC_PROFIT_AND_LOSS[Date],AM$5) -> 18445 | AN61: =SUMIFS(PBC_PROFIT_AND_LOSS[AccountBalance], PBC_PROFIT_AND_LOSS[Id],$L61,PBC_PROFIT_AND_LOSS[Date],AN$5) -> 18445 | AO61: =SUMIFS(PBC_PROFIT_AND_LOSS[AccountBalance], PBC_PROFIT_AND_LOSS[Id],$L61,PBC_PROFIT_AND_LOSS[Date],AO$5) -> 18445 | AP61: =SUMIFS(PBC_PROFIT_AND_LOSS[AccountBalance], PBC_PROFIT_AND_LOSS[Id],$L61,PBC_PROFIT_AND_LOSS[Date],AP$5) -> 18445 | ... BD61: =SUMIFS(PBC_PROFIT_AND_LOSS[AccountBalance], PBC_PROFIT_AND_LOSS[Id],$L61,PBC_PROFIT_AND_LOSS[Date],BD$5) -> 18444.76 | BE61: =AVERAGE(AY61:BD61) * (1 + $F61) -> 19367.082 | BF61: =AVERAGE(AZ61:BE61) * (1 + $F61) -> 19528.446 | BG61: =AVERAGE(BA61:BF61) * (1 + $F61) -> 19718.049 | BH61: =AVERAGE(BB61:BG61) * (1 + $F61) -> 19940.875 | BI61: =AVERAGE(BC61:BH61) * (1 + $F61) -> 20202.695 | BJ61: =AVERAGE(BD61:BI61) * (1 + $F61) -> 20510.334 | BK61: =AVERAGE(BE61:BJ61) * (1 + $F61) -> 20871.809 | BL61: =AVERAGE(BF61:BK61) * (1 + $F61) -> 21135.137 | ... BS61: =AVERAGE(BM61:BR61) * (1 + $F61) -> 23298.69
C63: Net Other Income | P63: =P53-P58 -> -257951.5 | Q63: =Q53-Q58 -> -261767.65 | R63: =R53-R58 -> -301947.68 | U63: =U53-U58 -> -64487.5 | V63: =V53-V58 -> -64488 | W63: =W53-W58 -> -64488 | X63: =X53-X58 -> -64488 | Y63: =Y53-Y58 -> -64486.74 | Z63: =Z53-Z58 -> -64486.74 | AA63: =AA53-AA58 -> -64486.26 | AB63: =AB53-AB58 -> -68307.908 | ... AF63: =AF53-AF58 -> -80340.111 | AI63: =AI53-AI58 -> -21495.5 | AJ63: =AJ53-AJ58 -> -21495.5 | AK63: =AK53-AK58 -> -21496 | AL63: =AL53-AL58 -> -21496 | AM63: =AM53-AM58 -> -21496 | AN63: =AN53-AN58 -> -21496 | AO63: =AO53-AO58 -> -21496 | AP63: =AP53-AP58 -> -21496 | ... BS63: =BS53-BS58 -> -27152.156
C65: Net Income | P65: =P51+P63 -> -1553482.5 | Q65: =Q51+Q63 -> -2565316.1 | R65: =R51+R63 -> -3195451.7 | U65: =U51+U63 -> -277494 | V65: =V51+V63 -> -353145 | W65: =W51+W63 -> -445187 | X65: =X51+X63 -> -477656.5 | Y65: =Y51+Y63 -> -542782.23 | Z65: =Z51+Z63 -> -610775.53 | AA65: =AA51+AA63 -> -704448.25 | AB65: =AB51+AB63 -> -707310.08 | ... AF65: =AF51+AF63 -> -849220.88 | AI65: =AI51+AI63 -> -124185 | AJ65: =AJ51+AJ63 -> -72804.5 | AK65: =AK51+AK63 -> -129320 | AL65: =AL51+AL63 -> -75369.5 | AM65: =AM51+AM63 -> -134710.5 | AN65: =AN51+AN63 -> -78062.5 | AO65: =AO51+AO63 -> -140372 | AP65: =AP51+AP63 -> -146316 | ... BS65: =BS51+BS63 -> -287163.19
B67: Balance Sheet
C68: Assets | P68: =SUM(P69:P83) -> 5635256 | Q68: =SUM(Q69:Q83) -> 2375957.4 | R68: =SUM(R69:R83) -> -819494.28 | U68: =SUM(U69:U83) -> 8171102.5 | V68: =SUM(V69:V83) -> 7469968.5 | W68: =SUM(W69:W83) -> 6585150.5 | X68: =SUM(X69:X83) -> 5635256 | Y68: =SUM(Y69:Y83) -> 4554849.7 | Z68: =SUM(Z69:Z83) -> 3331755.9 | AA68: =SUM(AA69:AA83) -> 1926390.3 | AB68: =SUM(AB69:AB83) -> 2375957.4 | ... AF68: =SUM(AF69:AF83) -> -819494.28 | AI68: =IF(AI$5<=LatestMonthOfActuals,SUMIFS(AI69:AI83,$K69:$K83,"Account"),SUMIFS(AI69:AI83,$K69:$K83,"<>Sub-Account")) -> 4443756 | AJ68: =IF(AJ$5<=LatestMonthOfActuals,SUMIFS(AJ69:AJ83,$K69:$K83,"Account"),SUMIFS(AJ69:AJ83,$K69:$K83,"<>Sub-Account")) -> 4370951.5 | AK68: =IF(AK$5<=LatestMonthOfActuals,SUMIFS(AK69:AK83,$K69:$K83,"Account"),SUMIFS(AK69:AK83,$K69:$K83,"<>Sub-Account")) -> 4241631.5 | AL68: =IF(AL$5<=LatestMonthOfActuals,SUMIFS(AL69:AL83,$K69:$K83,"Account"),SUMIFS(AL69:AL83,$K69:$K83,"<>Sub-Account")) -> 4166262 | AM68: =IF(AM$5<=LatestMonthOfActuals,SUMIFS(AM69:AM83,$K69:$K83,"Account"),SUMIFS(AM69:AM83,$K69:$K83,"<>Sub-Account")) -> 4031551.5 | AN68: =IF(AN$5<=LatestMonthOfActuals,SUMIFS(AN69:AN83,$K69:$K83,"Account"),SUMIFS(AN69:AN83,$K69:$K83,"<>Sub-Account")) -> 3953489 | AO68: =IF(AO$5<=LatestMonthOfActuals,SUMIFS(AO69:AO83,$K69:$K83,"Account"),SUMIFS(AO69:AO83,$K69:$K83,"<>Sub-Account")) -> 3813117 | AP68: =IF(AP$5<=LatestMonthOfActuals,SUMIFS(AP69:AP83,$K69:$K83,"Account"),SUMIFS(AP69:AP83,$K69:$K83,"<>Sub-Account")) -> 3666801 | ... BS68: =IF(BS$5<=LatestMonthOfActuals,SUMIFS(BS69:BS83,$K69:$K83,"Account"),SUMIFS(BS69:BS83,$K69:$K83,"<>Sub-Account")) -> -819494.28
D70: 1000000 American Bank | J70: =IFERROR(INDEX(PBC_ACCOUNT_LIST[Cash Flow Section],MATCH(Drivers!L70,PBC_ACCOUNT_LIST[Id],0)),"") -> 0 | L70: 1150040000 | P70: =INDEX($AI70:$BS70,MATCH(P$5,$AI$5:$BS$5,0)) -> 2744982.5 | Q70: =INDEX($AI70:$BS70,MATCH(Q$5,$AI$5:$BS$5,0)) -> 0 | R70: =INDEX($AI70:$BS70,MATCH(R$5,$AI$5:$BS$5,0)) -> 0 | U70: =INDEX($AI70:$BS70,MATCH(U$5,$AI$5:$BS$5,0)) -> 4004840.5 | V70: =INDEX($AI70:$BS70,MATCH(V$5,$AI$5:$BS$5,0)) -> 3656851.5 | W70: =INDEX($AI70:$BS70,MATCH(W$5,$AI$5:$BS$5,0)) -> 3217220.5 | X70: =INDEX($AI70:$BS70,MATCH(X$5,$AI$5:$BS$5,0)) -> 2744982.5 | Y70: =INDEX($AI70:$BS70,MATCH(Y$5,$AI$5:$BS$5,0)) -> 2207358.5 | Z70: =INDEX($AI70:$BS70,MATCH(Z$5,$AI$5:$BS$5,0)) -> 1594040.1 | AA70: =INDEX($AI70:$BS70,MATCH(AA$5,$AI$5:$BS$5,0)) -> 893122.77 | AB70: =INDEX($AI70:$BS70,MATCH(AB$5,$AI$5:$BS$5,0)) -> 0 | ... AF70: =INDEX($AI70:$BS70,MATCH(AF$5,$AI$5:$BS$5,0)) -> 0 | AI70: =SUMIFS(PBC_BALANCE_SHEET[AccountBalance], PBC_BALANCE_SHEET[Id],$L70,PBC_BALANCE_SHEET[Date],AI$5) -> 4285000.5 | AJ70: =SUMIFS(PBC_BALANCE_SHEET[AccountBalance], PBC_BALANCE_SHEET[Id],$L70,PBC_BALANCE_SHEET[Date],AJ$5) -> 4191288.5 | AK70: =SUMIFS(PBC_BALANCE_SHEET[AccountBalance], PBC_BALANCE_SHEET[Id],$L70,PBC_BALANCE_SHEET[Date],AK$5) -> 4076334.5 | AL70: =SUMIFS(PBC_BALANCE_SHEET[AccountBalance], PBC_BALANCE_SHEET[Id],$L70,PBC_BALANCE_SHEET[Date],AL$5) -> 4004840.5 | AM70: =SUMIFS(PBC_BALANCE_SHEET[AccountBalance], PBC_BALANCE_SHEET[Id],$L70,PBC_BALANCE_SHEET[Date],AM$5) -> 3870793.5 | AN70: =SUMIFS(PBC_BALANCE_SHEET[AccountBalance], PBC_BALANCE_SHEET[Id],$L70,PBC_BALANCE_SHEET[Date],AN$5) -> 3794994.5 | AO70: =SUMIFS(PBC_BALANCE_SHEET[AccountBalance], PBC_BALANCE_SHEET[Id],$L70,PBC_BALANCE_SHEET[Date],AO$5) -> 3656851.5 | AP70: =SUMIFS(PBC_BALANCE_SHEET[AccountBalance], PBC_BALANCE_SHEET[Id],$L70,PBC_BALANCE_SHEET[Date],AP$5) -> 3512188.5 | ... BD70: =SUMIFS(PBC_BALANCE_SHEET[AccountBalance], PBC_BALANCE_SHEET[Id],$L70,PBC_BALANCE_SHEET[Date],BD$5) -> 893122.77 | BE70: 0 | BF70: 0 | BG70: 0 | BH70: 0 | BI70: 0 | BJ70: 0 | BK70: 0 | BL70: 0 | BM70: 0 | BN70: 0 | BO70: 0 | BP70: 0 | BQ70: 0 | BR70: 0 | BS70: 0
D71: Total Bank Accounts | E71: formula | G71: Assets | H71: Cash | K71: Account | L71: sum(Bank Accounts) | P71: =INDEX($AI71:$BS71,MATCH(P$5,$AI$5:$BS$5,0)) -> 2744982.5 | Q71: =INDEX($AI71:$BS71,MATCH(Q$5,$AI$5:$BS$5,0)) -> 2245812.7 | R71: =INDEX($AI71:$BS71,MATCH(R$5,$AI$5:$BS$5,0)) -> -949639 | U71: =INDEX($AI71:$BS71,MATCH(U$5,$AI$5:$BS$5,0)) -> 4004840.5 | V71: =INDEX($AI71:$BS71,MATCH(V$5,$AI$5:$BS$5,0)) -> 3656851.5 | W71: =INDEX($AI71:$BS71,MATCH(W$5,$AI$5:$BS$5,0)) -> 3217220.5 | X71: =INDEX($AI71:$BS71,MATCH(X$5,$AI$5:$BS$5,0)) -> 2744982.5 | Y71: =INDEX($AI71:$BS71,MATCH(Y$5,$AI$5:$BS$5,0)) -> 2207358.5 | Z71: =INDEX($AI71:$BS71,MATCH(Z$5,$AI$5:$BS$5,0)) -> 1594040.1 | AA71: =INDEX($AI71:$BS71,MATCH(AA$5,$AI$5:$BS$5,0)) -> 893122.77 | AB71: =INDEX($AI71:$BS71,MATCH(AB$5,$AI$5:$BS$5,0)) -> 2245812.7 | ... AF71: =INDEX($AI71:$BS71,MATCH(AF$5,$AI$5:$BS$5,0)) -> -949639 | AI71: =SUMIFS(AI$72:AI$103,$G$72:$G$103,"Liabilities")+SUMIFS(AI$72:AI$103,$G$72:$G$103,"Owners Equity")-SUMIFS(AI$72:AI$103,$G$72:$G$103,"Assets") -> 4285000.5 | AJ71: =SUMIFS(AJ$72:AJ$103,$G$72:$G$103,"Liabilities")+SUMIFS(AJ$72:AJ$103,$G$72:$G$103,"Owners Equity")-SUMIFS(AJ$72:AJ$103,$G$72:$G$103,"Assets") -> 4191288.5 | AK71: =SUMIFS(AK$72:AK$103,$G$72:$G$103,"Liabilities")+SUMIFS(AK$72:AK$103,$G$72:$G$103,"Owners Equity")-SUMIFS(AK$72:AK$103,$G$72:$G$103,"Assets") -> 4076334.5 | AL71: =SUMIFS(AL$72:AL$103,$G$72:$G$103,"Liabilities")+SUMIFS(AL$72:AL$103,$G$72:$G$103,"Owners Equity")-SUMIFS(AL$72:AL$103,$G$72:$G$103,"Assets") -> 4004840.5 | AM71: =SUMIFS(AM$72:AM$103,$G$72:$G$103,"Liabilities")+SUMIFS(AM$72:AM$103,$G$72:$G$103,"Owners Equity")-SUMIFS(AM$72:AM$103,$G$72:$G$103,"Assets") -> 3870793.5 | AN71: =SUMIFS(AN$72:AN$103,$G$72:$G$103,"Liabilities")+SUMIFS(AN$72:AN$103,$G$72:$G$103,"Owners Equity")-SUMIFS(AN$72:AN$103,$G$72:$G$103,"Assets") -> 3794994.5 | AO71: =SUMIFS(AO$72:AO$103,$G$72:$G$103,"Liabilities")+SUMIFS(AO$72:AO$103,$G$72:$G$103,"Owners Equity")-SUMIFS(AO$72:AO$103,$G$72:$G$103,"Assets") -> 3656851.5 | AP71: =SUMIFS(AP$72:AP$103,$G$72:$G$103,"Liabilities")+SUMIFS(AP$72:AP$103,$G$72:$G$103,"Owners Equity")-SUMIFS(AP$72:AP$103,$G$72:$G$103,"Assets") -> 3512188.5 | ... BS71: =SUMIFS(BS$72:BS$103,$G$72:$G$103,"Liabilities")+SUMIFS(BS$72:BS$103,$G$72:$G$103,"Owners Equity")-SUMIFS(BS$72:BS$103,$G$72:$G$103,"Assets") -> -949639
D72: 10200 Accounts receivable (A/R) | E72: Prior Month | G72: =IFERROR(INDEX(PBC_ACCOUNT_LIST[Drivers Section],MATCH(Drivers!L72,PBC_ACCOUNT_LIST[Id],0)),"") -> Assets | H72: =IFERROR(INDEX(PBC_ACCOUNT_LIST[Summary Grouping],MATCH(Drivers!L72,PBC_ACCOUNT_LIST[Id],0)),"") -> Accounts Receivable | I72: =H72 -> Accounts Receivable | J72: =IFERROR(INDEX(PBC_ACCOUNT_LIST[Cash Flow Section],MATCH(Drivers!L72,PBC_ACCOUNT_LIST[Id],0)),"") -> Cash from Operating Activities | K72: Account | L72: 8 | P72: =INDEX($AI72:$BS72,MATCH(P$5,$AI$5:$BS$5,0)) -> 52314 | Q72: =INDEX($AI72:$BS72,MATCH(Q$5,$AI$5:$BS$5,0)) -> 63923.66 | R72: =INDEX($AI72:$BS72,MATCH(R$5,$AI$5:$BS$5,0)) -> 63923.66 | U72: =INDEX($AI72:$BS72,MATCH(U$5,$AI$5:$BS$5,0)) -> 40987 | V72: =INDEX($AI72:$BS72,MATCH(V$5,$AI$5:$BS$5,0)) -> 44983 | W72: =INDEX($AI72:$BS72,MATCH(W$5,$AI$5:$BS$5,0)) -> 48580 | X72: =INDEX($AI72:$BS72,MATCH(X$5,$AI$5:$BS$5,0)) -> 52314 | Y72: =INDEX($AI72:$BS72,MATCH(Y$5,$AI$5:$BS$5,0)) -> 56307.77 | Z72: =INDEX($AI72:$BS72,MATCH(Z$5,$AI$5:$BS$5,0)) -> 69302.55 | AA72: =INDEX($AI72:$BS72,MATCH(AA$5,$AI$5:$BS$5,0)) -> 73923.66 | AB72: =INDEX($AI72:$BS72,MATCH(AB$5,$AI$5:$BS$5,0)) -> 63923.66 | ... AF72: =INDEX($AI72:$BS72,MATCH(AF$5,$AI$5:$BS$5,0)) -> 63923.66 | AI72: =SUMIFS(PBC_BALANCE_SHEET[AccountBalance], PBC_BALANCE_SHEET[Id],$L72,PBC_BALANCE_SHEET[Date],AI$5) -> 34169 | AJ72: =SUMIFS(PBC_BALANCE_SHEET[AccountBalance], PBC_BALANCE_SHEET[Id],$L72,PBC_BALANCE_SHEET[Date],AJ$5) -> 41127 | AK72: =SUMIFS(PBC_BALANCE_SHEET[AccountBalance], PBC_BALANCE_SHEET[Id],$L72,PBC_BALANCE_SHEET[Date],AK$5) -> 41812 | AL72: =SUMIFS(PBC_BALANCE_SHEET[AccountBalance], PBC_BALANCE_SHEET[Id],$L72,PBC_BALANCE_SHEET[Date],AL$5) -> 40987 | AM72: =SUMIFS(PBC_BALANCE_SHEET[AccountBalance], PBC_BALANCE_SHEET[Id],$L72,PBC_BALANCE_SHEET[Date],AM$5) -> 43374 | AN72: =SUMIFS(PBC_BALANCE_SHEET[AccountBalance], PBC_BALANCE_SHEET[Id],$L72,PBC_BALANCE_SHEET[Date],AN$5) -> 44161 | AO72: =SUMIFS(PBC_BALANCE_SHEET[AccountBalance], PBC_BALANCE_SHEET[Id],$L72,PBC_BALANCE_SHEET[Date],AO$5) -> 44983 | AP72: =SUMIFS(PBC_BALANCE_SHEET[AccountBalance], PBC_BALANCE_SHEET[Id],$L72,PBC_BALANCE_SHEET[Date],AP$5) -> 46381 | ... BD72: =SUMIFS(PBC_BALANCE_SHEET[AccountBalance], PBC_BALANCE_SHEET[Id],$L72,PBC_BALANCE_SHEET[Date],BD$5) -> 73923.66 | BE72: =BD72-10000 -> 63923.66 | BF72: =BE72 -> 63923.66 | BG72: =BF72 -> 63923.66 | BH72: =BG72 -> 63923.66 | BI72: =BH72 -> 63923.66 | BJ72: =BI72 -> 63923.66 | BK72: =BJ72 -> 63923.66 | BL72: =BK72 -> 63923.66 | BM72: =BL72 -> 63923.66 | ... BS72: =BR72 -> 63923.66
D73: 10310 Prepaid Expenses | E73: Prior Month | G73: =IFERROR(INDEX(PBC_ACCOUNT_LIST[Drivers Section],MATCH(Drivers!L73,PBC_ACCOUNT_LIST[Id],0)),"") -> Assets | H73: =IFERROR(INDEX(PBC_ACCOUNT_LIST[Summary Grouping],MATCH(Drivers!L73,PBC_ACCOUNT_LIST[Id],0)),"") -> Current Assets | I73: =H73 -> Current Assets | J73: =IFERROR(INDEX(PBC_ACCOUNT_LIST[Cash Flow Section],MATCH(Drivers!L73,PBC_ACCOUNT_LIST[Id],0)),"") -> Cash from Operating Activities | K73: Account | L73: 193 | P73: =INDEX($AI73:$BS73,MATCH(P$5,$AI$5:$BS$5,0)) -> 1119.5 | Q73: =INDEX($AI73:$BS73,MATCH(Q$5,$AI$5:$BS$5,0)) -> 1119.5 | R73: =INDEX($AI73:$BS73,MATCH(R$5,$AI$5:$BS$5,0)) -> 1119.5 | U73: =INDEX($AI73:$BS73,MATCH(U$5,$AI$5:$BS$5,0)) -> 1119.5 | V73: =INDEX($AI73:$BS73,MATCH(V$5,$AI$5:$BS$5,0)) -> 1119.5 | W73: =INDEX($AI73:$BS73,MATCH(W$5,$AI$5:$BS$5,0)) -> 1119.5 | X73: =INDEX($AI73:$BS73,MATCH(X$5,$AI$5:$BS$5,0)) -> 1119.5 | Y73: =INDEX($AI73:$BS73,MATCH(Y$5,$AI$5:$BS$5,0)) -> 1119.5 | Z73: =INDEX($AI73:$BS73,MATCH(Z$5,$AI$5:$BS$5,0)) -> 1119.5 | AA73: =INDEX($AI73:$BS73,MATCH(AA$5,$AI$5:$BS$5,0)) -> 1119.5 | AB73: =INDEX($AI73:$BS73,MATCH(AB$5,$AI$5:$BS$5,0)) -> 1119.5 | ... AF73: =INDEX($AI73:$BS73,MATCH(AF$5,$AI$5:$BS$5,0)) -> 1119.5 | AI73: =SUMIFS(PBC_BALANCE_SHEET[AccountBalance], PBC_BALANCE_SHEET[Id],$L73,PBC_BALANCE_SHEET[Date],AI$5) -> 1119.5 | AJ73: =SUMIFS(PBC_BALANCE_SHEET[AccountBalance], PBC_BALANCE_SHEET[Id],$L73,PBC_BALANCE_SHEET[Date],AJ$5) -> 1119.5 | AK73: =SUMIFS(PBC_BALANCE_SHEET[AccountBalance], PBC_BALANCE_SHEET[Id],$L73,PBC_BALANCE_SHEET[Date],AK$5) -> 1119.5 | AL73: =SUMIFS(PBC_BALANCE_SHEET[AccountBalance], PBC_BALANCE_SHEET[Id],$L73,PBC_BALANCE_SHEET[Date],AL$5) -> 1119.5 | AM73: =SUMIFS(PBC_BALANCE_SHEET[AccountBalance], PBC_BALANCE_SHEET[Id],$L73,PBC_BALANCE_SHEET[Date],AM$5) -> 1119.5 | AN73: =SUMIFS(PBC_BALANCE_SHEET[AccountBalance], PBC_BALANCE_SHEET[Id],$L73,PBC_BALANCE_SHEET[Date],AN$5) -> 1119.5 | AO73: =SUMIFS(PBC_BALANCE_SHEET[AccountBalance], PBC_BALANCE_SHEET[Id],$L73,PBC_BALANCE_SHEET[Date],AO$5) -> 1119.5 | AP73: =SUMIFS(PBC_BALANCE_SHEET[AccountBalance], PBC_BALANCE_SHEET[Id],$L73,PBC_BALANCE_SHEET[Date],AP$5) -> 1119.5 | ... BD73: =SUMIFS(PBC_BALANCE_SHEET[AccountBalance], PBC_BALANCE_SHEET[Id],$L73,PBC_BALANCE_SHEET[Date],BD$5) -> 1119.5 | BE73: =BD73 -> 1119.5 | BF73: =BE73 -> 1119.5 | BG73: =BF73 -> 1119.5 | BH73: =BG73 -> 1119.5 | BI73: =BH73 -> 1119.5 | BJ73: =BI73 -> 1119.5 | BK73: =BJ73 -> 1119.5 | BL73: =BK73 -> 1119.5 | ... BS73: =BR73 -> 1119.5
D74: 10320 Security Deposit | E74: Prior Month | G74: =IFERROR(INDEX(PBC_ACCOUNT_LIST[Drivers Section],MATCH(Drivers!L74,PBC_ACCOUNT_LIST[Id],0)),"") -> Assets | H74: =IFERROR(INDEX(PBC_ACCOUNT_LIST[Summary Grouping],MATCH(Drivers!L74,PBC_ACCOUNT_LIST[Id],0)),"") -> Current Assets | I74: =H74 -> Current Assets | J74: =IFERROR(INDEX(PBC_ACCOUNT_LIST[Cash Flow Section],MATCH(Drivers!L74,PBC_ACCOUNT_LIST[Id],0)),"") -> Cash from Operating Activities | K74: Account | L74: 150 | P74: =INDEX($AI74:$BS74,MATCH(P$5,$AI$5:$BS$5,0)) -> 25000 | Q74: =INDEX($AI74:$BS74,MATCH(Q$5,$AI$5:$BS$5,0)) -> 25000 | R74: =INDEX($AI74:$BS74,MATCH(R$5,$AI$5:$BS$5,0)) -> 25000 | U74: =INDEX($AI74:$BS74,MATCH(U$5,$AI$5:$BS$5,0)) -> 25000 | V74: =INDEX($AI74:$BS74,MATCH(V$5,$AI$5:$BS$5,0)) -> 25000 | W74: =INDEX($AI74:$BS74,MATCH(W$5,$AI$5:$BS$5,0)) -> 25000 | X74: =INDEX($AI74:$BS74,MATCH(X$5,$AI$5:$BS$5,0)) -> 25000 | Y74: =INDEX($AI74:$BS74,MATCH(Y$5,$AI$5:$BS$5,0)) -> 25000 | Z74: =INDEX($AI74:$BS74,MATCH(Z$5,$AI$5:$BS$5,0)) -> 25000 | AA74: =INDEX($AI74:$BS74,MATCH(AA$5,$AI$5:$BS$5,0)) -> 25000 | AB74: =INDEX($AI74:$BS74,MATCH(AB$5,$AI$5:$BS$5,0)) -> 25000 | ... AF74: =INDEX($AI74:$BS74,MATCH(AF$5,$AI$5:$BS$5,0)) -> 25000 | AI74: =SUMIFS(PBC_BALANCE_SHEET[AccountBalance], PBC_BALANCE_SHEET[Id],$L74,PBC_BALANCE_SHEET[Date],AI$5) -> 25000 | AJ74: =SUMIFS(PBC_BALANCE_SHEET[AccountBalance], PBC_BALANCE_SHEET[Id],$L74,PBC_BALANCE_SHEET[Date],AJ$5) -> 25000 | AK74: =SUMIFS(PBC_BALANCE_SHEET[AccountBalance], PBC_BALANCE_SHEET[Id],$L74,PBC_BALANCE_SHEET[Date],AK$5) -> 25000 | AL74: =SUMIFS(PBC_BALANCE_SHEET[AccountBalance], PBC_BALANCE_SHEET[Id],$L74,PBC_BALANCE_SHEET[Date],AL$5) -> 25000 | AM74: =SUMIFS(PBC_BALANCE_SHEET[AccountBalance], PBC_BALANCE_SHEET[Id],$L74,PBC_BALANCE_SHEET[Date],AM$5) -> 25000 | AN74: =SUMIFS(PBC_BALANCE_SHEET[AccountBalance], PBC_BALANCE_SHEET[Id],$L74,PBC_BALANCE_SHEET[Date],AN$5) -> 25000 | AO74: =SUMIFS(PBC_BALANCE_SHEET[AccountBalance], PBC_BALANCE_SHEET[Id],$L74,PBC_BALANCE_SHEET[Date],AO$5) -> 25000 | AP74: =SUMIFS(PBC_BALANCE_SHEET[AccountBalance], PBC_BALANCE_SHEET[Id],$L74,PBC_BALANCE_SHEET[Date],AP$5) -> 25000 | ... BD74: =SUMIFS(PBC_BALANCE_SHEET[AccountBalance], PBC_BALANCE_SHEET[Id],$L74,PBC_BALANCE_SHEET[Date],BD$5) -> 25000 | BE74: =BD74 -> 25000 | BF74: =BE74 -> 25000 | BG74: =BF74 -> 25000 | BH74: =BG74 -> 25000 | BI74: =BH74 -> 25000 | BJ74: =BI74 -> 25000 | BK74: =BJ74 -> 25000 | BL74: =BK74 -> 25000 | ... BS74: =BR74 -> 25000
D75: 10330 Due to/from Officers | E75: Prior Month | G75: =IFERROR(INDEX(PBC_ACCOUNT_LIST[Drivers Section],MATCH(Drivers!L75,PBC_ACCOUNT_LIST[Id],0)),"") -> Assets | H75: =IFERROR(INDEX(PBC_ACCOUNT_LIST[Summary Grouping],MATCH(Drivers!L75,PBC_ACCOUNT_LIST[Id],0)),"") -> Current Assets | I75: =H75 -> Current Assets | J75: =IFERROR(INDEX(PBC_ACCOUNT_LIST[Cash Flow Section],MATCH(Drivers!L75,PBC_ACCOUNT_LIST[Id],0)),"") -> Cash from Operating Activities | K75: Account | L75: 151 | P75: =INDEX($AI75:$BS75,MATCH(P$5,$AI$5:$BS$5,0)) -> 0 | Q75: =INDEX($AI75:$BS75,MATCH(Q$5,$AI$5:$BS$5,0)) -> 0 | R75: =INDEX($AI75:$BS75,MATCH(R$5,$AI$5:$BS$5,0)) -> 0 | U75: =INDEX($AI75:$BS75,MATCH(U$5,$AI$5:$BS$5,0)) -> 0 | V75: =INDEX($AI75:$BS75,MATCH(V$5,$AI$5:$BS$5,0)) -> 0 | W75: =INDEX($AI75:$BS75,MATCH(W$5,$AI$5:$BS$5,0)) -> 0 | X75: =INDEX($AI75:$BS75,MATCH(X$5,$AI$5:$BS$5,0)) -> 0 | Y75: =INDEX($AI75:$BS75,MATCH(Y$5,$AI$5:$BS$5,0)) -> 0 | Z75: =INDEX($AI75:$BS75,MATCH(Z$5,$AI$5:$BS$5,0)) -> 0 | AA75: =INDEX($AI75:$BS75,MATCH(AA$5,$AI$5:$BS$5,0)) -> 0 | AB75: =INDEX($AI75:$BS75,MATCH(AB$5,$AI$5:$BS$5,0)) -> 0 | ... AF75: =INDEX($AI75:$BS75,MATCH(AF$5,$AI$5:$BS$5,0)) -> 0 | AI75: =SUMIFS(PBC_BALANCE_SHEET[AccountBalance], PBC_BALANCE_SHEET[Id],$L75,PBC_BALANCE_SHEET[Date],AI$5) -> 0 | AJ75: =SUMIFS(PBC_BALANCE_SHEET[AccountBalance], PBC_BALANCE_SHEET[Id],$L75,PBC_BALANCE_SHEET[Date],AJ$5) -> 0 | AK75: =SUMIFS(PBC_BALANCE_SHEET[AccountBalance], PBC_BALANCE_SHEET[Id],$L75,PBC_BALANCE_SHEET[Date],AK$5) -> 0 | AL75: =SUMIFS(PBC_BALANCE_SHEET[AccountBalance], PBC_BALANCE_SHEET[Id],$L75,PBC_BALANCE_SHEET[Date],AL$5) -> 0 | AM75: =SUMIFS(PBC_BALANCE_SHEET[AccountBalance], PBC_BALANCE_SHEET[Id],$L75,PBC_BALANCE_SHEET[Date],AM$5) -> 0 | AN75: =SUMIFS(PBC_BALANCE_SHEET[AccountBalance], PBC_BALANCE_SHEET[Id],$L75,PBC_BALANCE_SHEET[Date],AN$5) -> 0 | AO75: =SUMIFS(PBC_BALANCE_SHEET[AccountBalance], PBC_BALANCE_SHEET[Id],$L75,PBC_BALANCE_SHEET[Date],AO$5) -> 0 | AP75: =SUMIFS(PBC_BALANCE_SHEET[AccountBalance], PBC_BALANCE_SHEET[Id],$L75,PBC_BALANCE_SHEET[Date],AP$5) -> 0 | ... BD75: =SUMIFS(PBC_BALANCE_SHEET[AccountBalance], PBC_BALANCE_SHEET[Id],$L75,PBC_BALANCE_SHEET[Date],BD$5) -> 0 | BE75: =BD75 -> 0 | BF75: =BE75 -> 0 | BG75: =BF75 -> 0 | BH75: =BG75 -> 0 | BI75: =BH75 -> 0 | BJ75: =BI75 -> 0 | BK75: =BJ75 -> 0 | BL75: =BK75 -> 0 | ... BS75: =BR75 -> 0
D76: Inventory Asset | E76: Prior Month | G76: =IFERROR(INDEX(PBC_ACCOUNT_LIST[Drivers Section],MATCH(Drivers!L76,PBC_ACCOUNT_LIST[Id],0)),"") -> Assets | H76: =IFERROR(INDEX(PBC_ACCOUNT_LIST[Summary Grouping],MATCH(Drivers!L76,PBC_ACCOUNT_LIST[Id],0)),"") -> Current Assets | I76: =H76 -> Current Assets | J76: =IFERROR(INDEX(PBC_ACCOUNT_LIST[Cash Flow Section],MATCH(Drivers!L76,PBC_ACCOUNT_LIST[Id],0)),"") -> Cash from Operating Activities | K76: Account | L76: 42 | P76: =INDEX($AI76:$BS76,MATCH(P$5,$AI$5:$BS$5,0)) -> 0 | Q76: =INDEX($AI76:$BS76,MATCH(Q$5,$AI$5:$BS$5,0)) -> 700 | R76: =INDEX($AI76:$BS76,MATCH(R$5,$AI$5:$BS$5,0)) -> 700 | U76: =INDEX($AI76:$BS76,MATCH(U$5,$AI$5:$BS$5,0)) -> 0 | V76: =INDEX($AI76:$BS76,MATCH(V$5,$AI$5:$BS$5,0)) -> 0 | W76: =INDEX($AI76:$BS76,MATCH(W$5,$AI$5:$BS$5,0)) -> 0 | X76: =INDEX($AI76:$BS76,MATCH(X$5,$AI$5:$BS$5,0)) -> 0 | Y76: =INDEX($AI76:$BS76,MATCH(Y$5,$AI$5:$BS$5,0)) -> 0 | Z76: =INDEX($AI76:$BS76,MATCH(Z$5,$AI$5:$BS$5,0)) -> -300 | AA76: =INDEX($AI76:$BS76,MATCH(AA$5,$AI$5:$BS$5,0)) -> 700 | AB76: =INDEX($AI76:$BS76,MATCH(AB$5,$AI$5:$BS$5,0)) -> 700 | ... AF76: =INDEX($AI76:$BS76,MATCH(AF$5,$AI$5:$BS$5,0)) -> 700 | AI76: =SUMIFS(PBC_BALANCE_SHEET[AccountBalance], PBC_BALANCE_SHEET[Id],$L76,PBC_BALANCE_SHEET[Date],AI$5) -> 0 | AJ76: =SUMIFS(PBC_BALANCE_SHEET[AccountBalance], PBC_BALANCE_SHEET[Id],$L76,PBC_BALANCE_SHEET[Date],AJ$5) -> 0 | AK76: =SUMIFS(PBC_BALANCE_SHEET[AccountBalance], PBC_BALANCE_SHEET[Id],$L76,PBC_BALANCE_SHEET[Date],AK$5) -> 0 | AL76: =SUMIFS(PBC_BALANCE_SHEET[AccountBalance], PBC_BALANCE_SHEET[Id],$L76,PBC_BALANCE_SHEET[Date],AL$5) -> 0 | AM76: =SUMIFS(PBC_BALANCE_SHEET[AccountBalance], PBC_BALANCE_SHEET[Id],$L76,PBC_BALANCE_SHEET[Date],AM$5) -> 0 | AN76: =SUMIFS(PBC_BALANCE_SHEET[AccountBalance], PBC_BALANCE_SHEET[Id],$L76,PBC_BALANCE_SHEET[Date],AN$5) -> 0 | AO76: =SUMIFS(PBC_BALANCE_SHEET[AccountBalance], PBC_BALANCE_SHEET[Id],$L76,PBC_BALANCE_SHEET[Date],AO$5) -> 0 | AP76: =SUMIFS(PBC_BALANCE_SHEET[AccountBalance], PBC_BALANCE_SHEET[Id],$L76,PBC_BALANCE_SHEET[Date],AP$5) -> 0 | ... BD76: =SUMIFS(PBC_BALANCE_SHEET[AccountBalance], PBC_BALANCE_SHEET[Id],$L76,PBC_BALANCE_SHEET[Date],BD$5) -> 700 | BE76: =BD76 -> 700 | BF76: =BE76 -> 700 | BG76: =BF76 -> 700 | BH76: =BG76 -> 700 | BI76: =BH76 -> 700 | BJ76: =BI76 -> 700 | BK76: =BJ76 -> 700 | BL76: =BK76 -> 700 | ... BS76: =BR76 -> 700
D77: 10410 Computers | E77: Prior Month | G77: =IFERROR(INDEX(PBC_ACCOUNT_LIST[Drivers Section],MATCH(Drivers!L77,PBC_ACCOUNT_LIST[Id],0)),"") -> Assets | H77: =IFERROR(INDEX(PBC_ACCOUNT_LIST[Summary Grouping],MATCH(Drivers!L77,PBC_ACCOUNT_LIST[Id],0)),"") -> Fixed Assets | I77: =H77 -> Fixed Assets | J77: =IFERROR(INDEX(PBC_ACCOUNT_LIST[Cash Flow Section],MATCH(Drivers!L77,PBC_ACCOUNT_LIST[Id],0)),"") -> Cash From Investing Activities | K77: Account | L77: 152 | P77: =INDEX($AI77:$BS77,MATCH(P$5,$AI$5:$BS$5,0)) -> 15000 | Q77: =INDEX($AI77:$BS77,MATCH(Q$5,$AI$5:$BS$5,0)) -> 15000 | R77: =INDEX($AI77:$BS77,MATCH(R$5,$AI$5:$BS$5,0)) -> 15000 | U77: =INDEX($AI77:$BS77,MATCH(U$5,$AI$5:$BS$5,0)) -> 15000 | V77: =INDEX($AI77:$BS77,MATCH(V$5,$AI$5:$BS$5,0)) -> 15000 | W77: =INDEX($AI77:$BS77,MATCH(W$5,$AI$5:$BS$5,0)) -> 15000 | X77: =INDEX($AI77:$BS77,MATCH(X$5,$AI$5:$BS$5,0)) -> 15000 | Y77: =INDEX($AI77:$BS77,MATCH(Y$5,$AI$5:$BS$5,0)) -> 15000 | Z77: =INDEX($AI77:$BS77,MATCH(Z$5,$AI$5:$BS$5,0)) -> 15000 | AA77: =INDEX($AI77:$BS77,MATCH(AA$5,$AI$5:$BS$5,0)) -> 15000 | AB77: =INDEX($AI77:$BS77,MATCH(AB$5,$AI$5:$BS$5,0)) -> 15000 | ... AF77: =INDEX($AI77:$BS77,MATCH(AF$5,$AI$5:$BS$5,0)) -> 15000 | AI77: =SUMIFS(PBC_BALANCE_SHEET[AccountBalance], PBC_BALANCE_SHEET[Id],$L77,PBC_BALANCE_SHEET[Date],AI$5) -> 10000 | AJ77: =SUMIFS(PBC_BALANCE_SHEET[AccountBalance], PBC_BALANCE_SHEET[Id],$L77,PBC_BALANCE_SHEET[Date],AJ$5) -> 15000 | AK77: =SUMIFS(PBC_BALANCE_SHEET[AccountBalance], PBC_BALANCE_SHEET[Id],$L77,PBC_BALANCE_SHEET[Date],AK$5) -> 15000 | AL77: =SUMIFS(PBC_BALANCE_SHEET[AccountBalance], PBC_BALANCE_SHEET[Id],$L77,PBC_BALANCE_SHEET[Date],AL$5) -> 15000 | AM77: =SUMIFS(PBC_BALANCE_SHEET[AccountBalance], PBC_BALANCE_SHEET[Id],$L77,PBC_BALANCE_SHEET[Date],AM$5) -> 15000 | AN77: =SUMIFS(PBC_BALANCE_SHEET[AccountBalance], PBC_BALANCE_SHEET[Id],$L77,PBC_BALANCE_SHEET[Date],AN$5) -> 15000 | AO77: =SUMIFS(PBC_BALANCE_SHEET[AccountBalance], PBC_BALANCE_SHEET[Id],$L77,PBC_BALANCE_SHEET[Date],AO$5) -> 15000 | AP77: =SUMIFS(PBC_BALANCE_SHEET[AccountBalance], PBC_BALANCE_SHEET[Id],$L77,PBC_BALANCE_SHEET[Date],AP$5) -> 15000 | ... BD77: =SUMIFS(PBC_BALANCE_SHEET[AccountBalance], PBC_BALANCE_SHEET[Id],$L77,PBC_BALANCE_SHEET[Date],BD$5) -> 15000 | BE77: =BD77 -> 15000 | BF77: =BE77 -> 15000 | BG77: =BF77 -> 15000 | BH77: =BG77 -> 15000 | BI77: =BH77 -> 15000 | BJ77: =BI77 -> 15000 | BK77: =BJ77 -> 15000 | BL77: =BK77 -> 15000 | ... BS77: =BR77 -> 15000
D78: 10420 Furniture | E78: Prior Month | G78: =IFERROR(INDEX(PBC_ACCOUNT_LIST[Drivers Section],MATCH(Drivers!L78,PBC_ACCOUNT_LIST[Id],0)),"") -> Assets | H78: =IFERROR(INDEX(PBC_ACCOUNT_LIST[Summary Grouping],MATCH(Drivers!L78,PBC_ACCOUNT_LIST[Id],0)),"") -> Fixed Assets | I78: =H78 -> Fixed Assets | J78: =IFERROR(INDEX(PBC_ACCOUNT_LIST[Cash Flow Section],MATCH(Drivers!L78,PBC_ACCOUNT_LIST[Id],0)),"") -> Cash From Investing Activities | K78: Account | L78: 153 | P78: =INDEX($AI78:$BS78,MATCH(P$5,$AI$5:$BS$5,0)) -> 35000 | Q78: =INDEX($AI78:$BS78,MATCH(Q$5,$AI$5:$BS$5,0)) -> 35000 | R78: =INDEX($AI78:$BS78,MATCH(R$5,$AI$5:$BS$5,0)) -> 35000 | U78: =INDEX($AI78:$BS78,MATCH(U$5,$AI$5:$BS$5,0)) -> 35000 | V78: =INDEX($AI78:$BS78,MATCH(V$5,$AI$5:$BS$5,0)) -> 35000 | W78: =INDEX($AI78:$BS78,MATCH(W$5,$AI$5:$BS$5,0)) -> 35000 | X78: =INDEX($AI78:$BS78,MATCH(X$5,$AI$5:$BS$5,0)) -> 35000 | Y78: =INDEX($AI78:$BS78,MATCH(Y$5,$AI$5:$BS$5,0)) -> 35000 | Z78: =INDEX($AI78:$BS78,MATCH(Z$5,$AI$5:$BS$5,0)) -> 35000 | AA78: =INDEX($AI78:$BS78,MATCH(AA$5,$AI$5:$BS$5,0)) -> 35000 | AB78: =INDEX($AI78:$BS78,MATCH(AB$5,$AI$5:$BS$5,0)) -> 35000 | ... AF78: =INDEX($AI78:$BS78,MATCH(AF$5,$AI$5:$BS$5,0)) -> 35000 | AI78: =SUMIFS(PBC_BALANCE_SHEET[AccountBalance], PBC_BALANCE_SHEET[Id],$L78,PBC_BALANCE_SHEET[Date],AI$5) -> 35000 | AJ78: =SUMIFS(PBC_BALANCE_SHEET[AccountBalance], PBC_BALANCE_SHEET[Id],$L78,PBC_BALANCE_SHEET[Date],AJ$5) -> 45000 | AK78: =SUMIFS(PBC_BALANCE_SHEET[AccountBalance], PBC_BALANCE_SHEET[Id],$L78,PBC_BALANCE_SHEET[Date],AK$5) -> 35000 | AL78: =SUMIFS(PBC_BALANCE_SHEET[AccountBalance], PBC_BALANCE_SHEET[Id],$L78,PBC_BALANCE_SHEET[Date],AL$5) -> 35000 | AM78: =SUMIFS(PBC_BALANCE_SHEET[AccountBalance], PBC_BALANCE_SHEET[Id],$L78,PBC_BALANCE_SHEET[Date],AM$5) -> 35000 | AN78: =SUMIFS(PBC_BALANCE_SHEET[AccountBalance], PBC_BALANCE_SHEET[Id],$L78,PBC_BALANCE_SHEET[Date],AN$5) -> 35000 | AO78: =SUMIFS(PBC_BALANCE_SHEET[AccountBalance], PBC_BALANCE_SHEET[Id],$L78,PBC_BALANCE_SHEET[Date],AO$5) -> 35000 | AP78: =SUMIFS(PBC_BALANCE_SHEET[AccountBalance], PBC_BALANCE_SHEET[Id],$L78,PBC_BALANCE_SHEET[Date],AP$5) -> 35000 | ... BD78: =SUMIFS(PBC_BALANCE_SHEET[AccountBalance], PBC_BALANCE_SHEET[Id],$L78,PBC_BALANCE_SHEET[Date],BD$5) -> 35000 | BE78: =BD78 -> 35000 | BF78: =BE78 -> 35000 | BG78: =BF78 -> 35000 | BH78: =BG78 -> 35000 | BI78: =BH78 -> 35000 | BJ78: =BI78 -> 35000 | BK78: =BJ78 -> 35000 | BL78: =BK78 -> 35000 | ... BS78: =BR78 -> 35000
D79: 10430 Equipment | E79: Prior Month | G79: =IFERROR(INDEX(PBC_ACCOUNT_LIST[Drivers Section],MATCH(Drivers!L79,PBC_ACCOUNT_LIST[Id],0)),"") -> Assets | H79: =IFERROR(INDEX(PBC_ACCOUNT_LIST[Summary Grouping],MATCH(Drivers!L79,PBC_ACCOUNT_LIST[Id],0)),"") -> Fixed Assets | I79: =H79 -> Fixed Assets | J79: =IFERROR(INDEX(PBC_ACCOUNT_LIST[Cash Flow Section],MATCH(Drivers!L79,PBC_ACCOUNT_LIST[Id],0)),"") -> Cash From Investing Activities | K79: Account | L79: 154 | P79: =INDEX($AI79:$BS79,MATCH(P$5,$AI$5:$BS$5,0)) -> 8000 | Q79: =INDEX($AI79:$BS79,MATCH(Q$5,$AI$5:$BS$5,0)) -> 8000 | R79: =INDEX($AI79:$BS79,MATCH(R$5,$AI$5:$BS$5,0)) -> 8000 | U79: =INDEX($AI79:$BS79,MATCH(U$5,$AI$5:$BS$5,0)) -> 8000 | V79: =INDEX($AI79:$BS79,MATCH(V$5,$AI$5:$BS$5,0)) -> 8000 | W79: =INDEX($AI79:$BS79,MATCH(W$5,$AI$5:$BS$5,0)) -> 8000 | X79: =INDEX($AI79:$BS79,MATCH(X$5,$AI$5:$BS$5,0)) -> 8000 | Y79: =INDEX($AI79:$BS79,MATCH(Y$5,$AI$5:$BS$5,0)) -> 8000 | Z79: =INDEX($AI79:$BS79,MATCH(Z$5,$AI$5:$BS$5,0)) -> 8000 | AA79: =INDEX($AI79:$BS79,MATCH(AA$5,$AI$5:$BS$5,0)) -> 8000 | AB79: =INDEX($AI79:$BS79,MATCH(AB$5,$AI$5:$BS$5,0)) -> 8000 | ... AF79: =INDEX($AI79:$BS79,MATCH(AF$5,$AI$5:$BS$5,0)) -> 8000 | AI79: =SUMIFS(PBC_BALANCE_SHEET[AccountBalance], PBC_BALANCE_SHEET[Id],$L79,PBC_BALANCE_SHEET[Date],AI$5) -> 8000 | AJ79: =SUMIFS(PBC_BALANCE_SHEET[AccountBalance], PBC_BALANCE_SHEET[Id],$L79,PBC_BALANCE_SHEET[Date],AJ$5) -> 10000 | AK79: =SUMIFS(PBC_BALANCE_SHEET[AccountBalance], PBC_BALANCE_SHEET[Id],$L79,PBC_BALANCE_SHEET[Date],AK$5) -> 8000 | AL79: =SUMIFS(PBC_BALANCE_SHEET[AccountBalance], PBC_BALANCE_SHEET[Id],$L79,PBC_BALANCE_SHEET[Date],AL$5) -> 8000 | AM79: =SUMIFS(PBC_BALANCE_SHEET[AccountBalance], PBC_BALANCE_SHEET[Id],$L79,PBC_BALANCE_SHEET[Date],AM$5) -> 8000 | AN79: =SUMIFS(PBC_BALANCE_SHEET[AccountBalance], PBC_BALANCE_SHEET[Id],$L79,PBC_BALANCE_SHEET[Date],AN$5) -> 8000 | AO79: =SUMIFS(PBC_BALANCE_SHEET[AccountBalance], PBC_BALANCE_SHEET[Id],$L79,PBC_BALANCE_SHEET[Date],AO$5) -> 8000 | AP79: =SUMIFS(PBC_BALANCE_SHEET[AccountBalance], PBC_BALANCE_SHEET[Id],$L79,PBC_BALANCE_SHEET[Date],AP$5) -> 8000 | ... BD79: =SUMIFS(PBC_BALANCE_SHEET[AccountBalance], PBC_BALANCE_SHEET[Id],$L79,PBC_BALANCE_SHEET[Date],BD$5) -> 8000 | BE79: =BD79 -> 8000 | BF79: =BE79 -> 8000 | BG79: =BF79 -> 8000 | BH79: =BG79 -> 8000 | BI79: =BH79 -> 8000 | BJ79: =BI79 -> 8000 | BK79: =BJ79 -> 8000 | BL79: =BK79 -> 8000 | ... BS79: =BR79 -> 8000
D80: 10440 Accumulated Depreciation | E80: Prior Month | G80: =IFERROR(INDEX(PBC_ACCOUNT_LIST[Drivers Section],MATCH(Drivers!L80,PBC_ACCOUNT_LIST[Id],0)),"") -> Assets | H80: =IFERROR(INDEX(PBC_ACCOUNT_LIST[Summary Grouping],MATCH(Drivers!L80,PBC_ACCOUNT_LIST[Id],0)),"") -> Fixed Assets | I80: Depreciation & Amortization | J80: =IFERROR(INDEX(PBC_ACCOUNT_LIST[Cash Flow Section],MATCH(Drivers!L80,PBC_ACCOUNT_LIST[Id],0)),"") -> Cash From Operating Activities | K80: Account | L80: 194 | P80: =INDEX($AI80:$BS80,MATCH(P$5,$AI$5:$BS$5,0)) -> -51811.5 | Q80: =INDEX($AI80:$BS80,MATCH(Q$5,$AI$5:$BS$5,0)) -> -79267.44 | R80: =INDEX($AI80:$BS80,MATCH(R$5,$AI$5:$BS$5,0)) -> -79267.44 | U80: =INDEX($AI80:$BS80,MATCH(U$5,$AI$5:$BS$5,0)) -> -24354 | V80: =INDEX($AI80:$BS80,MATCH(V$5,$AI$5:$BS$5,0)) -> -33506 | W80: =INDEX($AI80:$BS80,MATCH(W$5,$AI$5:$BS$5,0)) -> -42659 | X80: =INDEX($AI80:$BS80,MATCH(X$5,$AI$5:$BS$5,0)) -> -51811.5 | Y80: =INDEX($AI80:$BS80,MATCH(Y$5,$AI$5:$BS$5,0)) -> -60963.48 | Z80: =INDEX($AI80:$BS80,MATCH(Z$5,$AI$5:$BS$5,0)) -> -70115.46 | AA80: =INDEX($AI80:$BS80,MATCH(AA$5,$AI$5:$BS$5,0)) -> -79267.44 | AB80: =INDEX($AI80:$BS80,MATCH(AB$5,$AI$5:$BS$5,0)) -> -79267.44 | ... AF80: =INDEX($AI80:$BS80,MATCH(AF$5,$AI$5:$BS$5,0)) -> -79267.44 | AI80: =SUMIFS(PBC_BALANCE_SHEET[AccountBalance], PBC_BALANCE_SHEET[Id],$L80,PBC_BALANCE_SHEET[Date],AI$5) -> -15202 | AJ80: =SUMIFS(PBC_BALANCE_SHEET[AccountBalance], PBC_BALANCE_SHEET[Id],$L80,PBC_BALANCE_SHEET[Date],AJ$5) -> -18252.5 | AK80: =SUMIFS(PBC_BALANCE_SHEET[AccountBalance], PBC_BALANCE_SHEET[Id],$L80,PBC_BALANCE_SHEET[Date],AK$5) -> -21303.5 | AL80: =SUMIFS(PBC_BALANCE_SHEET[AccountBalance], PBC_BALANCE_SHEET[Id],$L80,PBC_BALANCE_SHEET[Date],AL$5) -> -24354 | AM80: =SUMIFS(PBC_BALANCE_SHEET[AccountBalance], PBC_BALANCE_SHEET[Id],$L80,PBC_BALANCE_SHEET[Date],AM$5) -> -27404.5 | AN80: =SUMIFS(PBC_BALANCE_SHEET[AccountBalance], PBC_BALANCE_SHEET[Id],$L80,PBC_BALANCE_SHEET[Date],AN$5) -> -30455 | AO80: =SUMIFS(PBC_BALANCE_SHEET[AccountBalance], PBC_BALANCE_SHEET[Id],$L80,PBC_BALANCE_SHEET[Date],AO$5) -> -33506 | AP80: =SUMIFS(PBC_BALANCE_SHEET[AccountBalance], PBC_BALANCE_SHEET[Id],$L80,PBC_BALANCE_SHEET[Date],AP$5) -> -36557 | ... BD80: =SUMIFS(PBC_BALANCE_SHEET[AccountBalance], PBC_BALANCE_SHEET[Id],$L80,PBC_BALANCE_SHEET[Date],BD$5) -> -79267.44 | BE80: =BD80 -> -79267.44 | BF80: =BE80 -> -79267.44 | BG80: =BF80 -> -79267.44 | BH80: =BG80 -> -79267.44 | BI80: =BH80 -> -79267.44 | BJ80: =BI80 -> -79267.44 | BK80: =BJ80 -> -79267.44 | BL80: =BK80 -> -79267.44 | ... BS80: =BR80 -> -79267.44
D81: Copyrights | E81: Prior Month | G81: =IFERROR(INDEX(PBC_ACCOUNT_LIST[Drivers Section],MATCH(Drivers!L81,PBC_ACCOUNT_LIST[Id],0)),"") -> Assets | H81: =IFERROR(INDEX(PBC_ACCOUNT_LIST[Summary Grouping],MATCH(Drivers!L81,PBC_ACCOUNT_LIST[Id],0)),"") -> Fixed Assets | I81: =H81 -> Fixed Assets | J81: =IFERROR(INDEX(PBC_ACCOUNT_LIST[Cash Flow Section],MATCH(Drivers!L81,PBC_ACCOUNT_LIST[Id],0)),"") -> Cash From Investing Activities | K81: Account | L81: 60 | P81: =INDEX($AI81:$BS81,MATCH(P$5,$AI$5:$BS$5,0)) -> 52718 | Q81: =INDEX($AI81:$BS81,MATCH(Q$5,$AI$5:$BS$5,0)) -> 52718 | R81: =INDEX($AI81:$BS81,MATCH(R$5,$AI$5:$BS$5,0)) -> 52718 | U81: =INDEX($AI81:$BS81,MATCH(U$5,$AI$5:$BS$5,0)) -> 52718 | V81: =INDEX($AI81:$BS81,MATCH(V$5,$AI$5:$BS$5,0)) -> 52718 | W81: =INDEX($AI81:$BS81,MATCH(W$5,$AI$5:$BS$5,0)) -> 52718 | X81: =INDEX($AI81:$BS81,MATCH(X$5,$AI$5:$BS$5,0)) -> 52718 | Y81: =INDEX($AI81:$BS81,MATCH(Y$5,$AI$5:$BS$5,0)) -> 52718 | Z81: =INDEX($AI81:$BS81,MATCH(Z$5,$AI$5:$BS$5,0)) -> 52718 | AA81: =INDEX($AI81:$BS81,MATCH(AA$5,$AI$5:$BS$5,0)) -> 52718 | AB81: =INDEX($AI81:$BS81,MATCH(AB$5,$AI$5:$BS$5,0)) -> 52718 | ... AF81: =INDEX($AI81:$BS81,MATCH(AF$5,$AI$5:$BS$5,0)) -> 52718 | AI81: =SUMIFS(PBC_BALANCE_SHEET[AccountBalance], PBC_BALANCE_SHEET[Id],$L81,PBC_BALANCE_SHEET[Date],AI$5) -> 52718 | AJ81: =SUMIFS(PBC_BALANCE_SHEET[AccountBalance], PBC_BALANCE_SHEET[Id],$L81,PBC_BALANCE_SHEET[Date],AJ$5) -> 52718 | AK81: =SUMIFS(PBC_BALANCE_SHEET[AccountBalance], PBC_BALANCE_SHEET[Id],$L81,PBC_BALANCE_SHEET[Date],AK$5) -> 52718 | AL81: =SUMIFS(PBC_BALANCE_SHEET[AccountBalance], PBC_BALANCE_SHEET[Id],$L81,PBC_BALANCE_SHEET[Date],AL$5) -> 52718 | AM81: =SUMIFS(PBC_BALANCE_SHEET[AccountBalance], PBC_BALANCE_SHEET[Id],$L81,PBC_BALANCE_SHEET[Date],AM$5) -> 52718 | AN81: =SUMIFS(PBC_BALANCE_SHEET[AccountBalance], PBC_BALANCE_SHEET[Id],$L81,PBC_BALANCE_SHEET[Date],AN$5) -> 52718 | AO81: =SUMIFS(PBC_BALANCE_SHEET[AccountBalance], PBC_BALANCE_SHEET[Id],$L81,PBC_BALANCE_SHEET[Date],AO$5) -> 52718 | AP81: =SUMIFS(PBC_BALANCE_SHEET[AccountBalance], PBC_BALANCE_SHEET[Id],$L81,PBC_BALANCE_SHEET[Date],AP$5) -> 52718 | ... BD81: =SUMIFS(PBC_BALANCE_SHEET[AccountBalance], PBC_BALANCE_SHEET[Id],$L81,PBC_BALANCE_SHEET[Date],BD$5) -> 52718 | BE81: =BD81 -> 52718 | BF81: =BE81 -> 52718 | BG81: =BF81 -> 52718 | BH81: =BG81 -> 52718 | BI81: =BH81 -> 52718 | BJ81: =BI81 -> 52718 | BK81: =BJ81 -> 52718 | BL81: =BK81 -> 52718 | ... BS81: =BR81 -> 52718
